Workbook
Name _______DAT10: #REF!
Name _______DAT10: #REF!
Name _______DAT11: #REF!
Name _______DAT11: #REF!
Name _______DAT12: #REF!
Name _______DAT12: #REF!
Name _______DAT13: #REF!
Name _______DAT14: #REF!
Name _______DAT15: #REF!
Name _______DAT16: #REF!
Name _______DAT17: #REF!
Name _______DAT18: #REF!
Name _______DAT19: #REF!
Name _______DAT2: #REF!
Name _______DAT20: #REF!
Name _______DAT22: #REF!
Name _______DAT23: #REF!
Name _______DAT24: #REF!
Name _______DAT26: #REF!
Name _______DAT27: #REF!
Name _______DAT28: #REF!
Name _______DAT29: #REF!
Name _______DAT3: #REF!
Name _______DAT30: #REF!
Name _______DAT31: #REF!
Name _______DAT32: #REF!
Name _______DAT33: #REF!
Name _______DAT34: #REF!
Name _______DAT35: #REF!
Name _______DAT36: #REF!
Name _______DAT37: #REF!
Name _______DAT38: #REF!
Name _______DAT39: #REF!
Name _______DAT4: #REF!
Name _______DAT40: #REF!
Name _______DAT41: #REF!
Name _______DAT42: #REF!
Name _______DAT43: #REF!
Name _______DAT44: #REF!
Name _______DAT45: #REF!
Name _______DAT46: #REF!
Name _______DAT47: #REF!
Name _______DAT48: #REF!
Name _______DAT5: #REF!
Name _______DAT6: #REF!
Name _______DAT7: #REF!
Name _______DAT8: #REF!
Name _______DAT9: #REF!
Name ______DAT1: #REF!
Name ______DAT10: #REF!
Name ______DAT11: #REF!
Name ______DAT12: #REF!
Name ______DAT13: #REF!
Name ______DAT14: #REF!
Name ______DAT15: #REF!
Name ______DAT16: #REF!
Name ______DAT17: #REF!
Name ______DAT18: #REF!
Name ______DAT19: #REF!
Name ______DAT2: #REF!

Sheet Cover

Sheet 1. General Facility Information
A1: Setting the organizational boundaries of the Hojeon Limited _ General information of the business site
B3: Gernal Infromation of Business Site | G3: Target Business Establishments for Reporting: Business establishments of entities (subsidiaries + affiliates) that are reported as affiliates in the business report of Hojeon Limited. Business establishments where Hojeon Limited has actual operational control, such as those leased, even if not directly owned by Hojeon Limited.
B5: Basic Infromation of Business Site | G5: 사업장 상세정보 | J5: 온실가스 활동 데이터 관리 현황2)
B6: No. | C6: Name of Entity | D6: Name of Facility | E6: Country of Business Location | F6: Business Type | G6: Lease Status | H6: Detailed Address | I6: Area | J6: Greenhouse Gas Emission Sources Under Management3) | K6: Current Status of Management Tools | L6: Department in Charge (Name of the Responsible Person) | M6: Contact Information
B7: 1 | C7: HOJEON LIMITED | D7: HOJEON LIMITED Co., Ltd | E7: Korea | F7: Head Quarters | G7: Ownership | H7: 11th and 12th Floors, Shinhwa Building, 19 Mapo-daero, Mapo-gu, Seoul, Korea | I7: 2,430.2㎡ - 4F(Part), 9F, 11F, 12F, 13F | J7: Scope 1: Vehicles (Mobile Combustion) Scope 2: Electricity, Water Supply | K7: Other (Insert a note if 'Other' is selected) | L7: 박달원 부장, 이소영 과장 | M7: dwpark1@hojeon.co.kr , sylee4@hojeon.co.kr
B8: 2 | C8: PT. KAHOINDAH CITRAGARMENT | D8: KAHOINDAH CITRAGARMENT | E8: Indonesia | F8: Clothing manufacturing factory | G8: Ownership | H8: JI.Bali Blok D16, Kawasan Berikat Nusantara Cilincing Cakung Jakarta Utara, Indonesia | I8: 14,100 M2 (facility) | J8: Scope 1 + Scope 2 | K8: Other (Insert a note if 'Other' is selected) | L8: MS. REZA | M8: reza@kaho.co.id
B9: 3 | C9: PT. YONGJIN JAVASUKA GARMENT | D9: PT. YONGJIN JAVASUKA GARMENT (1공장) | E9: Indonesia | F9: Clothing manufacturing factory | G9: Ownership | H9: JL. RAYA SILLIWANGI KM 35 DESA BUNDA KEC. CICURUG - KAB. SUKABUMI 43359 | I9: Yongjin 1공장 : 21,605 SQM | J9: Scope 1 + Scope 2 | K9: Other (Insert a note if 'Other' is selected) | L9: MS. ANITA | M9: anita@yongjin.co.id
B10: 5 | C10: PT. YONGJIN JAVASUKA GARMENT | D10: PT. YONGJIN JAVASUKA GARMENT (2,3공장) | E10: Indonesia | F10: Clothing manufacturing factory | G10: Ownership | I10: Yongjin 2공장 : 63,266 SQM Yongjin 3공장 : 38,300 SQM
B11: 4 | C11: PT. HJL INDO NETWORKS | D11: PT. HJL INDO NETWORKS | E11: Indonesia | F11: Sales corporation | G11: Ownership | H11: Graha Surveyor Indonesia 17th fl. 1701 Jl. Jend. Gatot Subroto Kav. 56 Jakarta 12950, Indonesia | I11: 1,304 M2 | J11: Scope 1 + Scope 2 (Didn't managed) | K11: Other (Insert a note if 'Other' is selected) | L11: Mr. Fahmi | M11: fahmi@hjl.co.id
B12: 5 | C12: PT.HOGA REKSA GARMENT | D12: PT.HOGA REKSA GARMENT | E12: Indonesia | F12: Clothing manufacturing factory | G12: Ownership | H12: Jl.Raya Leles KM. 13 Kp. Tutugan RT001/ RW. 002 Desa Haruman, Kecamatan Leles, Kabupaten Garut, Jawa Barat. 44152, Indonesia T. +62 0262 2457677 | I12: 125,052 m2 (land) 51,968 m2 (facility) | J12: Scope 1 + Scope 2 | K12: Other (Insert a note if 'Other' is selected) | L12: mr. Andri | M12: andri@hoga.co.id
B13: 6 | C13: ㈜엠파파 | D13: MFAFA Co., Ltd | E13: Korea | F13: Head Quarters | G13: Lease | H13: 13rd Floor, Shinhwa Building, 19 Mapo-daero, Mapo-gu, Seoul, Korea | I13: 66㎡ - 13F(Part) | J13: Scope 2 : Electricty, Water supply | K13: Other (Insert a note if 'Other' is selected) | L13: 박달원 부장, 이소영 과장 | M13: dwpark1@hojeon.co.kr , sylee4@hojeon.co.kr
B17: [Reference] Classification of Greenhouse Gas Emission Sources
B19: Part | D19: Definition | F19: Target
B20: Scope 1 (Direct Emission) | D20: Green House Gas Emissions from sources owned or controlled by the company | F20: Boilers, Furnaces, Turbines, Transportation vehicles, Incinerators Greenhouse gas-emitting chemical processes
B21: Scope 2 (Indirect Enission) | D21: Green House Gas Emissions from the generation of purchased electricity and steam consumed by the company | F21: Electricity and steam purchased or brought into the organizational boundary of the company through other means
B22: Scope 3 (Other Indirect Emissions) | D22: Green House Gas Emissions from activities related to the company, but occurring at facilities not owned or controlled by the company | F22: - Leased assets, Franchises, Outsourced activities - Use of sold products and services - Waste disposal

Sheet 2-1. Quantitative data_Location
B1: HOJEON LIMITED Scope 1,2 Emissions (tCO2eq) (2022~2024) / Location-based
B3: HOJEON LIMITED Annual GHG Emissions for Scope 1&2
B5: 구분 | C5: Scope 1+2 | D5: Scope 1 | H5: Scope 2
B6: Data Collection Year | C6: Total GHG Emissions (tCO2eq) | D6: Fuel Consumption (kg) | E6: Energy Consumption (MJ) | F6: GHG Emissions (tCO2eq) | G6: GHG Emissions Share (%) | H6: Energy Purchased (MJ) | I6: GHG Emissions (tCO2eq) | J6: GHG Emissions Share (%)
B7: 2022 | C7: =F7+I7 -> 17488.362 | D7: =SUMIF('3-1. (Raw data) Scope 1'!$Y:$Y,'2-1. Quantitative data_Location'!$B7,'3-1. (Raw data) Scope 1'!$AR:$AR) -> 1753340.4 | E7: =SUMIF('3-1. (Raw data) Scope 1'!$Y:$Y,'2-1. Quantitative data_Location'!$B7,'3-1. (Raw data) Scope 1'!$AS:$AS) -> 46194039 | F7: =SUMIF('3-1. (Raw data) Scope 1'!$Y:$Y,'2-1. Quantitative data_Location'!$B7,'3-1. (Raw data) Scope 1'!$AT:$AT) -> 5807.3723 | G7: =F7/$C7 -> 0.33207069 | H7: =SUMIF('3-2. (Raw data) Scope2_Location'!$AD:$AD,'2-1. Quantitative data_Location'!$B7,'3-2. (Raw data) Scope2_Location'!$AT:$AT) -> 49010653 | I7: =SUMIF('3-2. (Raw data) Scope2_Location'!$AD:$AD,'2-1. Quantitative data_Location'!$B7,'3-2. (Raw data) Scope2_Location'!$AY:$AY) -> 11680.989 | J7: =I7/$C7 -> 0.66792931
B8: 2023 | C8: =F8+I8 -> 17676.947 | D8: =SUMIF('3-1. (Raw data) Scope 1'!$Y:$Y,'2-1. Quantitative data_Location'!$B8,'3-1. (Raw data) Scope 1'!$AR:$AR) -> 1670455.1 | E8: =SUMIF('3-1. (Raw data) Scope 1'!$Y:$Y,'2-1. Quantitative data_Location'!$B8,'3-1. (Raw data) Scope 1'!$AS:$AS) -> 45214988 | F8: =SUMIF('3-1. (Raw data) Scope 1'!$Y:$Y,'2-1. Quantitative data_Location'!$B8,'3-1. (Raw data) Scope 1'!$AT:$AT) -> 5472.6179 | G8: =F8/$C8 -> 0.30959067 | H8: =SUMIF('3-2. (Raw data) Scope2_Location'!$AD:$AD,'2-1. Quantitative data_Location'!$B8,'3-2. (Raw data) Scope2_Location'!$AT:$AT) -> 51149870 | I8: =SUMIF('3-2. (Raw data) Scope2_Location'!$AD:$AD,'2-1. Quantitative data_Location'!$B8,'3-2. (Raw data) Scope2_Location'!$AY:$AY) -> 12204.329 | J8: =I8/$C8 -> 0.69040933
B9: 2024 | C9: =F9+I9 -> 19499.897 | D9: =SUMIF('3-1. (Raw data) Scope 1'!$Y:$Y,'2-1. Quantitative data_Location'!$B9,'3-1. (Raw data) Scope 1'!$AR:$AR) -> 1648587.9 | E9: =SUMIF('3-1. (Raw data) Scope 1'!$Y:$Y,'2-1. Quantitative data_Location'!$B9,'3-1. (Raw data) Scope 1'!$AS:$AS) -> 43372620 | F9: =SUMIF('3-1. (Raw data) Scope 1'!$Y:$Y,'2-1. Quantitative data_Location'!$B9,'3-1. (Raw data) Scope 1'!$AT:$AT) -> 5415.5677 | G9: =F9/$C9 -> 0.27772289 | H9: =SUMIF('3-2. (Raw data) Scope2_Location'!$AD:$AD,'2-1. Quantitative data_Location'!$B9,'3-2. (Raw data) Scope2_Location'!$AT:$AT) -> 58948770 | I9: =SUMIF('3-2. (Raw data) Scope2_Location'!$AD:$AD,'2-1. Quantitative data_Location'!$B9,'3-2. (Raw data) Scope2_Location'!$AY:$AY) -> 14084.329 | J9: =I9/$C9 -> 0.72227711
B11: HOJEON LIMITED GHG Emissions for Scope 1&2 by Facility
B13: 구분 | C13: Scope 1 + Scope 2 | F13: Scope 1 | I13: Scope 2
B14: Name of Facility | C14: 2022 | D14: 2023 | E14: 2024 | F14: 2022 | G14: 2023 | H14: 2024 | I14: 2022 | J14: 2023 | K14: 2024
B15: Total | C15: =SUM(C16:C22) -> 17488.362 | D15: =SUM(D16:D22) -> 17676.947 | E15: =SUM(E16:E22) -> 19499.897 | F15: =SUM(F16:F22) -> 5807.3723 | G15: =SUM(G16:G22) -> 5472.6179 | H15: =SUM(H16:H22) -> 5415.5677 | I15: =SUM(I16:I22) -> 11680.989 | J15: =SUM(J16:J22) -> 12204.329 | K15: =SUM(K16:K22) -> 14084.329
B16: HOJEON LIMITED Co., Ltd | C16: =F16+I16 -> 235.99585 | D16: =G16+J16 -> 239.15711 | E16: =H16+K16 -> 242.87393 | F16: =D47 -> 49.986937 | G16: =D57 -> 59.95623 | H16: =D67 -> 58.215798 | I16: =K47 -> 186.00891 | J16: =K57 -> 179.20088 | K16: =K67 -> 184.65813
B17: KAHOINDAH CITRAGARMENT | C17: =F17+I17 -> 2538.3389 | D17: =G17+J17 -> 2386.1475 | E17: =H17+K17 -> 2205.9967 | F17: =D48 -> 1092.0335 | G17: =D58 -> 1049.9841 | H17: =D68 -> 877.44929 | I17: =K48 -> 1446.3054 | J17: =K58 -> 1336.1634 | K17: =K68 -> 1328.5474
B18: PT. YONGJIN JAVASUKA GARMENT (1공장) | C18: =F18+I18 -> 2622.4944 | D18: =G18+J18 -> 2504.7999 | E18: =H18+K18 -> 2680.1847 | F18: =D49 -> 1478.1033 | G18: =D59 -> 1377.433 | H18: =D69 -> 1334.7981 | I18: =K49 -> 1144.391 | J18: =K59 -> 1127.3669 | K18: =K69 -> 1345.3866
B19: PT. YONGJIN JAVASUKA GARMENT (2,3공장) | C19: =F19+I19 -> 9864.3183 | D19: =G19+J19 -> 10307.784 | E19: =H19+K19 -> 11041.413 | F19: =D50 -> 3051.6824 | G19: =D60 -> 2809.4554 | H19: =D70 -> 2918.3443 | I19: =K50 -> 6812.6359 | J19: =K60 -> 7498.3282 | K19: =K70 -> 8123.0689
B20: PT. HJL INDO NETWORKS | C20: =F20+I20 -> 91.09388 | D20: =G20+J20 -> 119.04118 | E20: =H20+K20 -> 128.43711 | F20: =D51 -> 71.458589 | G20: =D61 -> 100.83886 | H20: =D71 -> 110.40541 | I20: =K51 -> 19.635291 | J20: =K61 -> 18.202314 | K20: =K71 -> 18.031707
B21: PT.HOGA REKSA GARMENT | C21: =F21+I21 -> 2132.9814 | D21: =G21+J21 -> 2117.4424 | E21: =H21+K21 -> 3198.3873 | F21: =D52 -> 64.107488 | G21: =D62 -> 74.950319 | H21: =D72 -> 116.35485 | I21: =K52 -> 2068.8739 | J21: =K62 -> 2042.492 | K21: =K72 -> 3082.0324
B22: MFAFA Co., Ltd | C22: =F22+I22 -> 3.1390089 | D22: =G22+J22 -> 2.5755052 | E22: =H22+K22 -> 2.6038034 | F22: 0 | G22: 0 | H22: 0 | I22: =K53 -> 3.1390089 | J22: =K63 -> 2.5755052 | K22: =K73 -> 2.6038034
B23: * MFAFA Co., Ltd has been confirmed not to emit Scope 1 energy.
B25: GHG Emissions for Scope 1&2 by Energy Source (tCO2eq)
B27: Scope 1 | C27: Annual GHG Emissions (tCO2eq)
B28: Types of fuel | C28: 2022 | D28: 2023 | E28: 2024
B29: Total | C29: =SUM(C30:C35) -> 5807.3723 | D29: =SUM(D30:D35) -> 5472.6179 | E29: =SUM(E30:E35) -> 5415.5677
B30: {=_xlfn.UNIQUE('3-1. (Raw data) Scope 1'!AB6:AB79)} -> Automotive gasoline (petrol) | C30: =SUMIFS('3-1. (Raw data) Scope 1'!$AT$6:$AT$79,'3-1. (Raw data) Scope 1'!$Y$6:$Y$79,'2-1. Quantitative data_Location'!C$28,'3-1. (Raw data) Scope 1'!$AB$6:$AB$79,'2-1. Quantitative data_Location'!$B30) -> 1034.4686 | D30: =SUMIFS('3-1. (Raw data) Scope 1'!$AT$6:$AT$79,'3-1. (Raw data) Scope 1'!$Y$6:$Y$79,'2-1. Quantitative data_Location'!D$28,'3-1. (Raw data) Scope 1'!$AB$6:$AB$79,'2-1. Quantitative data_Location'!$B30) -> 1098.8887 | E30: =SUMIFS('3-1. (Raw data) Scope 1'!$AT$6:$AT$79,'3-1. (Raw data) Scope 1'!$Y$6:$Y$79,'2-1. Quantitative data_Location'!E$28,'3-1. (Raw data) Scope 1'!$AB$6:$AB$79,'2-1. Quantitative data_Location'!$B30) -> 945.71449
B31: Industrial Wastes | C31: =SUMIFS('3-1. (Raw data) Scope 1'!$AT$6:$AT$79,'3-1. (Raw data) Scope 1'!$Y$6:$Y$79,'2-1. Quantitative data_Location'!C$28,'3-1. (Raw data) Scope 1'!$AB$6:$AB$79,'2-1. Quantitative data_Location'!$B31) -> 4369.6399 | D31: =SUMIFS('3-1. (Raw data) Scope 1'!$AT$6:$AT$79,'3-1. (Raw data) Scope 1'!$Y$6:$Y$79,'2-1. Quantitative data_Location'!D$28,'3-1. (Raw data) Scope 1'!$AB$6:$AB$79,'2-1. Quantitative data_Location'!$B31) -> 3986.6566 | E31: =SUMIFS('3-1. (Raw data) Scope 1'!$AT$6:$AT$79,'3-1. (Raw data) Scope 1'!$Y$6:$Y$79,'2-1. Quantitative data_Location'!E$28,'3-1. (Raw data) Scope 1'!$AB$6:$AB$79,'2-1. Quantitative data_Location'!$B31) -> 4052.7375
B32: Biodiesel | C32: =SUMIFS('3-1. (Raw data) Scope 1'!$AT$6:$AT$79,'3-1. (Raw data) Scope 1'!$Y$6:$Y$79,'2-1. Quantitative data_Location'!C$28,'3-1. (Raw data) Scope 1'!$AB$6:$AB$79,'2-1. Quantitative data_Location'!$B32) -> 23.71627 | D32: =SUMIFS('3-1. (Raw data) Scope 1'!$AT$6:$AT$79,'3-1. (Raw data) Scope 1'!$Y$6:$Y$79,'2-1. Quantitative data_Location'!D$28,'3-1. (Raw data) Scope 1'!$AB$6:$AB$79,'2-1. Quantitative data_Location'!$B32) -> 26.422966 | E32: =SUMIFS('3-1. (Raw data) Scope 1'!$AT$6:$AT$79,'3-1. (Raw data) Scope 1'!$Y$6:$Y$79,'2-1. Quantitative data_Location'!E$28,'3-1. (Raw data) Scope 1'!$AB$6:$AB$79,'2-1. Quantitative data_Location'!$B32) -> 73.41294
B33: Liquefied Petroleum Gas (LPG) | C33: =SUMIFS('3-1. (Raw data) Scope 1'!$AT$6:$AT$79,'3-1. (Raw data) Scope 1'!$Y$6:$Y$79,'2-1. Quantitative data_Location'!C$28,'3-1. (Raw data) Scope 1'!$AB$6:$AB$79,'2-1. Quantitative data_Location'!$B33) -> 8.6025638 | D33: =SUMIFS('3-1. (Raw data) Scope 1'!$AT$6:$AT$79,'3-1. (Raw data) Scope 1'!$Y$6:$Y$79,'2-1. Quantitative data_Location'!D$28,'3-1. (Raw data) Scope 1'!$AB$6:$AB$79,'2-1. Quantitative data_Location'!$B33) -> 7.584198 | E33: =SUMIFS('3-1. (Raw data) Scope 1'!$AT$6:$AT$79,'3-1. (Raw data) Scope 1'!$Y$6:$Y$79,'2-1. Quantitative data_Location'!E$28,'3-1. (Raw data) Scope 1'!$AB$6:$AB$79,'2-1. Quantitative data_Location'!$B33) -> 7.477188
B34: Gas / Diesel oil | C34: =SUMIFS('3-1. (Raw data) Scope 1'!$AT$6:$AT$79,'3-1. (Raw data) Scope 1'!$Y$6:$Y$79,'2-1. Quantitative data_Location'!C$28,'3-1. (Raw data) Scope 1'!$AB$6:$AB$79,'2-1. Quantitative data_Location'!$B34) -> 51.544913 | D34: =SUMIFS('3-1. (Raw data) Scope 1'!$AT$6:$AT$79,'3-1. (Raw data) Scope 1'!$Y$6:$Y$79,'2-1. Quantitative data_Location'!D$28,'3-1. (Raw data) Scope 1'!$AB$6:$AB$79,'2-1. Quantitative data_Location'!$B34) -> 104.75457 | E34: =SUMIFS('3-1. (Raw data) Scope 1'!$AT$6:$AT$79,'3-1. (Raw data) Scope 1'!$Y$6:$Y$79,'2-1. Quantitative data_Location'!E$28,'3-1. (Raw data) Scope 1'!$AB$6:$AB$79,'2-1. Quantitative data_Location'!$B34) -> 48.579677
B35: Hydrofluorocarbons(HFCs) | C35: =SUMIFS('3-1. (Raw data) Scope 1'!$AT$6:$AT$79,'3-1. (Raw data) Scope 1'!$Y$6:$Y$79,'2-1. Quantitative data_Location'!C$28,'3-1. (Raw data) Scope 1'!$AB$6:$AB$79,'2-1. Quantitative data_Location'!$B35) -> 319.40005 | D35: =SUMIFS('3-1. (Raw data) Scope 1'!$AT$6:$AT$79,'3-1. (Raw data) Scope 1'!$Y$6:$Y$79,'2-1. Quantitative data_Location'!D$28,'3-1. (Raw data) Scope 1'!$AB$6:$AB$79,'2-1. Quantitative data_Location'!$B35) -> 248.3109 | E35: =SUMIFS('3-1. (Raw data) Scope 1'!$AT$6:$AT$79,'3-1. (Raw data) Scope 1'!$Y$6:$Y$79,'2-1. Quantitative data_Location'!E$28,'3-1. (Raw data) Scope 1'!$AB$6:$AB$79,'2-1. Quantitative data_Location'!$B35) -> 287.6459
B36: Scope 2 | C36: GHG Emissions (tCO2eq)
B37: Energy sources | C37: 2022 | D37: 2023 | E37: 2024
B38: Total | C38: =SUM(C39:C40) -> 11680.989 | D38: =SUM(D39:D40) -> 12204.329 | E38: =SUM(E39:E40) -> 14084.329
B39: Electricity | C39: =SUMIFS('3-2. (Raw data) Scope2_Location'!$AY:$AY,'3-2. (Raw data) Scope2_Location'!$AD:$AD,'2-1. Quantitative data_Location'!C$37,'3-2. (Raw data) Scope2_Location'!$AE:$AE,$B39) -> 11680.989 | D39: =SUMIFS('3-2. (Raw data) Scope2_Location'!$AY:$AY,'3-2. (Raw data) Scope2_Location'!$AD:$AD,'2-1. Quantitative data_Location'!D$37,'3-2. (Raw data) Scope2_Location'!$AE:$AE,$B39) -> 12204.329 | E39: =SUMIFS('3-2. (Raw data) Scope2_Location'!$AY:$AY,'3-2. (Raw data) Scope2_Location'!$AD:$AD,'2-1. Quantitative data_Location'!E$37,'3-2. (Raw data) Scope2_Location'!$AE:$AE,$B39) -> 14084.329
B40: Steam | C40: =SUMIFS('3-2. (Raw data) Scope2_Location'!$AY:$AY,'3-2. (Raw data) Scope2_Location'!$AD:$AD,'2-1. Quantitative data_Location'!C$37,'3-2. (Raw data) Scope2_Location'!$AE:$AE,$B40) -> 0 | D40: =SUMIFS('3-2. (Raw data) Scope2_Location'!$AY:$AY,'3-2. (Raw data) Scope2_Location'!$AD:$AD,'2-1. Quantitative data_Location'!D$37,'3-2. (Raw data) Scope2_Location'!$AE:$AE,$B40) -> 0 | E40: =SUMIFS('3-2. (Raw data) Scope2_Location'!$AY:$AY,'3-2. (Raw data) Scope2_Location'!$AD:$AD,'2-1. Quantitative data_Location'!E$37,'3-2. (Raw data) Scope2_Location'!$AE:$AE,$B40) -> 0
B42: GHG Emissions for Scope 1&2 by Fuel Type and Facility (tCO2eq)
A44: 2022년 | B44: 2022 | C44: Scope 1 + Scope 2 | D44: Scope 1 | K44: Scope 2
A45: 2022년 | D45: Scope 1 GHG Emissions by Facility | E45: {=_xlfn.TOROW(_xlfn.UNIQUE('3-1. (Raw data) Scope 1'!AB6:AB79))} -> Automotive gasoline (petrol) | F45: Industrial Wastes | G45: Biodiesel | H45: Liquefied Petroleum Gas (LPG) | I45: Gas / Diesel oil | J45: Hydrofluorocarbons(HFCs) | K45: Scope 2 GHG Emissions by Facility | L45: Electricity | M45: Electricity Consumption (MWh)
A46: 2022년 | B46: Total | C46: =D46+K46 -> 17488.362 | D46: =SUM(E46:J46) -> 5807.3723 | E46: =SUM(E47:E53) -> 1034.4686 | F46: =SUM(F47:F53) -> 4369.6399 | G46: =SUM(G47:G53) -> 23.71627 | H46: =SUM(H47:H53) -> 8.6025638 | I46: =SUM(I47:I53) -> 51.544913 | J46: =SUM(J47:J53) -> 319.40005 | K46: =SUM(K47:K53) -> 11680.989 | L46: =SUM(L47:L53) -> 11680.989 | M46: =SUM(M47:M53) -> 13614.07
A47: 2022년 | B47: HOJEON LIMITED Co., Ltd | C47: =D47+K47 -> 235.99585 | D47: =SUM(E47:J47) -> 49.986937 | E47: =SUMIFS('3-1. (Raw data) Scope 1'!$AT$6:$AT$79,'3-1. (Raw data) Scope 1'!$Y$6:$Y$79,'2-1. Quantitative data_Location'!$B$44,'3-1. (Raw data) Scope 1'!$D$6:$D$79,'2-1. Quantitative data_Location'!$B47,'3-1. (Raw data) Scope 1'!$AB$6:$AB$79,'2-1. Quantitative data_Location'!E$45) -> 49.986937 | F47: =SUMIFS('3-1. (Raw data) Scope 1'!$AT$6:$AT$79,'3-1. (Raw data) Scope 1'!$Y$6:$Y$79,'2-1. Quantitative data_Location'!$B$44,'3-1. (Raw data) Scope 1'!$D$6:$D$79,'2-1. Quantitative data_Location'!$B47,'3-1. (Raw data) Scope 1'!$AB$6:$AB$79,'2-1. Quantitative data_Location'!F$45) -> 0 | G47: =SUMIFS('3-1. (Raw data) Scope 1'!$AT$6:$AT$79,'3-1. (Raw data) Scope 1'!$Y$6:$Y$79,'2-1. Quantitative data_Location'!$B$44,'3-1. (Raw data) Scope 1'!$D$6:$D$79,'2-1. Quantitative data_Location'!$B47,'3-1. (Raw data) Scope 1'!$AB$6:$AB$79,'2-1. Quantitative data_Location'!G$45) -> 0 | H47: =SUMIFS('3-1. (Raw data) Scope 1'!$AT$6:$AT$79,'3-1. (Raw data) Scope 1'!$Y$6:$Y$79,'2-1. Quantitative data_Location'!$B$44,'3-1. (Raw data) Scope 1'!$D$6:$D$79,'2-1. Quantitative data_Location'!$B47,'3-1. (Raw data) Scope 1'!$AB$6:$AB$79,'2-1. Quantitative data_Location'!H$45) -> 0 | I47: =SUMIFS('3-1. (Raw data) Scope 1'!$AT$6:$AT$79,'3-1. (Raw data) Scope 1'!$Y$6:$Y$79,'2-1. Quantitative data_Location'!$B$44,'3-1. (Raw data) Scope 1'!$D$6:$D$79,'2-1. Quantitative data_Location'!$B47,'3-1. (Raw data) Scope 1'!$AB$6:$AB$79,'2-1. Quantitative data_Location'!I$45) -> 0 | J47: =SUMIFS('3-1. (Raw data) Scope 1'!$AT$6:$AT$79,'3-1. (Raw data) Scope 1'!$Y$6:$Y$79,'2-1. Quantitative data_Location'!$B$44,'3-1. (Raw data) Scope 1'!$D$6:$D$79,'2-1. Quantitative data_Location'!$B47,'3-1. (Raw data) Scope 1'!$AB$6:$AB$79,'2-1. Quantitative data_Location'!J$45) -> 0 | K47: =SUMIFS('3-2. (Raw data) Scope2_Location'!$AY$6:$AY$33,'3-2. (Raw data) Scope2_Location'!$AD$6:$AD$33,'2-1. Quantitative data_Location'!B$44,'3-2. (Raw data) Scope2_Location'!$D$6:$D$33,'2-1. Quantitative data_Location'!$B47) -> 186.00891 | L47: =SUMIFS('3-2. (Raw data) Scope2_Location'!$AY$6:$AY$33,'3-2. (Raw data) Scope2_Location'!$AD$6:$AD$33,'2-1. Quantitative data_Location'!B$44,'3-2. (Raw data) Scope2_Location'!$D$6:$D$33,'2-1. Quantitative data_Location'!$B47) -> 186.00891 | M47: =SUMIFS('3-2. (Raw data) Scope2_Location'!$AR$6:$AR$33,'3-2. (Raw data) Scope2_Location'!$AD$6:$AD$33,'2-1. Quantitative data_Location'!B$44,'3-2. (Raw data) Scope2_Location'!$D$6:$D$33,'2-1. Quantitative data_Location'!$B47) -> 398.33487
A48: 2022년 | B48: KAHOINDAH CITRAGARMENT | C48: =D48+K48 -> 2538.3389 | D48: =SUM(E48:J48) -> 1092.0335 | E48: =SUMIFS('3-1. (Raw data) Scope 1'!$AT$6:$AT$79,'3-1. (Raw data) Scope 1'!$Y$6:$Y$79,'2-1. Quantitative data_Location'!$B$44,'3-1. (Raw data) Scope 1'!$D$6:$D$79,'2-1. Quantitative data_Location'!$B48,'3-1. (Raw data) Scope 1'!$AB$6:$AB$79,'2-1. Quantitative data_Location'!E$45) -> 69.067883 | F48: =SUMIFS('3-1. (Raw data) Scope 1'!$AT$6:$AT$79,'3-1. (Raw data) Scope 1'!$Y$6:$Y$79,'2-1. Quantitative data_Location'!$B$44,'3-1. (Raw data) Scope 1'!$D$6:$D$79,'2-1. Quantitative data_Location'!$B48,'3-1. (Raw data) Scope 1'!$AB$6:$AB$79,'2-1. Quantitative data_Location'!F$45) -> 1019.5213 | G48: =SUMIFS('3-1. (Raw data) Scope 1'!$AT$6:$AT$79,'3-1. (Raw data) Scope 1'!$Y$6:$Y$79,'2-1. Quantitative data_Location'!$B$44,'3-1. (Raw data) Scope 1'!$D$6:$D$79,'2-1. Quantitative data_Location'!$B48,'3-1. (Raw data) Scope 1'!$AB$6:$AB$79,'2-1. Quantitative data_Location'!G$45) -> 2.512375 | H48: =SUMIFS('3-1. (Raw data) Scope 1'!$AT$6:$AT$79,'3-1. (Raw data) Scope 1'!$Y$6:$Y$79,'2-1. Quantitative data_Location'!$B$44,'3-1. (Raw data) Scope 1'!$D$6:$D$79,'2-1. Quantitative data_Location'!$B48,'3-1. (Raw data) Scope 1'!$AB$6:$AB$79,'2-1. Quantitative data_Location'!H$45) -> 0.9320059 | I48: =SUMIFS('3-1. (Raw data) Scope 1'!$AT$6:$AT$79,'3-1. (Raw data) Scope 1'!$Y$6:$Y$79,'2-1. Quantitative data_Location'!$B$44,'3-1. (Raw data) Scope 1'!$D$6:$D$79,'2-1. Quantitative data_Location'!$B48,'3-1. (Raw data) Scope 1'!$AB$6:$AB$79,'2-1. Quantitative data_Location'!I$45) -> 0 | J48: =SUMIFS('3-1. (Raw data) Scope 1'!$AT$6:$AT$79,'3-1. (Raw data) Scope 1'!$Y$6:$Y$79,'2-1. Quantitative data_Location'!$B$44,'3-1. (Raw data) Scope 1'!$D$6:$D$79,'2-1. Quantitative data_Location'!$B48,'3-1. (Raw data) Scope 1'!$AB$6:$AB$79,'2-1. Quantitative data_Location'!J$45) -> 0 | K48: =SUMIFS('3-2. (Raw data) Scope2_Location'!$AY$6:$AY$33,'3-2. (Raw data) Scope2_Location'!$AD$6:$AD$33,'2-1. Quantitative data_Location'!B$44,'3-2. (Raw data) Scope2_Location'!$D$6:$D$33,'2-1. Quantitative data_Location'!$B48) -> 1446.3054 | L48: =SUMIFS('3-2. (Raw data) Scope2_Location'!$AY$6:$AY$33,'3-2. (Raw data) Scope2_Location'!$AD$6:$AD$33,'2-1. Quantitative data_Location'!B$44,'3-2. (Raw data) Scope2_Location'!$D$6:$D$33,'2-1. Quantitative data_Location'!$B48) -> 1446.3054 | M48: =SUMIFS('3-2. (Raw data) Scope2_Location'!$AR$6:$AR$33,'3-2. (Raw data) Scope2_Location'!$AD$6:$AD$33,'2-1. Quantitative data_Location'!B$44,'3-2. (Raw data) Scope2_Location'!$D$6:$D$33,'2-1. Quantitative data_Location'!$B48) -> 1662.42
A49: 2022년 | B49: PT. YONGJIN JAVASUKA GARMENT (1공장) | C49: =D49+K49 -> 2622.4944 | D49: =SUM(E49:J49) -> 1478.1033 | E49: =SUMIFS('3-1. (Raw data) Scope 1'!$AT$6:$AT$79,'3-1. (Raw data) Scope 1'!$Y$6:$Y$79,'2-1. Quantitative data_Location'!$B$44,'3-1. (Raw data) Scope 1'!$D$6:$D$79,'2-1. Quantitative data_Location'!$B49,'3-1. (Raw data) Scope 1'!$AB$6:$AB$79,'2-1. Quantitative data_Location'!E$45) -> 164.92964 | F49: =SUMIFS('3-1. (Raw data) Scope 1'!$AT$6:$AT$79,'3-1. (Raw data) Scope 1'!$Y$6:$Y$79,'2-1. Quantitative data_Location'!$B$44,'3-1. (Raw data) Scope 1'!$D$6:$D$79,'2-1. Quantitative data_Location'!$B49,'3-1. (Raw data) Scope 1'!$AB$6:$AB$79,'2-1. Quantitative data_Location'!F$45) -> 1149.5978 | G49: =SUMIFS('3-1. (Raw data) Scope 1'!$AT$6:$AT$79,'3-1. (Raw data) Scope 1'!$Y$6:$Y$79,'2-1. Quantitative data_Location'!$B$44,'3-1. (Raw data) Scope 1'!$D$6:$D$79,'2-1. Quantitative data_Location'!$B49,'3-1. (Raw data) Scope 1'!$AB$6:$AB$79,'2-1. Quantitative data_Location'!G$45) -> 0 | H49: =SUMIFS('3-1. (Raw data) Scope 1'!$AT$6:$AT$79,'3-1. (Raw data) Scope 1'!$Y$6:$Y$79,'2-1. Quantitative data_Location'!$B$44,'3-1. (Raw data) Scope 1'!$D$6:$D$79,'2-1. Quantitative data_Location'!$B49,'3-1. (Raw data) Scope 1'!$AB$6:$AB$79,'2-1. Quantitative data_Location'!H$45) -> 2.6945426 | I49: =SUMIFS('3-1. (Raw data) Scope 1'!$AT$6:$AT$79,'3-1. (Raw data) Scope 1'!$Y$6:$Y$79,'2-1. Quantitative data_Location'!$B$44,'3-1. (Raw data) Scope 1'!$D$6:$D$79,'2-1. Quantitative data_Location'!$B49,'3-1. (Raw data) Scope 1'!$AB$6:$AB$79,'2-1. Quantitative data_Location'!I$45) -> 4.4519004 | J49: =SUMIFS('3-1. (Raw data) Scope 1'!$AT$6:$AT$79,'3-1. (Raw data) Scope 1'!$Y$6:$Y$79,'2-1. Quantitative data_Location'!$B$44,'3-1. (Raw data) Scope 1'!$D$6:$D$79,'2-1. Quantitative data_Location'!$B49,'3-1. (Raw data) Scope 1'!$AB$6:$AB$79,'2-1. Quantitative data_Location'!J$45) -> 156.42945 | K49: =SUMIFS('3-2. (Raw data) Scope2_Location'!$AY$6:$AY$33,'3-2. (Raw data) Scope2_Location'!$AD$6:$AD$33,'2-1. Quantitative data_Location'!B$44,'3-2. (Raw data) Scope2_Location'!$D$6:$D$33,'2-1. Quantitative data_Location'!$B49) -> 1144.391 | L49: =SUMIFS('3-2. (Raw data) Scope2_Location'!$AY$6:$AY$33,'3-2. (Raw data) Scope2_Location'!$AD$6:$AD$33,'2-1. Quantitative data_Location'!B$44,'3-2. (Raw data) Scope2_Location'!$D$6:$D$33,'2-1. Quantitative data_Location'!$B49) -> 1144.391 | M49: =SUMIFS('3-2. (Raw data) Scope2_Location'!$AR$6:$AR$33,'3-2. (Raw data) Scope2_Location'!$AD$6:$AD$33,'2-1. Quantitative data_Location'!B$44,'3-2. (Raw data) Scope2_Location'!$D$6:$D$33,'2-1. Quantitative data_Location'!$B49) -> 1315.392
A50: 2022년 | B50: PT. YONGJIN JAVASUKA GARMENT (2,3공장) | C50: =D50+K50 -> 9864.3183 | D50: =SUM(E50:J50) -> 3051.6824 | E50: =SUMIFS('3-1. (Raw data) Scope 1'!$AT$6:$AT$79,'3-1. (Raw data) Scope 1'!$Y$6:$Y$79,'2-1. Quantitative data_Location'!$B$44,'3-1. (Raw data) Scope 1'!$D$6:$D$79,'2-1. Quantitative data_Location'!$B50,'3-1. (Raw data) Scope 1'!$AB$6:$AB$79,'2-1. Quantitative data_Location'!E$45) -> 636.12194 | F50: =SUMIFS('3-1. (Raw data) Scope 1'!$AT$6:$AT$79,'3-1. (Raw data) Scope 1'!$Y$6:$Y$79,'2-1. Quantitative data_Location'!$B$44,'3-1. (Raw data) Scope 1'!$D$6:$D$79,'2-1. Quantitative data_Location'!$B50,'3-1. (Raw data) Scope 1'!$AB$6:$AB$79,'2-1. Quantitative data_Location'!F$45) -> 2200.5209 | G50: =SUMIFS('3-1. (Raw data) Scope 1'!$AT$6:$AT$79,'3-1. (Raw data) Scope 1'!$Y$6:$Y$79,'2-1. Quantitative data_Location'!$B$44,'3-1. (Raw data) Scope 1'!$D$6:$D$79,'2-1. Quantitative data_Location'!$B50,'3-1. (Raw data) Scope 1'!$AB$6:$AB$79,'2-1. Quantitative data_Location'!G$45) -> 0 | H50: =SUMIFS('3-1. (Raw data) Scope 1'!$AT$6:$AT$79,'3-1. (Raw data) Scope 1'!$Y$6:$Y$79,'2-1. Quantitative data_Location'!$B$44,'3-1. (Raw data) Scope 1'!$D$6:$D$79,'2-1. Quantitative data_Location'!$B50,'3-1. (Raw data) Scope 1'!$AB$6:$AB$79,'2-1. Quantitative data_Location'!H$45) -> 4.9760153 | I50: =SUMIFS('3-1. (Raw data) Scope 1'!$AT$6:$AT$79,'3-1. (Raw data) Scope 1'!$Y$6:$Y$79,'2-1. Quantitative data_Location'!$B$44,'3-1. (Raw data) Scope 1'!$D$6:$D$79,'2-1. Quantitative data_Location'!$B50,'3-1. (Raw data) Scope 1'!$AB$6:$AB$79,'2-1. Quantitative data_Location'!I$45) -> 47.093012 | J50: =SUMIFS('3-1. (Raw data) Scope 1'!$AT$6:$AT$79,'3-1. (Raw data) Scope 1'!$Y$6:$Y$79,'2-1. Quantitative data_Location'!$B$44,'3-1. (Raw data) Scope 1'!$D$6:$D$79,'2-1. Quantitative data_Location'!$B50,'3-1. (Raw data) Scope 1'!$AB$6:$AB$79,'2-1. Quantitative data_Location'!J$45) -> 162.9706 | K50: =SUMIFS('3-2. (Raw data) Scope2_Location'!$AY$6:$AY$33,'3-2. (Raw data) Scope2_Location'!$AD$6:$AD$33,'2-1. Quantitative data_Location'!B$44,'3-2. (Raw data) Scope2_Location'!$D$6:$D$33,'2-1. Quantitative data_Location'!$B50) -> 6812.6359 | L50: =SUMIFS('3-2. (Raw data) Scope2_Location'!$AY$6:$AY$33,'3-2. (Raw data) Scope2_Location'!$AD$6:$AD$33,'2-1. Quantitative data_Location'!B$44,'3-2. (Raw data) Scope2_Location'!$D$6:$D$33,'2-1. Quantitative data_Location'!$B50) -> 6812.6359 | M50: =SUMIFS('3-2. (Raw data) Scope2_Location'!$AR$6:$AR$33,'3-2. (Raw data) Scope2_Location'!$AD$6:$AD$33,'2-1. Quantitative data_Location'!B$44,'3-2. (Raw data) Scope2_Location'!$D$6:$D$33,'2-1. Quantitative data_Location'!$B50) -> 7830.616
A51: 2022년 | B51: PT. HJL INDO NETWORKS | C51: =D51+K51 -> 91.09388 | D51: =SUM(E51:J51) -> 71.458589 | E51: =SUMIFS('3-1. (Raw data) Scope 1'!$AT$6:$AT$79,'3-1. (Raw data) Scope 1'!$Y$6:$Y$79,'2-1. Quantitative data_Location'!$B$44,'3-1. (Raw data) Scope 1'!$D$6:$D$79,'2-1. Quantitative data_Location'!$B51,'3-1. (Raw data) Scope 1'!$AB$6:$AB$79,'2-1. Quantitative data_Location'!E$45) -> 71.458589 | F51: =SUMIFS('3-1. (Raw data) Scope 1'!$AT$6:$AT$79,'3-1. (Raw data) Scope 1'!$Y$6:$Y$79,'2-1. Quantitative data_Location'!$B$44,'3-1. (Raw data) Scope 1'!$D$6:$D$79,'2-1. Quantitative data_Location'!$B51,'3-1. (Raw data) Scope 1'!$AB$6:$AB$79,'2-1. Quantitative data_Location'!F$45) -> 0 | G51: =SUMIFS('3-1. (Raw data) Scope 1'!$AT$6:$AT$79,'3-1. (Raw data) Scope 1'!$Y$6:$Y$79,'2-1. Quantitative data_Location'!$B$44,'3-1. (Raw data) Scope 1'!$D$6:$D$79,'2-1. Quantitative data_Location'!$B51,'3-1. (Raw data) Scope 1'!$AB$6:$AB$79,'2-1. Quantitative data_Location'!G$45) -> 0 | H51: =SUMIFS('3-1. (Raw data) Scope 1'!$AT$6:$AT$79,'3-1. (Raw data) Scope 1'!$Y$6:$Y$79,'2-1. Quantitative data_Location'!$B$44,'3-1. (Raw data) Scope 1'!$D$6:$D$79,'2-1. Quantitative data_Location'!$B51,'3-1. (Raw data) Scope 1'!$AB$6:$AB$79,'2-1. Quantitative data_Location'!H$45) -> 0 | I51: =SUMIFS('3-1. (Raw data) Scope 1'!$AT$6:$AT$79,'3-1. (Raw data) Scope 1'!$Y$6:$Y$79,'2-1. Quantitative data_Location'!$B$44,'3-1. (Raw data) Scope 1'!$D$6:$D$79,'2-1. Quantitative data_Location'!$B51,'3-1. (Raw data) Scope 1'!$AB$6:$AB$79,'2-1. Quantitative data_Location'!I$45) -> 0 | J51: =SUMIFS('3-1. (Raw data) Scope 1'!$AT$6:$AT$79,'3-1. (Raw data) Scope 1'!$Y$6:$Y$79,'2-1. Quantitative data_Location'!$B$44,'3-1. (Raw data) Scope 1'!$D$6:$D$79,'2-1. Quantitative data_Location'!$B51,'3-1. (Raw data) Scope 1'!$AB$6:$AB$79,'2-1. Quantitative data_Location'!J$45) -> 0 | K51: =SUMIFS('3-2. (Raw data) Scope2_Location'!$AY$6:$AY$33,'3-2. (Raw data) Scope2_Location'!$AD$6:$AD$33,'2-1. Quantitative data_Location'!B$44,'3-2. (Raw data) Scope2_Location'!$D$6:$D$33,'2-1. Quantitative data_Location'!$B51) -> 19.635291 | L51: =SUMIFS('3-2. (Raw data) Scope2_Location'!$AY$6:$AY$33,'3-2. (Raw data) Scope2_Location'!$AD$6:$AD$33,'2-1. Quantitative data_Location'!B$44,'3-2. (Raw data) Scope2_Location'!$D$6:$D$33,'2-1. Quantitative data_Location'!$B51) -> 19.635291 | M51: =SUMIFS('3-2. (Raw data) Scope2_Location'!$AR$6:$AR$33,'3-2. (Raw data) Scope2_Location'!$AD$6:$AD$33,'2-1. Quantitative data_Location'!B$44,'3-2. (Raw data) Scope2_Location'!$D$6:$D$33,'2-1. Quantitative data_Location'!$B51) -> 22.5693
A52: 2022년 | B52: PT.HOGA REKSA GARMENT | C52: =D52+K52 -> 2132.9814 | D52: =SUM(E52:J52) -> 64.107488 | E52: =SUMIFS('3-1. (Raw data) Scope 1'!$AT$6:$AT$79,'3-1. (Raw data) Scope 1'!$Y$6:$Y$79,'2-1. Quantitative data_Location'!$B$44,'3-1. (Raw data) Scope 1'!$D$6:$D$79,'2-1. Quantitative data_Location'!$B52,'3-1. (Raw data) Scope 1'!$AB$6:$AB$79,'2-1. Quantitative data_Location'!E$45) -> 42.903594 | F52: =SUMIFS('3-1. (Raw data) Scope 1'!$AT$6:$AT$79,'3-1. (Raw data) Scope 1'!$Y$6:$Y$79,'2-1. Quantitative data_Location'!$B$44,'3-1. (Raw data) Scope 1'!$D$6:$D$79,'2-1. Quantitative data_Location'!$B52,'3-1. (Raw data) Scope 1'!$AB$6:$AB$79,'2-1. Quantitative data_Location'!F$45) -> 0 | G52: =SUMIFS('3-1. (Raw data) Scope 1'!$AT$6:$AT$79,'3-1. (Raw data) Scope 1'!$Y$6:$Y$79,'2-1. Quantitative data_Location'!$B$44,'3-1. (Raw data) Scope 1'!$D$6:$D$79,'2-1. Quantitative data_Location'!$B52,'3-1. (Raw data) Scope 1'!$AB$6:$AB$79,'2-1. Quantitative data_Location'!G$45) -> 21.203895 | H52: =SUMIFS('3-1. (Raw data) Scope 1'!$AT$6:$AT$79,'3-1. (Raw data) Scope 1'!$Y$6:$Y$79,'2-1. Quantitative data_Location'!$B$44,'3-1. (Raw data) Scope 1'!$D$6:$D$79,'2-1. Quantitative data_Location'!$B52,'3-1. (Raw data) Scope 1'!$AB$6:$AB$79,'2-1. Quantitative data_Location'!H$45) -> 0 | I52: =SUMIFS('3-1. (Raw data) Scope 1'!$AT$6:$AT$79,'3-1. (Raw data) Scope 1'!$Y$6:$Y$79,'2-1. Quantitative data_Location'!$B$44,'3-1. (Raw data) Scope 1'!$D$6:$D$79,'2-1. Quantitative data_Location'!$B52,'3-1. (Raw data) Scope 1'!$AB$6:$AB$79,'2-1. Quantitative data_Location'!I$45) -> 0 | J52: =SUMIFS('3-1. (Raw data) Scope 1'!$AT$6:$AT$79,'3-1. (Raw data) Scope 1'!$Y$6:$Y$79,'2-1. Quantitative data_Location'!$B$44,'3-1. (Raw data) Scope 1'!$D$6:$D$79,'2-1. Quantitative data_Location'!$B52,'3-1. (Raw data) Scope 1'!$AB$6:$AB$79,'2-1. Quantitative data_Location'!J$45) -> 0 | K52: =SUMIFS('3-2. (Raw data) Scope2_Location'!$AY$6:$AY$33,'3-2. (Raw data) Scope2_Location'!$AD$6:$AD$33,'2-1. Quantitative data_Location'!B$44,'3-2. (Raw data) Scope2_Location'!$D$6:$D$33,'2-1. Quantitative data_Location'!$B52) -> 2068.8739 | L52: =SUMIFS('3-2. (Raw data) Scope2_Location'!$AY$6:$AY$33,'3-2. (Raw data) Scope2_Location'!$AD$6:$AD$33,'2-1. Quantitative data_Location'!B$44,'3-2. (Raw data) Scope2_Location'!$D$6:$D$33,'2-1. Quantitative data_Location'!$B52) -> 2068.8739 | M52: =SUMIFS('3-2. (Raw data) Scope2_Location'!$AR$6:$AR$33,'3-2. (Raw data) Scope2_Location'!$AD$6:$AD$33,'2-1. Quantitative data_Location'!B$44,'3-2. (Raw data) Scope2_Location'!$D$6:$D$33,'2-1. Quantitative data_Location'!$B52) -> 2378.016
A53: 2022년 | B53: MFAFA Co., Ltd | C53: =D53+K53 -> 3.1390089 | D53: =SUM(E53:J53) -> 0 | E53: =SUMIFS('3-1. (Raw data) Scope 1'!$AT$6:$AT$79,'3-1. (Raw data) Scope 1'!$Y$6:$Y$79,'2-1. Quantitative data_Location'!$B$44,'3-1. (Raw data) Scope 1'!$D$6:$D$79,'2-1. Quantitative data_Location'!$B53,'3-1. (Raw data) Scope 1'!$AB$6:$AB$79,'2-1. Quantitative data_Location'!E$45) -> 0 | F53: =SUMIFS('3-1. (Raw data) Scope 1'!$AT$6:$AT$79,'3-1. (Raw data) Scope 1'!$Y$6:$Y$79,'2-1. Quantitative data_Location'!$B$44,'3-1. (Raw data) Scope 1'!$D$6:$D$79,'2-1. Quantitative data_Location'!$B53,'3-1. (Raw data) Scope 1'!$AB$6:$AB$79,'2-1. Quantitative data_Location'!F$45) -> 0 | G53: =SUMIFS('3-1. (Raw data) Scope 1'!$AT$6:$AT$79,'3-1. (Raw data) Scope 1'!$Y$6:$Y$79,'2-1. Quantitative data_Location'!$B$44,'3-1. (Raw data) Scope 1'!$D$6:$D$79,'2-1. Quantitative data_Location'!$B53,'3-1. (Raw data) Scope 1'!$AB$6:$AB$79,'2-1. Quantitative data_Location'!G$45) -> 0 | H53: =SUMIFS('3-1. (Raw data) Scope 1'!$AT$6:$AT$79,'3-1. (Raw data) Scope 1'!$Y$6:$Y$79,'2-1. Quantitative data_Location'!$B$44,'3-1. (Raw data) Scope 1'!$D$6:$D$79,'2-1. Quantitative data_Location'!$B53,'3-1. (Raw data) Scope 1'!$AB$6:$AB$79,'2-1. Quantitative data_Location'!H$45) -> 0 | I53: =SUMIFS('3-1. (Raw data) Scope 1'!$AT$6:$AT$79,'3-1. (Raw data) Scope 1'!$Y$6:$Y$79,'2-1. Quantitative data_Location'!$B$44,'3-1. (Raw data) Scope 1'!$D$6:$D$79,'2-1. Quantitative data_Location'!$B53,'3-1. (Raw data) Scope 1'!$AB$6:$AB$79,'2-1. Quantitative data_Location'!I$45) -> 0 | J53: =SUMIFS('3-1. (Raw data) Scope 1'!$AT$6:$AT$79,'3-1. (Raw data) Scope 1'!$Y$6:$Y$79,'2-1. Quantitative data_Location'!$B$44,'3-1. (Raw data) Scope 1'!$D$6:$D$79,'2-1. Quantitative data_Location'!$B53,'3-1. (Raw data) Scope 1'!$AB$6:$AB$79,'2-1. Quantitative data_Location'!J$45) -> 0 | K53: =SUMIFS('3-2. (Raw data) Scope2_Location'!$AY$6:$AY$33,'3-2. (Raw data) Scope2_Location'!$AD$6:$AD$33,'2-1. Quantitative data_Location'!B$44,'3-2. (Raw data) Scope2_Location'!$D$6:$D$33,'2-1. Quantitative data_Location'!$B53) -> 3.1390089 | L53: =SUMIFS('3-2. (Raw data) Scope2_Location'!$AY$6:$AY$33,'3-2. (Raw data) Scope2_Location'!$AD$6:$AD$33,'2-1. Quantitative data_Location'!B$44,'3-2. (Raw data) Scope2_Location'!$D$6:$D$33,'2-1. Quantitative data_Location'!$B53) -> 3.1390089 | M53: =SUMIFS('3-2. (Raw data) Scope2_Location'!$AR$6:$AR$33,'3-2. (Raw data) Scope2_Location'!$AD$6:$AD$33,'2-1. Quantitative data_Location'!B$44,'3-2. (Raw data) Scope2_Location'!$D$6:$D$33,'2-1. Quantitative data_Location'!$B53) -> 6.7221333
A54: 2023년 | B54: 2023 | C54: Scope 1 + Scope 2 | D54: Scope 1 | K54: Scope 2
A55: 2023년 | D55: Scope 1 GHG Emissions by Facility | E55: {=_xlfn.TOROW(_xlfn.UNIQUE('3-1. (Raw data) Scope 1'!AB6:AB79))} -> Automotive gasoline (petrol) | F55: Industrial Wastes | G55: Biodiesel | H55: Liquefied Petroleum Gas (LPG) | I55: Gas / Diesel oil | J55: Hydrofluorocarbons(HFCs) | K55: Scope 2 GHG Emissions by Facility | L55: Electricity | M55: Electricity Consumption (MWh)
A56: 2023년 | B56: Total | C56: =D56+K56 -> 17676.947 | D56: =SUM(E56:J56) -> 5472.6179 | E56: =SUM(E57:E63) -> 1098.8887 | F56: =SUM(F57:F63) -> 3986.6566 | G56: =SUM(G57:G63) -> 26.422966 | H56: =SUM(H57:H63) -> 7.584198 | I56: =SUM(I57:I63) -> 104.75457 | J56: =SUM(J57:J63) -> 248.3109 | K56: =SUM(K57:K63) -> 12204.329 | L56: =SUM(L57:L63) -> 12204.329 | M56: =SUM(M57:M63) -> 14208.297
A57: 2023년 | B57: HOJEON LIMITED Co., Ltd | C57: =D57+K57 -> 239.15711 | D57: =SUM(E57:J57) -> 59.95623 | E57: =SUMIFS('3-1. (Raw data) Scope 1'!$AT$6:$AT$79,'3-1. (Raw data) Scope 1'!$Y$6:$Y$79,'2-1. Quantitative data_Location'!$B$54,'3-1. (Raw data) Scope 1'!$D$6:$D$79,'2-1. Quantitative data_Location'!$B57,'3-1. (Raw data) Scope 1'!$AB$6:$AB$79,'2-1. Quantitative data_Location'!E$55) -> 59.95623 | F57: =SUMIFS('3-1. (Raw data) Scope 1'!$AT$6:$AT$79,'3-1. (Raw data) Scope 1'!$Y$6:$Y$79,'2-1. Quantitative data_Location'!$B$54,'3-1. (Raw data) Scope 1'!$D$6:$D$79,'2-1. Quantitative data_Location'!$B57,'3-1. (Raw data) Scope 1'!$AB$6:$AB$79,'2-1. Quantitative data_Location'!F$55) -> 0 | G57: =SUMIFS('3-1. (Raw data) Scope 1'!$AT$6:$AT$79,'3-1. (Raw data) Scope 1'!$Y$6:$Y$79,'2-1. Quantitative data_Location'!$B$54,'3-1. (Raw data) Scope 1'!$D$6:$D$79,'2-1. Quantitative data_Location'!$B57,'3-1. (Raw data) Scope 1'!$AB$6:$AB$79,'2-1. Quantitative data_Location'!G$55) -> 0 | H57: =SUMIFS('3-1. (Raw data) Scope 1'!$AT$6:$AT$79,'3-1. (Raw data) Scope 1'!$Y$6:$Y$79,'2-1. Quantitative data_Location'!$B$54,'3-1. (Raw data) Scope 1'!$D$6:$D$79,'2-1. Quantitative data_Location'!$B57,'3-1. (Raw data) Scope 1'!$AB$6:$AB$79,'2-1. Quantitative data_Location'!H$55) -> 0 | I57: =SUMIFS('3-1. (Raw data) Scope 1'!$AT$6:$AT$79,'3-1. (Raw data) Scope 1'!$Y$6:$Y$79,'2-1. Quantitative data_Location'!$B$54,'3-1. (Raw data) Scope 1'!$D$6:$D$79,'2-1. Quantitative data_Location'!$B57,'3-1. (Raw data) Scope 1'!$AB$6:$AB$79,'2-1. Quantitative data_Location'!I$55) -> 0 | J57: =SUMIFS('3-1. (Raw data) Scope 1'!$AT$6:$AT$79,'3-1. (Raw data) Scope 1'!$Y$6:$Y$79,'2-1. Quantitative data_Location'!$B$54,'3-1. (Raw data) Scope 1'!$D$6:$D$79,'2-1. Quantitative data_Location'!$B57,'3-1. (Raw data) Scope 1'!$AB$6:$AB$79,'2-1. Quantitative data_Location'!J$55) -> 0 | K57: =SUMIFS('3-2. (Raw data) Scope2_Location'!$AY$6:$AY$33,'3-2. (Raw data) Scope2_Location'!$AD$6:$AD$33,'2-1. Quantitative data_Location'!$B$54,'3-2. (Raw data) Scope2_Location'!$D$6:$D$33,'2-1. Quantitative data_Location'!$B57) -> 179.20088 | L57: =SUMIFS('3-2. (Raw data) Scope2_Location'!$AY$6:$AY$33,'3-2. (Raw data) Scope2_Location'!$AD$6:$AD$33,'2-1. Quantitative data_Location'!$B$54,'3-2. (Raw data) Scope2_Location'!$D$6:$D$33,'2-1. Quantitative data_Location'!$B57) -> 179.20088 | M57: =SUMIFS('3-2. (Raw data) Scope2_Location'!$AR$6:$AR$33,'3-2. (Raw data) Scope2_Location'!$AD$6:$AD$33,'2-1. Quantitative data_Location'!B$54,'3-2. (Raw data) Scope2_Location'!$D$6:$D$33,'2-1. Quantitative data_Location'!$B57) -> 383.7556
A58: 2023년 | B58: KAHOINDAH CITRAGARMENT | C58: =D58+K58 -> 2386.1475 | D58: =SUM(E58:J58) -> 1049.9841 | E58: =SUMIFS('3-1. (Raw data) Scope 1'!$AT$6:$AT$79,'3-1. (Raw data) Scope 1'!$Y$6:$Y$79,'2-1. Quantitative data_Location'!$B$54,'3-1. (Raw data) Scope 1'!$D$6:$D$79,'2-1. Quantitative data_Location'!$B58,'3-1. (Raw data) Scope 1'!$AB$6:$AB$79,'2-1. Quantitative data_Location'!E$55) -> 64.022518 | F58: =SUMIFS('3-1. (Raw data) Scope 1'!$AT$6:$AT$79,'3-1. (Raw data) Scope 1'!$Y$6:$Y$79,'2-1. Quantitative data_Location'!$B$54,'3-1. (Raw data) Scope 1'!$D$6:$D$79,'2-1. Quantitative data_Location'!$B58,'3-1. (Raw data) Scope 1'!$AB$6:$AB$79,'2-1. Quantitative data_Location'!F$55) -> 982.67677 | G58: =SUMIFS('3-1. (Raw data) Scope 1'!$AT$6:$AT$79,'3-1. (Raw data) Scope 1'!$Y$6:$Y$79,'2-1. Quantitative data_Location'!$B$54,'3-1. (Raw data) Scope 1'!$D$6:$D$79,'2-1. Quantitative data_Location'!$B58,'3-1. (Raw data) Scope 1'!$AB$6:$AB$79,'2-1. Quantitative data_Location'!G$55) -> 2.4961662 | H58: =SUMIFS('3-1. (Raw data) Scope 1'!$AT$6:$AT$79,'3-1. (Raw data) Scope 1'!$Y$6:$Y$79,'2-1. Quantitative data_Location'!$B$54,'3-1. (Raw data) Scope 1'!$D$6:$D$79,'2-1. Quantitative data_Location'!$B58,'3-1. (Raw data) Scope 1'!$AB$6:$AB$79,'2-1. Quantitative data_Location'!H$55) -> 0.78862037 | I58: =SUMIFS('3-1. (Raw data) Scope 1'!$AT$6:$AT$79,'3-1. (Raw data) Scope 1'!$Y$6:$Y$79,'2-1. Quantitative data_Location'!$B$54,'3-1. (Raw data) Scope 1'!$D$6:$D$79,'2-1. Quantitative data_Location'!$B58,'3-1. (Raw data) Scope 1'!$AB$6:$AB$79,'2-1. Quantitative data_Location'!I$55) -> 0 | J58: =SUMIFS('3-1. (Raw data) Scope 1'!$AT$6:$AT$79,'3-1. (Raw data) Scope 1'!$Y$6:$Y$79,'2-1. Quantitative data_Location'!$B$54,'3-1. (Raw data) Scope 1'!$D$6:$D$79,'2-1. Quantitative data_Location'!$B58,'3-1. (Raw data) Scope 1'!$AB$6:$AB$79,'2-1. Quantitative data_Location'!J$55) -> 0 | K58: =SUMIFS('3-2. (Raw data) Scope2_Location'!$AY$6:$AY$33,'3-2. (Raw data) Scope2_Location'!$AD$6:$AD$33,'2-1. Quantitative data_Location'!$B$54,'3-2. (Raw data) Scope2_Location'!$D$6:$D$33,'2-1. Quantitative data_Location'!$B58) -> 1336.1634 | L58: =SUMIFS('3-2. (Raw data) Scope2_Location'!$AY$6:$AY$33,'3-2. (Raw data) Scope2_Location'!$AD$6:$AD$33,'2-1. Quantitative data_Location'!$B$54,'3-2. (Raw data) Scope2_Location'!$D$6:$D$33,'2-1. Quantitative data_Location'!$B58) -> 1336.1634 | M58: =SUMIFS('3-2. (Raw data) Scope2_Location'!$AR$6:$AR$33,'3-2. (Raw data) Scope2_Location'!$AD$6:$AD$33,'2-1. Quantitative data_Location'!B$54,'3-2. (Raw data) Scope2_Location'!$D$6:$D$33,'2-1. Quantitative data_Location'!$B58) -> 1535.82
A59: 2023년 | B59: PT. YONGJIN JAVASUKA GARMENT (1공장) | C59: =D59+K59 -> 2504.7999 | D59: =SUM(E59:J59) -> 1377.433 | E59: =SUMIFS('3-1. (Raw data) Scope 1'!$AT$6:$AT$79,'3-1. (Raw data) Scope 1'!$Y$6:$Y$79,'2-1. Quantitative data_Location'!$B$54,'3-1. (Raw data) Scope 1'!$D$6:$D$79,'2-1. Quantitative data_Location'!$B59,'3-1. (Raw data) Scope 1'!$AB$6:$AB$79,'2-1. Quantitative data_Location'!E$55) -> 189.67944 | F59: =SUMIFS('3-1. (Raw data) Scope 1'!$AT$6:$AT$79,'3-1. (Raw data) Scope 1'!$Y$6:$Y$79,'2-1. Quantitative data_Location'!$B$54,'3-1. (Raw data) Scope 1'!$D$6:$D$79,'2-1. Quantitative data_Location'!$B59,'3-1. (Raw data) Scope 1'!$AB$6:$AB$79,'2-1. Quantitative data_Location'!F$55) -> 1119.3328 | G59: =SUMIFS('3-1. (Raw data) Scope 1'!$AT$6:$AT$79,'3-1. (Raw data) Scope 1'!$Y$6:$Y$79,'2-1. Quantitative data_Location'!$B$54,'3-1. (Raw data) Scope 1'!$D$6:$D$79,'2-1. Quantitative data_Location'!$B59,'3-1. (Raw data) Scope 1'!$AB$6:$AB$79,'2-1. Quantitative data_Location'!G$55) -> 0 | H59: =SUMIFS('3-1. (Raw data) Scope 1'!$AT$6:$AT$79,'3-1. (Raw data) Scope 1'!$Y$6:$Y$79,'2-1. Quantitative data_Location'!$B$54,'3-1. (Raw data) Scope 1'!$D$6:$D$79,'2-1. Quantitative data_Location'!$B59,'3-1. (Raw data) Scope 1'!$AB$6:$AB$79,'2-1. Quantitative data_Location'!H$55) -> 2.6317815 | I59: =SUMIFS('3-1. (Raw data) Scope 1'!$AT$6:$AT$79,'3-1. (Raw data) Scope 1'!$Y$6:$Y$79,'2-1. Quantitative data_Location'!$B$54,'3-1. (Raw data) Scope 1'!$D$6:$D$79,'2-1. Quantitative data_Location'!$B59,'3-1. (Raw data) Scope 1'!$AB$6:$AB$79,'2-1. Quantitative data_Location'!I$55) -> 5.9358673 | J59: =SUMIFS('3-1. (Raw data) Scope 1'!$AT$6:$AT$79,'3-1. (Raw data) Scope 1'!$Y$6:$Y$79,'2-1. Quantitative data_Location'!$B$54,'3-1. (Raw data) Scope 1'!$D$6:$D$79,'2-1. Quantitative data_Location'!$B59,'3-1. (Raw data) Scope 1'!$AB$6:$AB$79,'2-1. Quantitative data_Location'!J$55) -> 59.85315 | K59: =SUMIFS('3-2. (Raw data) Scope2_Location'!$AY$6:$AY$33,'3-2. (Raw data) Scope2_Location'!$AD$6:$AD$33,'2-1. Quantitative data_Location'!$B$54,'3-2. (Raw data) Scope2_Location'!$D$6:$D$33,'2-1. Quantitative data_Location'!$B59) -> 1127.3669 | L59: =SUMIFS('3-2. (Raw data) Scope2_Location'!$AY$6:$AY$33,'3-2. (Raw data) Scope2_Location'!$AD$6:$AD$33,'2-1. Quantitative data_Location'!$B$54,'3-2. (Raw data) Scope2_Location'!$D$6:$D$33,'2-1. Quantitative data_Location'!$B59) -> 1127.3669 | M59: =SUMIFS('3-2. (Raw data) Scope2_Location'!$AR$6:$AR$33,'3-2. (Raw data) Scope2_Location'!$AD$6:$AD$33,'2-1. Quantitative data_Location'!B$54,'3-2. (Raw data) Scope2_Location'!$D$6:$D$33,'2-1. Quantitative data_Location'!$B59) -> 1295.824
A60: 2023년 | B60: PT. YONGJIN JAVASUKA GARMENT (2,3공장) | C60: =D60+K60 -> 10307.784 | D60: =SUM(E60:J60) -> 2809.4554 | E60: =SUMIFS('3-1. (Raw data) Scope 1'!$AT$6:$AT$79,'3-1. (Raw data) Scope 1'!$Y$6:$Y$79,'2-1. Quantitative data_Location'!$B$54,'3-1. (Raw data) Scope 1'!$D$6:$D$79,'2-1. Quantitative data_Location'!$B60,'3-1. (Raw data) Scope 1'!$AB$6:$AB$79,'2-1. Quantitative data_Location'!E$55) -> 633.36815 | F60: =SUMIFS('3-1. (Raw data) Scope 1'!$AT$6:$AT$79,'3-1. (Raw data) Scope 1'!$Y$6:$Y$79,'2-1. Quantitative data_Location'!$B$54,'3-1. (Raw data) Scope 1'!$D$6:$D$79,'2-1. Quantitative data_Location'!$B60,'3-1. (Raw data) Scope 1'!$AB$6:$AB$79,'2-1. Quantitative data_Location'!F$55) -> 1884.647 | G60: =SUMIFS('3-1. (Raw data) Scope 1'!$AT$6:$AT$79,'3-1. (Raw data) Scope 1'!$Y$6:$Y$79,'2-1. Quantitative data_Location'!$B$54,'3-1. (Raw data) Scope 1'!$D$6:$D$79,'2-1. Quantitative data_Location'!$B60,'3-1. (Raw data) Scope 1'!$AB$6:$AB$79,'2-1. Quantitative data_Location'!G$55) -> 0 | H60: =SUMIFS('3-1. (Raw data) Scope 1'!$AT$6:$AT$79,'3-1. (Raw data) Scope 1'!$Y$6:$Y$79,'2-1. Quantitative data_Location'!$B$54,'3-1. (Raw data) Scope 1'!$D$6:$D$79,'2-1. Quantitative data_Location'!$B60,'3-1. (Raw data) Scope 1'!$AB$6:$AB$79,'2-1. Quantitative data_Location'!H$55) -> 4.1637961 | I60: =SUMIFS('3-1. (Raw data) Scope 1'!$AT$6:$AT$79,'3-1. (Raw data) Scope 1'!$Y$6:$Y$79,'2-1. Quantitative data_Location'!$B$54,'3-1. (Raw data) Scope 1'!$D$6:$D$79,'2-1. Quantitative data_Location'!$B60,'3-1. (Raw data) Scope 1'!$AB$6:$AB$79,'2-1. Quantitative data_Location'!I$55) -> 98.818699 | J60: =SUMIFS('3-1. (Raw data) Scope 1'!$AT$6:$AT$79,'3-1. (Raw data) Scope 1'!$Y$6:$Y$79,'2-1. Quantitative data_Location'!$B$54,'3-1. (Raw data) Scope 1'!$D$6:$D$79,'2-1. Quantitative data_Location'!$B60,'3-1. (Raw data) Scope 1'!$AB$6:$AB$79,'2-1. Quantitative data_Location'!J$55) -> 188.45775 | K60: =SUMIFS('3-2. (Raw data) Scope2_Location'!$AY$6:$AY$33,'3-2. (Raw data) Scope2_Location'!$AD$6:$AD$33,'2-1. Quantitative data_Location'!$B$54,'3-2. (Raw data) Scope2_Location'!$D$6:$D$33,'2-1. Quantitative data_Location'!$B60) -> 7498.3282 | L60: =SUMIFS('3-2. (Raw data) Scope2_Location'!$AY$6:$AY$33,'3-2. (Raw data) Scope2_Location'!$AD$6:$AD$33,'2-1. Quantitative data_Location'!$B$54,'3-2. (Raw data) Scope2_Location'!$D$6:$D$33,'2-1. Quantitative data_Location'!$B60) -> 7498.3282 | M60: =SUMIFS('3-2. (Raw data) Scope2_Location'!$AR$6:$AR$33,'3-2. (Raw data) Scope2_Location'!$AD$6:$AD$33,'2-1. Quantitative data_Location'!B$54,'3-2. (Raw data) Scope2_Location'!$D$6:$D$33,'2-1. Quantitative data_Location'!$B60) -> 8618.768
A61: 2023년 | B61: PT. HJL INDO NETWORKS | C61: =D61+K61 -> 119.04118 | D61: =SUM(E61:J61) -> 100.83886 | E61: =SUMIFS('3-1. (Raw data) Scope 1'!$AT$6:$AT$79,'3-1. (Raw data) Scope 1'!$Y$6:$Y$79,'2-1. Quantitative data_Location'!$B$54,'3-1. (Raw data) Scope 1'!$D$6:$D$79,'2-1. Quantitative data_Location'!$B61,'3-1. (Raw data) Scope 1'!$AB$6:$AB$79,'2-1. Quantitative data_Location'!E$55) -> 100.83886 | F61: =SUMIFS('3-1. (Raw data) Scope 1'!$AT$6:$AT$79,'3-1. (Raw data) Scope 1'!$Y$6:$Y$79,'2-1. Quantitative data_Location'!$B$54,'3-1. (Raw data) Scope 1'!$D$6:$D$79,'2-1. Quantitative data_Location'!$B61,'3-1. (Raw data) Scope 1'!$AB$6:$AB$79,'2-1. Quantitative data_Location'!F$55) -> 0 | G61: =SUMIFS('3-1. (Raw data) Scope 1'!$AT$6:$AT$79,'3-1. (Raw data) Scope 1'!$Y$6:$Y$79,'2-1. Quantitative data_Location'!$B$54,'3-1. (Raw data) Scope 1'!$D$6:$D$79,'2-1. Quantitative data_Location'!$B61,'3-1. (Raw data) Scope 1'!$AB$6:$AB$79,'2-1. Quantitative data_Location'!G$55) -> 0 | H61: =SUMIFS('3-1. (Raw data) Scope 1'!$AT$6:$AT$79,'3-1. (Raw data) Scope 1'!$Y$6:$Y$79,'2-1. Quantitative data_Location'!$B$54,'3-1. (Raw data) Scope 1'!$D$6:$D$79,'2-1. Quantitative data_Location'!$B61,'3-1. (Raw data) Scope 1'!$AB$6:$AB$79,'2-1. Quantitative data_Location'!H$55) -> 0 | I61: =SUMIFS('3-1. (Raw data) Scope 1'!$AT$6:$AT$79,'3-1. (Raw data) Scope 1'!$Y$6:$Y$79,'2-1. Quantitative data_Location'!$B$54,'3-1. (Raw data) Scope 1'!$D$6:$D$79,'2-1. Quantitative data_Location'!$B61,'3-1. (Raw data) Scope 1'!$AB$6:$AB$79,'2-1. Quantitative data_Location'!I$55) -> 0 | J61: =SUMIFS('3-1. (Raw data) Scope 1'!$AT$6:$AT$79,'3-1. (Raw data) Scope 1'!$Y$6:$Y$79,'2-1. Quantitative data_Location'!$B$54,'3-1. (Raw data) Scope 1'!$D$6:$D$79,'2-1. Quantitative data_Location'!$B61,'3-1. (Raw data) Scope 1'!$AB$6:$AB$79,'2-1. Quantitative data_Location'!J$55) -> 0 | K61: =SUMIFS('3-2. (Raw data) Scope2_Location'!$AY$6:$AY$33,'3-2. (Raw data) Scope2_Location'!$AD$6:$AD$33,'2-1. Quantitative data_Location'!$B$54,'3-2. (Raw data) Scope2_Location'!$D$6:$D$33,'2-1. Quantitative data_Location'!$B61) -> 18.202314 | L61: =SUMIFS('3-2. (Raw data) Scope2_Location'!$AY$6:$AY$33,'3-2. (Raw data) Scope2_Location'!$AD$6:$AD$33,'2-1. Quantitative data_Location'!$B$54,'3-2. (Raw data) Scope2_Location'!$D$6:$D$33,'2-1. Quantitative data_Location'!$B61) -> 18.202314 | M61: =SUMIFS('3-2. (Raw data) Scope2_Location'!$AR$6:$AR$33,'3-2. (Raw data) Scope2_Location'!$AD$6:$AD$33,'2-1. Quantitative data_Location'!B$54,'3-2. (Raw data) Scope2_Location'!$D$6:$D$33,'2-1. Quantitative data_Location'!$B61) -> 20.9222
A62: 2023년 | B62: PT.HOGA REKSA GARMENT | C62: =D62+K62 -> 2117.4424 | D62: =SUM(E62:J62) -> 74.950319 | E62: =SUMIFS('3-1. (Raw data) Scope 1'!$AT$6:$AT$79,'3-1. (Raw data) Scope 1'!$Y$6:$Y$79,'2-1. Quantitative data_Location'!$B$54,'3-1. (Raw data) Scope 1'!$D$6:$D$79,'2-1. Quantitative data_Location'!$B62,'3-1. (Raw data) Scope 1'!$AB$6:$AB$79,'2-1. Quantitative data_Location'!E$55) -> 51.023519 | F62: =SUMIFS('3-1. (Raw data) Scope 1'!$AT$6:$AT$79,'3-1. (Raw data) Scope 1'!$Y$6:$Y$79,'2-1. Quantitative data_Location'!$B$54,'3-1. (Raw data) Scope 1'!$D$6:$D$79,'2-1. Quantitative data_Location'!$B62,'3-1. (Raw data) Scope 1'!$AB$6:$AB$79,'2-1. Quantitative data_Location'!F$55) -> 0 | G62: =SUMIFS('3-1. (Raw data) Scope 1'!$AT$6:$AT$79,'3-1. (Raw data) Scope 1'!$Y$6:$Y$79,'2-1. Quantitative data_Location'!$B$54,'3-1. (Raw data) Scope 1'!$D$6:$D$79,'2-1. Quantitative data_Location'!$B62,'3-1. (Raw data) Scope 1'!$AB$6:$AB$79,'2-1. Quantitative data_Location'!G$55) -> 23.9268 | H62: =SUMIFS('3-1. (Raw data) Scope 1'!$AT$6:$AT$79,'3-1. (Raw data) Scope 1'!$Y$6:$Y$79,'2-1. Quantitative data_Location'!$B$54,'3-1. (Raw data) Scope 1'!$D$6:$D$79,'2-1. Quantitative data_Location'!$B62,'3-1. (Raw data) Scope 1'!$AB$6:$AB$79,'2-1. Quantitative data_Location'!H$55) -> 0 | I62: =SUMIFS('3-1. (Raw data) Scope 1'!$AT$6:$AT$79,'3-1. (Raw data) Scope 1'!$Y$6:$Y$79,'2-1. Quantitative data_Location'!$B$54,'3-1. (Raw data) Scope 1'!$D$6:$D$79,'2-1. Quantitative data_Location'!$B62,'3-1. (Raw data) Scope 1'!$AB$6:$AB$79,'2-1. Quantitative data_Location'!I$55) -> 0 | J62: =SUMIFS('3-1. (Raw data) Scope 1'!$AT$6:$AT$79,'3-1. (Raw data) Scope 1'!$Y$6:$Y$79,'2-1. Quantitative data_Location'!$B$54,'3-1. (Raw data) Scope 1'!$D$6:$D$79,'2-1. Quantitative data_Location'!$B62,'3-1. (Raw data) Scope 1'!$AB$6:$AB$79,'2-1. Quantitative data_Location'!J$55) -> 0 | K62: =SUMIFS('3-2. (Raw data) Scope2_Location'!$AY$6:$AY$33,'3-2. (Raw data) Scope2_Location'!$AD$6:$AD$33,'2-1. Quantitative data_Location'!$B$54,'3-2. (Raw data) Scope2_Location'!$D$6:$D$33,'2-1. Quantitative data_Location'!$B62) -> 2042.492 | L62: =SUMIFS('3-2. (Raw data) Scope2_Location'!$AY$6:$AY$33,'3-2. (Raw data) Scope2_Location'!$AD$6:$AD$33,'2-1. Quantitative data_Location'!$B$54,'3-2. (Raw data) Scope2_Location'!$D$6:$D$33,'2-1. Quantitative data_Location'!$B62) -> 2042.492 | M62: =SUMIFS('3-2. (Raw data) Scope2_Location'!$AR$6:$AR$33,'3-2. (Raw data) Scope2_Location'!$AD$6:$AD$33,'2-1. Quantitative data_Location'!B$54,'3-2. (Raw data) Scope2_Location'!$D$6:$D$33,'2-1. Quantitative data_Location'!$B62) -> 2347.692
A63: 2023년 | B63: MFAFA Co., Ltd | C63: =D63+K63 -> 2.5755052 | D63: =SUM(E63:J63) -> 0 | E63: =SUMIFS('3-1. (Raw data) Scope 1'!$AT$6:$AT$79,'3-1. (Raw data) Scope 1'!$Y$6:$Y$79,'2-1. Quantitative data_Location'!$B$54,'3-1. (Raw data) Scope 1'!$D$6:$D$79,'2-1. Quantitative data_Location'!$B63,'3-1. (Raw data) Scope 1'!$AB$6:$AB$79,'2-1. Quantitative data_Location'!E$55) -> 0 | F63: =SUMIFS('3-1. (Raw data) Scope 1'!$AT$6:$AT$79,'3-1. (Raw data) Scope 1'!$Y$6:$Y$79,'2-1. Quantitative data_Location'!$B$54,'3-1. (Raw data) Scope 1'!$D$6:$D$79,'2-1. Quantitative data_Location'!$B63,'3-1. (Raw data) Scope 1'!$AB$6:$AB$79,'2-1. Quantitative data_Location'!F$55) -> 0 | G63: =SUMIFS('3-1. (Raw data) Scope 1'!$AT$6:$AT$79,'3-1. (Raw data) Scope 1'!$Y$6:$Y$79,'2-1. Quantitative data_Location'!$B$54,'3-1. (Raw data) Scope 1'!$D$6:$D$79,'2-1. Quantitative data_Location'!$B63,'3-1. (Raw data) Scope 1'!$AB$6:$AB$79,'2-1. Quantitative data_Location'!G$55) -> 0 | H63: =SUMIFS('3-1. (Raw data) Scope 1'!$AT$6:$AT$79,'3-1. (Raw data) Scope 1'!$Y$6:$Y$79,'2-1. Quantitative data_Location'!$B$54,'3-1. (Raw data) Scope 1'!$D$6:$D$79,'2-1. Quantitative data_Location'!$B63,'3-1. (Raw data) Scope 1'!$AB$6:$AB$79,'2-1. Quantitative data_Location'!H$55) -> 0 | I63: =SUMIFS('3-1. (Raw data) Scope 1'!$AT$6:$AT$79,'3-1. (Raw data) Scope 1'!$Y$6:$Y$79,'2-1. Quantitative data_Location'!$B$54,'3-1. (Raw data) Scope 1'!$D$6:$D$79,'2-1. Quantitative data_Location'!$B63,'3-1. (Raw data) Scope 1'!$AB$6:$AB$79,'2-1. Quantitative data_Location'!I$55) -> 0 | J63: =SUMIFS('3-1. (Raw data) Scope 1'!$AT$6:$AT$79,'3-1. (Raw data) Scope 1'!$Y$6:$Y$79,'2-1. Quantitative data_Location'!$B$54,'3-1. (Raw data) Scope 1'!$D$6:$D$79,'2-1. Quantitative data_Location'!$B63,'3-1. (Raw data) Scope 1'!$AB$6:$AB$79,'2-1. Quantitative data_Location'!J$55) -> 0 | K63: =SUMIFS('3-2. (Raw data) Scope2_Location'!$AY$6:$AY$33,'3-2. (Raw data) Scope2_Location'!$AD$6:$AD$33,'2-1. Quantitative data_Location'!$B$54,'3-2. (Raw data) Scope2_Location'!$D$6:$D$33,'2-1. Quantitative data_Location'!$B63) -> 2.5755052 | L63: =SUMIFS('3-2. (Raw data) Scope2_Location'!$AY$6:$AY$33,'3-2. (Raw data) Scope2_Location'!$AD$6:$AD$33,'2-1. Quantitative data_Location'!$B$54,'3-2. (Raw data) Scope2_Location'!$D$6:$D$33,'2-1. Quantitative data_Location'!$B63) -> 2.5755052 | M63: =SUMIFS('3-2. (Raw data) Scope2_Location'!$AR$6:$AR$33,'3-2. (Raw data) Scope2_Location'!$AD$6:$AD$33,'2-1. Quantitative data_Location'!B$54,'3-2. (Raw data) Scope2_Location'!$D$6:$D$33,'2-1. Quantitative data_Location'!$B63) -> 5.5154
A64: 2024년 | B64: 2024 | C64: Scope 1 + Scope 2 | D64: Scope 1 | K64: Scope 2
A65: 2024년 | D65: Scope 1 GHG Emissions by Facility | E65: {=_xlfn.TOROW(_xlfn.UNIQUE('3-1. (Raw data) Scope 1'!AB6:AB79))} -> Automotive gasoline (petrol) | F65: Industrial Wastes | G65: Biodiesel | H65: Liquefied Petroleum Gas (LPG) | I65: Gas / Diesel oil | J65: Hydrofluorocarbons(HFCs) | K65: Scope 2 GHG Emissions by Facility | L65: Electricity | M65: Electricity Consumption (MWh)
A66: 2024년 | B66: Total | C66: =D66+K66 -> 19499.897 | D66: =SUM(E66:J66) -> 5415.5677 | E66: =SUM(E67:E73) -> 945.71449 | F66: =SUM(F67:F73) -> 4052.7375 | G66: =SUM(G67:G73) -> 73.41294 | H66: =SUM(H67:H73) -> 7.477188 | I66: =SUM(I67:I73) -> 48.579677 | J66: =SUM(J67:J73) -> 287.6459 | K66: =SUM(K67:K73) -> 14084.329 | L66: =SUM(L67:L73) -> 14084.329 | M66: =SUM(M67:M73) -> 16374.658
A67: 2024년 | B67: HOJEON LIMITED Co., Ltd | C67: =D67+K67 -> 242.87393 | D67: =SUM(E67:J67) -> 58.215798 | E67: =SUMIFS('3-1. (Raw data) Scope 1'!$AT$6:$AT$79,'3-1. (Raw data) Scope 1'!$Y$6:$Y$79,'2-1. Quantitative data_Location'!$B$64,'3-1. (Raw data) Scope 1'!$D$6:$D$79,'2-1. Quantitative data_Location'!$B67,'3-1. (Raw data) Scope 1'!$AB$6:$AB$79,'2-1. Quantitative data_Location'!E$65) -> 58.215798 | F67: =SUMIFS('3-1. (Raw data) Scope 1'!$AT$6:$AT$79,'3-1. (Raw data) Scope 1'!$Y$6:$Y$79,'2-1. Quantitative data_Location'!$B$64,'3-1. (Raw data) Scope 1'!$D$6:$D$79,'2-1. Quantitative data_Location'!$B67,'3-1. (Raw data) Scope 1'!$AB$6:$AB$79,'2-1. Quantitative data_Location'!F$65) -> 0 | G67: =SUMIFS('3-1. (Raw data) Scope 1'!$AT$6:$AT$79,'3-1. (Raw data) Scope 1'!$Y$6:$Y$79,'2-1. Quantitative data_Location'!$B$64,'3-1. (Raw data) Scope 1'!$D$6:$D$79,'2-1. Quantitative data_Location'!$B67,'3-1. (Raw data) Scope 1'!$AB$6:$AB$79,'2-1. Quantitative data_Location'!G$65) -> 0 | H67: =SUMIFS('3-1. (Raw data) Scope 1'!$AT$6:$AT$79,'3-1. (Raw data) Scope 1'!$Y$6:$Y$79,'2-1. Quantitative data_Location'!$B$64,'3-1. (Raw data) Scope 1'!$D$6:$D$79,'2-1. Quantitative data_Location'!$B67,'3-1. (Raw data) Scope 1'!$AB$6:$AB$79,'2-1. Quantitative data_Location'!H$65) -> 0 | I67: =SUMIFS('3-1. (Raw data) Scope 1'!$AT$6:$AT$79,'3-1. (Raw data) Scope 1'!$Y$6:$Y$79,'2-1. Quantitative data_Location'!$B$64,'3-1. (Raw data) Scope 1'!$D$6:$D$79,'2-1. Quantitative data_Location'!$B67,'3-1. (Raw data) Scope 1'!$AB$6:$AB$79,'2-1. Quantitative data_Location'!I$65) -> 0 | J67: =SUMIFS('3-1. (Raw data) Scope 1'!$AT$6:$AT$79,'3-1. (Raw data) Scope 1'!$Y$6:$Y$79,'2-1. Quantitative data_Location'!$B$64,'3-1. (Raw data) Scope 1'!$D$6:$D$79,'2-1. Quantitative data_Location'!$B67,'3-1. (Raw data) Scope 1'!$AB$6:$AB$79,'2-1. Quantitative data_Location'!J$65) -> 0 | K67: =SUMIFS('3-2. (Raw data) Scope2_Location'!$AY$6:$AY$33,'3-2. (Raw data) Scope2_Location'!$AD$6:$AD$33,'2-1. Quantitative data_Location'!$B$64,'3-2. (Raw data) Scope2_Location'!$D$6:$D$33,'2-1. Quantitative data_Location'!$B67) -> 184.65813 | L67: =SUMIFS('3-2. (Raw data) Scope2_Location'!$AY$6:$AY$33,'3-2. (Raw data) Scope2_Location'!$AD$6:$AD$33,'2-1. Quantitative data_Location'!$B$64,'3-2. (Raw data) Scope2_Location'!$D$6:$D$33,'2-1. Quantitative data_Location'!$B67) -> 184.65813 | M67: =SUMIFS('3-2. (Raw data) Scope2_Location'!$AR$6:$AR$33,'3-2. (Raw data) Scope2_Location'!$AD$6:$AD$33,'2-1. Quantitative data_Location'!B$64,'3-2. (Raw data) Scope2_Location'!$D$6:$D$33,'2-1. Quantitative data_Location'!$B67) -> 395.44221
A68: 2024년 | B68: KAHOINDAH CITRAGARMENT | C68: =D68+K68 -> 2205.9967 | D68: =SUM(E68:J68) -> 877.44929 | E68: =SUMIFS('3-1. (Raw data) Scope 1'!$AT$6:$AT$79,'3-1. (Raw data) Scope 1'!$Y$6:$Y$79,'2-1. Quantitative data_Location'!$B$64,'3-1. (Raw data) Scope 1'!$D$6:$D$79,'2-1. Quantitative data_Location'!$B68,'3-1. (Raw data) Scope 1'!$AB$6:$AB$79,'2-1. Quantitative data_Location'!E$65) -> 46.591949 | F68: =SUMIFS('3-1. (Raw data) Scope 1'!$AT$6:$AT$79,'3-1. (Raw data) Scope 1'!$Y$6:$Y$79,'2-1. Quantitative data_Location'!$B$64,'3-1. (Raw data) Scope 1'!$D$6:$D$79,'2-1. Quantitative data_Location'!$B68,'3-1. (Raw data) Scope 1'!$AB$6:$AB$79,'2-1. Quantitative data_Location'!F$65) -> 827.64421 | G68: =SUMIFS('3-1. (Raw data) Scope 1'!$AT$6:$AT$79,'3-1. (Raw data) Scope 1'!$Y$6:$Y$79,'2-1. Quantitative data_Location'!$B$64,'3-1. (Raw data) Scope 1'!$D$6:$D$79,'2-1. Quantitative data_Location'!$B68,'3-1. (Raw data) Scope 1'!$AB$6:$AB$79,'2-1. Quantitative data_Location'!G$65) -> 2.7112741 | H68: =SUMIFS('3-1. (Raw data) Scope 1'!$AT$6:$AT$79,'3-1. (Raw data) Scope 1'!$Y$6:$Y$79,'2-1. Quantitative data_Location'!$B$64,'3-1. (Raw data) Scope 1'!$D$6:$D$79,'2-1. Quantitative data_Location'!$B68,'3-1. (Raw data) Scope 1'!$AB$6:$AB$79,'2-1. Quantitative data_Location'!H$65) -> 0.50184933 | I68: =SUMIFS('3-1. (Raw data) Scope 1'!$AT$6:$AT$79,'3-1. (Raw data) Scope 1'!$Y$6:$Y$79,'2-1. Quantitative data_Location'!$B$64,'3-1. (Raw data) Scope 1'!$D$6:$D$79,'2-1. Quantitative data_Location'!$B68,'3-1. (Raw data) Scope 1'!$AB$6:$AB$79,'2-1. Quantitative data_Location'!I$65) -> 0 | J68: =SUMIFS('3-1. (Raw data) Scope 1'!$AT$6:$AT$79,'3-1. (Raw data) Scope 1'!$Y$6:$Y$79,'2-1. Quantitative data_Location'!$B$64,'3-1. (Raw data) Scope 1'!$D$6:$D$79,'2-1. Quantitative data_Location'!$B68,'3-1. (Raw data) Scope 1'!$AB$6:$AB$79,'2-1. Quantitative data_Location'!J$65) -> 0 | K68: =SUMIFS('3-2. (Raw data) Scope2_Location'!$AY$6:$AY$33,'3-2. (Raw data) Scope2_Location'!$AD$6:$AD$33,'2-1. Quantitative data_Location'!$B$64,'3-2. (Raw data) Scope2_Location'!$D$6:$D$33,'2-1. Quantitative data_Location'!$B68) -> 1328.5474 | L68: =SUMIFS('3-2. (Raw data) Scope2_Location'!$AY$6:$AY$33,'3-2. (Raw data) Scope2_Location'!$AD$6:$AD$33,'2-1. Quantitative data_Location'!$B$64,'3-2. (Raw data) Scope2_Location'!$D$6:$D$33,'2-1. Quantitative data_Location'!$B68) -> 1328.5474 | M68: =SUMIFS('3-2. (Raw data) Scope2_Location'!$AR$6:$AR$33,'3-2. (Raw data) Scope2_Location'!$AD$6:$AD$33,'2-1. Quantitative data_Location'!B$64,'3-2. (Raw data) Scope2_Location'!$D$6:$D$33,'2-1. Quantitative data_Location'!$B68) -> 1527.066
A69: 2024년 | B69: PT. YONGJIN JAVASUKA GARMENT (1공장) | C69: =D69+K69 -> 2680.1847 | D69: =SUM(E69:J69) -> 1334.7981 | E69: =SUMIFS('3-1. (Raw data) Scope 1'!$AT$6:$AT$79,'3-1. (Raw data) Scope 1'!$Y$6:$Y$79,'2-1. Quantitative data_Location'!$B$64,'3-1. (Raw data) Scope 1'!$D$6:$D$79,'2-1. Quantitative data_Location'!$B69,'3-1. (Raw data) Scope 1'!$AB$6:$AB$79,'2-1. Quantitative data_Location'!E$65) -> 140.07552 | F69: =SUMIFS('3-1. (Raw data) Scope 1'!$AT$6:$AT$79,'3-1. (Raw data) Scope 1'!$Y$6:$Y$79,'2-1. Quantitative data_Location'!$B$64,'3-1. (Raw data) Scope 1'!$D$6:$D$79,'2-1. Quantitative data_Location'!$B69,'3-1. (Raw data) Scope 1'!$AB$6:$AB$79,'2-1. Quantitative data_Location'!F$65) -> 1149.1249 | G69: =SUMIFS('3-1. (Raw data) Scope 1'!$AT$6:$AT$79,'3-1. (Raw data) Scope 1'!$Y$6:$Y$79,'2-1. Quantitative data_Location'!$B$64,'3-1. (Raw data) Scope 1'!$D$6:$D$79,'2-1. Quantitative data_Location'!$B69,'3-1. (Raw data) Scope 1'!$AB$6:$AB$79,'2-1. Quantitative data_Location'!G$65) -> 0 | H69: =SUMIFS('3-1. (Raw data) Scope 1'!$AT$6:$AT$79,'3-1. (Raw data) Scope 1'!$Y$6:$Y$79,'2-1. Quantitative data_Location'!$B$64,'3-1. (Raw data) Scope 1'!$D$6:$D$79,'2-1. Quantitative data_Location'!$B69,'3-1. (Raw data) Scope 1'!$AB$6:$AB$79,'2-1. Quantitative data_Location'!H$65) -> 2.6041798 | I69: =SUMIFS('3-1. (Raw data) Scope 1'!$AT$6:$AT$79,'3-1. (Raw data) Scope 1'!$Y$6:$Y$79,'2-1. Quantitative data_Location'!$B$64,'3-1. (Raw data) Scope 1'!$D$6:$D$79,'2-1. Quantitative data_Location'!$B69,'3-1. (Raw data) Scope 1'!$AB$6:$AB$79,'2-1. Quantitative data_Location'!I$65) -> 9.1196506 | J69: =SUMIFS('3-1. (Raw data) Scope 1'!$AT$6:$AT$79,'3-1. (Raw data) Scope 1'!$Y$6:$Y$79,'2-1. Quantitative data_Location'!$B$64,'3-1. (Raw data) Scope 1'!$D$6:$D$79,'2-1. Quantitative data_Location'!$B69,'3-1. (Raw data) Scope 1'!$AB$6:$AB$79,'2-1. Quantitative data_Location'!J$65) -> 33.8738 | K69: =SUMIFS('3-2. (Raw data) Scope2_Location'!$AY$6:$AY$33,'3-2. (Raw data) Scope2_Location'!$AD$6:$AD$33,'2-1. Quantitative data_Location'!$B$64,'3-2. (Raw data) Scope2_Location'!$D$6:$D$33,'2-1. Quantitative data_Location'!$B69) -> 1345.3866 | L69: =SUMIFS('3-2. (Raw data) Scope2_Location'!$AY$6:$AY$33,'3-2. (Raw data) Scope2_Location'!$AD$6:$AD$33,'2-1. Quantitative data_Location'!$B$64,'3-2. (Raw data) Scope2_Location'!$D$6:$D$33,'2-1. Quantitative data_Location'!$B69) -> 1345.3866 | M69: =SUMIFS('3-2. (Raw data) Scope2_Location'!$AR$6:$AR$33,'3-2. (Raw data) Scope2_Location'!$AD$6:$AD$33,'2-1. Quantitative data_Location'!B$64,'3-2. (Raw data) Scope2_Location'!$D$6:$D$33,'2-1. Quantitative data_Location'!$B69) -> 1546.4214
A70: 2024년 | B70: PT. YONGJIN JAVASUKA GARMENT (2,3공장) | C70: =D70+K70 -> 11041.413 | D70: =SUM(E70:J70) -> 2918.3443 | E70: =SUMIFS('3-1. (Raw data) Scope 1'!$AT$6:$AT$79,'3-1. (Raw data) Scope 1'!$Y$6:$Y$79,'2-1. Quantitative data_Location'!$B$64,'3-1. (Raw data) Scope 1'!$D$6:$D$79,'2-1. Quantitative data_Location'!$B70,'3-1. (Raw data) Scope 1'!$AB$6:$AB$79,'2-1. Quantitative data_Location'!E$65) -> 544.77263 | F70: =SUMIFS('3-1. (Raw data) Scope 1'!$AT$6:$AT$79,'3-1. (Raw data) Scope 1'!$Y$6:$Y$79,'2-1. Quantitative data_Location'!$B$64,'3-1. (Raw data) Scope 1'!$D$6:$D$79,'2-1. Quantitative data_Location'!$B70,'3-1. (Raw data) Scope 1'!$AB$6:$AB$79,'2-1. Quantitative data_Location'!F$65) -> 2075.9684 | G70: =SUMIFS('3-1. (Raw data) Scope 1'!$AT$6:$AT$79,'3-1. (Raw data) Scope 1'!$Y$6:$Y$79,'2-1. Quantitative data_Location'!$B$64,'3-1. (Raw data) Scope 1'!$D$6:$D$79,'2-1. Quantitative data_Location'!$B70,'3-1. (Raw data) Scope 1'!$AB$6:$AB$79,'2-1. Quantitative data_Location'!G$65) -> 0 | H70: =SUMIFS('3-1. (Raw data) Scope 1'!$AT$6:$AT$79,'3-1. (Raw data) Scope 1'!$Y$6:$Y$79,'2-1. Quantitative data_Location'!$B$64,'3-1. (Raw data) Scope 1'!$D$6:$D$79,'2-1. Quantitative data_Location'!$B70,'3-1. (Raw data) Scope 1'!$AB$6:$AB$79,'2-1. Quantitative data_Location'!H$65) -> 4.3711589 | I70: =SUMIFS('3-1. (Raw data) Scope 1'!$AT$6:$AT$79,'3-1. (Raw data) Scope 1'!$Y$6:$Y$79,'2-1. Quantitative data_Location'!$B$64,'3-1. (Raw data) Scope 1'!$D$6:$D$79,'2-1. Quantitative data_Location'!$B70,'3-1. (Raw data) Scope 1'!$AB$6:$AB$79,'2-1. Quantitative data_Location'!I$65) -> 39.460027 | J70: =SUMIFS('3-1. (Raw data) Scope 1'!$AT$6:$AT$79,'3-1. (Raw data) Scope 1'!$Y$6:$Y$79,'2-1. Quantitative data_Location'!$B$64,'3-1. (Raw data) Scope 1'!$D$6:$D$79,'2-1. Quantitative data_Location'!$B70,'3-1. (Raw data) Scope 1'!$AB$6:$AB$79,'2-1. Quantitative data_Location'!J$65) -> 253.7721 | K70: =SUMIFS('3-2. (Raw data) Scope2_Location'!$AY$6:$AY$33,'3-2. (Raw data) Scope2_Location'!$AD$6:$AD$33,'2-1. Quantitative data_Location'!$B$64,'3-2. (Raw data) Scope2_Location'!$D$6:$D$33,'2-1. Quantitative data_Location'!$B70) -> 8123.0689 | L70: =SUMIFS('3-2. (Raw data) Scope2_Location'!$AY$6:$AY$33,'3-2. (Raw data) Scope2_Location'!$AD$6:$AD$33,'2-1. Quantitative data_Location'!$B$64,'3-2. (Raw data) Scope2_Location'!$D$6:$D$33,'2-1. Quantitative data_Location'!$B70) -> 8123.0689 | M70: =SUMIFS('3-2. (Raw data) Scope2_Location'!$AR$6:$AR$33,'3-2. (Raw data) Scope2_Location'!$AD$6:$AD$33,'2-1. Quantitative data_Location'!B$64,'3-2. (Raw data) Scope2_Location'!$D$6:$D$33,'2-1. Quantitative data_Location'!$B70) -> 9336.8608
A71: 2024년 | B71: PT. HJL INDO NETWORKS | C71: =D71+K71 -> 128.43711 | D71: =SUM(E71:J71) -> 110.40541 | E71: =SUMIFS('3-1. (Raw data) Scope 1'!$AT$6:$AT$79,'3-1. (Raw data) Scope 1'!$Y$6:$Y$79,'2-1. Quantitative data_Location'!$B$64,'3-1. (Raw data) Scope 1'!$D$6:$D$79,'2-1. Quantitative data_Location'!$B71,'3-1. (Raw data) Scope 1'!$AB$6:$AB$79,'2-1. Quantitative data_Location'!E$65) -> 110.40541 | F71: =SUMIFS('3-1. (Raw data) Scope 1'!$AT$6:$AT$79,'3-1. (Raw data) Scope 1'!$Y$6:$Y$79,'2-1. Quantitative data_Location'!$B$64,'3-1. (Raw data) Scope 1'!$D$6:$D$79,'2-1. Quantitative data_Location'!$B71,'3-1. (Raw data) Scope 1'!$AB$6:$AB$79,'2-1. Quantitative data_Location'!F$65) -> 0 | G71: =SUMIFS('3-1. (Raw data) Scope 1'!$AT$6:$AT$79,'3-1. (Raw data) Scope 1'!$Y$6:$Y$79,'2-1. Quantitative data_Location'!$B$64,'3-1. (Raw data) Scope 1'!$D$6:$D$79,'2-1. Quantitative data_Location'!$B71,'3-1. (Raw data) Scope 1'!$AB$6:$AB$79,'2-1. Quantitative data_Location'!G$65) -> 0 | H71: =SUMIFS('3-1. (Raw data) Scope 1'!$AT$6:$AT$79,'3-1. (Raw data) Scope 1'!$Y$6:$Y$79,'2-1. Quantitative data_Location'!$B$64,'3-1. (Raw data) Scope 1'!$D$6:$D$79,'2-1. Quantitative data_Location'!$B71,'3-1. (Raw data) Scope 1'!$AB$6:$AB$79,'2-1. Quantitative data_Location'!H$65) -> 0 | I71: =SUMIFS('3-1. (Raw data) Scope 1'!$AT$6:$AT$79,'3-1. (Raw data) Scope 1'!$Y$6:$Y$79,'2-1. Quantitative data_Location'!$B$64,'3-1. (Raw data) Scope 1'!$D$6:$D$79,'2-1. Quantitative data_Location'!$B71,'3-1. (Raw data) Scope 1'!$AB$6:$AB$79,'2-1. Quantitative data_Location'!I$65) -> 0 | J71: =SUMIFS('3-1. (Raw data) Scope 1'!$AT$6:$AT$79,'3-1. (Raw data) Scope 1'!$Y$6:$Y$79,'2-1. Quantitative data_Location'!$B$64,'3-1. (Raw data) Scope 1'!$D$6:$D$79,'2-1. Quantitative data_Location'!$B71,'3-1. (Raw data) Scope 1'!$AB$6:$AB$79,'2-1. Quantitative data_Location'!J$65) -> 0 | K71: =SUMIFS('3-2. (Raw data) Scope2_Location'!$AY$6:$AY$33,'3-2. (Raw data) Scope2_Location'!$AD$6:$AD$33,'2-1. Quantitative data_Location'!$B$64,'3-2. (Raw data) Scope2_Location'!$D$6:$D$33,'2-1. Quantitative data_Location'!$B71) -> 18.031707 | L71: =SUMIFS('3-2. (Raw data) Scope2_Location'!$AY$6:$AY$33,'3-2. (Raw data) Scope2_Location'!$AD$6:$AD$33,'2-1. Quantitative data_Location'!$B$64,'3-2. (Raw data) Scope2_Location'!$D$6:$D$33,'2-1. Quantitative data_Location'!$B71) -> 18.031707 | M71: =SUMIFS('3-2. (Raw data) Scope2_Location'!$AR$6:$AR$33,'3-2. (Raw data) Scope2_Location'!$AD$6:$AD$33,'2-1. Quantitative data_Location'!B$64,'3-2. (Raw data) Scope2_Location'!$D$6:$D$33,'2-1. Quantitative data_Location'!$B71) -> 20.7261
A72: 2024년 | B72: PT.HOGA REKSA GARMENT | C72: =D72+K72 -> 3198.3873 | D72: =SUM(E72:J72) -> 116.35485 | E72: =SUMIFS('3-1. (Raw data) Scope 1'!$AT$6:$AT$79,'3-1. (Raw data) Scope 1'!$Y$6:$Y$79,'2-1. Quantitative data_Location'!$B$64,'3-1. (Raw data) Scope 1'!$D$6:$D$79,'2-1. Quantitative data_Location'!$B72,'3-1. (Raw data) Scope 1'!$AB$6:$AB$79,'2-1. Quantitative data_Location'!E$65) -> 45.653187 | F72: =SUMIFS('3-1. (Raw data) Scope 1'!$AT$6:$AT$79,'3-1. (Raw data) Scope 1'!$Y$6:$Y$79,'2-1. Quantitative data_Location'!$B$64,'3-1. (Raw data) Scope 1'!$D$6:$D$79,'2-1. Quantitative data_Location'!$B72,'3-1. (Raw data) Scope 1'!$AB$6:$AB$79,'2-1. Quantitative data_Location'!F$65) -> 0 | G72: =SUMIFS('3-1. (Raw data) Scope 1'!$AT$6:$AT$79,'3-1. (Raw data) Scope 1'!$Y$6:$Y$79,'2-1. Quantitative data_Location'!$B$64,'3-1. (Raw data) Scope 1'!$D$6:$D$79,'2-1. Quantitative data_Location'!$B72,'3-1. (Raw data) Scope 1'!$AB$6:$AB$79,'2-1. Quantitative data_Location'!G$65) -> 70.701666 | H72: =SUMIFS('3-1. (Raw data) Scope 1'!$AT$6:$AT$79,'3-1. (Raw data) Scope 1'!$Y$6:$Y$79,'2-1. Quantitative data_Location'!$B$64,'3-1. (Raw data) Scope 1'!$D$6:$D$79,'2-1. Quantitative data_Location'!$B72,'3-1. (Raw data) Scope 1'!$AB$6:$AB$79,'2-1. Quantitative data_Location'!H$65) -> 0 | I72: =SUMIFS('3-1. (Raw data) Scope 1'!$AT$6:$AT$79,'3-1. (Raw data) Scope 1'!$Y$6:$Y$79,'2-1. Quantitative data_Location'!$B$64,'3-1. (Raw data) Scope 1'!$D$6:$D$79,'2-1. Quantitative data_Location'!$B72,'3-1. (Raw data) Scope 1'!$AB$6:$AB$79,'2-1. Quantitative data_Location'!I$65) -> 0 | J72: =SUMIFS('3-1. (Raw data) Scope 1'!$AT$6:$AT$79,'3-1. (Raw data) Scope 1'!$Y$6:$Y$79,'2-1. Quantitative data_Location'!$B$64,'3-1. (Raw data) Scope 1'!$D$6:$D$79,'2-1. Quantitative data_Location'!$B72,'3-1. (Raw data) Scope 1'!$AB$6:$AB$79,'2-1. Quantitative data_Location'!J$65) -> 0 | K72: =SUMIFS('3-2. (Raw data) Scope2_Location'!$AY$6:$AY$33,'3-2. (Raw data) Scope2_Location'!$AD$6:$AD$33,'2-1. Quantitative data_Location'!$B$64,'3-2. (Raw data) Scope2_Location'!$D$6:$D$33,'2-1. Quantitative data_Location'!$B72) -> 3082.0324 | L72: =SUMIFS('3-2. (Raw data) Scope2_Location'!$AY$6:$AY$33,'3-2. (Raw data) Scope2_Location'!$AD$6:$AD$33,'2-1. Quantitative data_Location'!$B$64,'3-2. (Raw data) Scope2_Location'!$D$6:$D$33,'2-1. Quantitative data_Location'!$B72) -> 3082.0324 | M72: =SUMIFS('3-2. (Raw data) Scope2_Location'!$AR$6:$AR$33,'3-2. (Raw data) Scope2_Location'!$AD$6:$AD$33,'2-1. Quantitative data_Location'!B$64,'3-2. (Raw data) Scope2_Location'!$D$6:$D$33,'2-1. Quantitative data_Location'!$B72) -> 3542.566
A73: 2024년 | B73: MFAFA Co., Ltd | C73: =D73+K73 -> 2.6038034 | D73: =SUM(E73:J73) -> 0 | E73: =SUMIFS('3-1. (Raw data) Scope 1'!$AT$6:$AT$79,'3-1. (Raw data) Scope 1'!$Y$6:$Y$79,'2-1. Quantitative data_Location'!$B$64,'3-1. (Raw data) Scope 1'!$D$6:$D$79,'2-1. Quantitative data_Location'!$B73,'3-1. (Raw data) Scope 1'!$AB$6:$AB$79,'2-1. Quantitative data_Location'!E$65) -> 0 | F73: =SUMIFS('3-1. (Raw data) Scope 1'!$AT$6:$AT$79,'3-1. (Raw data) Scope 1'!$Y$6:$Y$79,'2-1. Quantitative data_Location'!$B$64,'3-1. (Raw data) Scope 1'!$D$6:$D$79,'2-1. Quantitative data_Location'!$B73,'3-1. (Raw data) Scope 1'!$AB$6:$AB$79,'2-1. Quantitative data_Location'!F$65) -> 0 | G73: =SUMIFS('3-1. (Raw data) Scope 1'!$AT$6:$AT$79,'3-1. (Raw data) Scope 1'!$Y$6:$Y$79,'2-1. Quantitative data_Location'!$B$64,'3-1. (Raw data) Scope 1'!$D$6:$D$79,'2-1. Quantitative data_Location'!$B73,'3-1. (Raw data) Scope 1'!$AB$6:$AB$79,'2-1. Quantitative data_Location'!G$65) -> 0 | H73: =SUMIFS('3-1. (Raw data) Scope 1'!$AT$6:$AT$79,'3-1. (Raw data) Scope 1'!$Y$6:$Y$79,'2-1. Quantitative data_Location'!$B$64,'3-1. (Raw data) Scope 1'!$D$6:$D$79,'2-1. Quantitative data_Location'!$B73,'3-1. (Raw data) Scope 1'!$AB$6:$AB$79,'2-1. Quantitative data_Location'!H$65) -> 0 | I73: =SUMIFS('3-1. (Raw data) Scope 1'!$AT$6:$AT$79,'3-1. (Raw data) Scope 1'!$Y$6:$Y$79,'2-1. Quantitative data_Location'!$B$64,'3-1. (Raw data) Scope 1'!$D$6:$D$79,'2-1. Quantitative data_Location'!$B73,'3-1. (Raw data) Scope 1'!$AB$6:$AB$79,'2-1. Quantitative data_Location'!I$65) -> 0 | J73: =SUMIFS('3-1. (Raw data) Scope 1'!$AT$6:$AT$79,'3-1. (Raw data) Scope 1'!$Y$6:$Y$79,'2-1. Quantitative data_Location'!$B$64,'3-1. (Raw data) Scope 1'!$D$6:$D$79,'2-1. Quantitative data_Location'!$B73,'3-1. (Raw data) Scope 1'!$AB$6:$AB$79,'2-1. Quantitative data_Location'!J$65) -> 0 | K73: =SUMIFS('3-2. (Raw data) Scope2_Location'!$AY$6:$AY$33,'3-2. (Raw data) Scope2_Location'!$AD$6:$AD$33,'2-1. Quantitative data_Location'!$B$64,'3-2. (Raw data) Scope2_Location'!$D$6:$D$33,'2-1. Quantitative data_Location'!$B73) -> 2.6038034 | L73: =SUMIFS('3-2. (Raw data) Scope2_Location'!$AY$6:$AY$33,'3-2. (Raw data) Scope2_Location'!$AD$6:$AD$33,'2-1. Quantitative data_Location'!$B$64,'3-2. (Raw data) Scope2_Location'!$D$6:$D$33,'2-1. Quantitative data_Location'!$B73) -> 2.6038034 | M73: =SUMIFS('3-2. (Raw data) Scope2_Location'!$AR$6:$AR$33,'3-2. (Raw data) Scope2_Location'!$AD$6:$AD$33,'2-1. Quantitative data_Location'!B$64,'3-2. (Raw data) Scope2_Location'!$D$6:$D$33,'2-1. Quantitative data_Location'!$B73) -> 5.576
B74: * No steam purchase has been recorded.

Sheet 2-2. Quantitative data_Market
B1: HOJEON LIMITED Scope 1,2 Emissions (tCO2eq) (2022~2024) / Market-based
B3: HOJEON LIMITED Annual GHG Emissions for Scope 1&2
B5: 구분 | C5: Scope 1+2 | D5: Scope 1 | H5: Scope 2
B6: Data Collection Year | C6: Total GHG Emissions (tCO2eq) | D6: Fuel Consumption (kg) | E6: Energy Consumption (MJ) | F6: GHG Emissions (tCO2eq) | G6: GHG Emissions Share (%) | H6: Energy Purchased (MJ) | I6: GHG Emissions (tCO2eq) | J6: GHG Emissions Share (%)
B7: 2022 | C7: =F7+I7 -> 17488.362 | D7: =SUMIF('3-1. (Raw data) Scope 1'!$Y:$Y,'2-2. Quantitative data_Market'!$B7,'3-1. (Raw data) Scope 1'!$AR:$AR) -> 1753340.4 | E7: =SUMIF('3-1. (Raw data) Scope 1'!$Y:$Y,'2-2. Quantitative data_Market'!$B7,'3-1. (Raw data) Scope 1'!$AS:$AS) -> 46194039 | F7: =SUMIF('3-1. (Raw data) Scope 1'!$Y:$Y,'2-2. Quantitative data_Market'!$B7,'3-1. (Raw data) Scope 1'!$AT:$AT) -> 5807.3723 | G7: =F7/$C7 -> 0.33207069 | H7: =SUMIF('3-3. (Raw data) Scope 2_Market'!$AD:$AD,'2-2. Quantitative data_Market'!$B7,'3-3. (Raw data) Scope 2_Market'!$AT:$AT) -> 49010653 | I7: =SUMIF('3-3. (Raw data) Scope 2_Market'!$AD:$AD,'2-2. Quantitative data_Market'!$B7,'3-3. (Raw data) Scope 2_Market'!$AY:$AY) -> 11680.989 | J7: =I7/$C7 -> 0.66792931
B8: 2023 | C8: =F8+I8 -> 17676.947 | D8: =SUMIF('3-1. (Raw data) Scope 1'!$Y:$Y,'2-2. Quantitative data_Market'!$B8,'3-1. (Raw data) Scope 1'!$AR:$AR) -> 1670455.1 | E8: =SUMIF('3-1. (Raw data) Scope 1'!$Y:$Y,'2-2. Quantitative data_Market'!$B8,'3-1. (Raw data) Scope 1'!$AS:$AS) -> 45214988 | F8: =SUMIF('3-1. (Raw data) Scope 1'!$Y:$Y,'2-2. Quantitative data_Market'!$B8,'3-1. (Raw data) Scope 1'!$AT:$AT) -> 5472.6179 | G8: =F8/$C8 -> 0.30959067 | H8: =SUMIF('3-3. (Raw data) Scope 2_Market'!$AD:$AD,'2-2. Quantitative data_Market'!$B8,'3-3. (Raw data) Scope 2_Market'!$AT:$AT) -> 51149870 | I8: =SUMIF('3-3. (Raw data) Scope 2_Market'!$AD:$AD,'2-2. Quantitative data_Market'!$B8,'3-3. (Raw data) Scope 2_Market'!$AY:$AY) -> 12204.329 | J8: =I8/$C8 -> 0.69040933
B9: 2024 | C9: =F9+I9 -> 18462.738 | D9: =SUMIF('3-1. (Raw data) Scope 1'!$Y:$Y,'2-2. Quantitative data_Market'!$B9,'3-1. (Raw data) Scope 1'!$AR:$AR) -> 1648587.9 | E9: =SUMIF('3-1. (Raw data) Scope 1'!$Y:$Y,'2-2. Quantitative data_Market'!$B9,'3-1. (Raw data) Scope 1'!$AS:$AS) -> 43372620 | F9: =SUMIF('3-1. (Raw data) Scope 1'!$Y:$Y,'2-2. Quantitative data_Market'!$B9,'3-1. (Raw data) Scope 1'!$AT:$AT) -> 5415.5677 | G9: =F9/$C9 -> 0.29332418 | H9: =SUMIF('3-3. (Raw data) Scope 2_Market'!$AD:$AD,'2-2. Quantitative data_Market'!$B9,'3-3. (Raw data) Scope 2_Market'!$AT:$AT) -> 54657081 | I9: =SUMIF('3-3. (Raw data) Scope 2_Market'!$AD:$AD,'2-2. Quantitative data_Market'!$B9,'3-3. (Raw data) Scope 2_Market'!$AY:$AY) -> 13047.171 | J9: =I9/$C9 -> 0.70667582
B11: HOJEON LIMITED GHG Emissions for Scope 1&2 by Facility
B13: 구분 | C13: Scope 1 + Scope 2 | F13: Scope 1 | I13: Scope 2
B14: Name of Facility | C14: 2022 | D14: 2023 | E14: 2024 | F14: 2022 | G14: 2023 | H14: 2024 | I14: 2022 | J14: 2023 | K14: 2024
B15: Total | C15: =SUM(C16:C22) -> 17488.362 | D15: =SUM(D16:D22) -> 17676.947 | E15: =SUM(E16:E22) -> 17134.191 | F15: =SUM(F16:F22) -> 5807.3723 | G15: =SUM(G16:G22) -> 5472.6179 | H15: =SUM(H16:H22) -> 5415.5677 | I15: =SUM(I16:I22) -> 11680.989 | J15: =SUM(J16:J22) -> 12204.329 | K15: =SUM(K16:K22) -> 11718.623
B16: HOJEON LIMITED Co., Ltd | C16: =F16+I16 -> 235.99585 | D16: =G16+J16 -> 239.15711 | E16: =H16+K16 -> 242.87393 | F16: =D47 -> 49.986937 | G16: =D57 -> 59.95623 | H16: =D67 -> 58.215798 | I16: =K47 -> 186.00891 | J16: =K57 -> 179.20088 | K16: =K67 -> 184.65813
B17: KAHOINDAH CITRAGARMENT | C17: =F17+I17 -> 2538.3389 | D17: =G17+J17 -> 2386.1475 | E17: =H17+K17 -> 877.44929 | F17: =D48 -> 1092.0335 | G17: =D58 -> 1049.9841 | H17: =D68 -> 877.44929 | I17: =K48 -> 1446.3054 | J17: =K58 -> 1336.1634 | K17: =K68 -> 0
B18: PT. YONGJIN JAVASUKA GARMENT (1공장) | C18: =F18+I18 -> 2622.4944 | D18: =G18+J18 -> 2504.7999 | E18: =H18+K18 -> 2549.6847 | F18: =D49 -> 1478.1033 | G18: =D59 -> 1377.433 | H18: =D69 -> 1334.7981 | I18: =K49 -> 1144.391 | J18: =K59 -> 1127.3669 | K18: =K69 -> 1214.8866
B19: PT. YONGJIN JAVASUKA GARMENT (2,3공장) | C19: =F19+I19 -> 9864.3183 | D19: =G19+J19 -> 10307.784 | E19: =H19+K19 -> 10134.755 | F19: =D50 -> 3051.6824 | G19: =D60 -> 2809.4554 | H19: =D70 -> 2918.3443 | I19: =K50 -> 6812.6359 | J19: =K60 -> 7498.3282 | K19: =K70 -> 7216.4106
B20: PT. HJL INDO NETWORKS | C20: =F20+I20 -> 91.09388 | D20: =G20+J20 -> 119.04118 | E20: =H20+K20 -> 128.43711 | F20: =D51 -> 71.458589 | G20: =D61 -> 100.83886 | H20: =D71 -> 110.40541 | I20: =K51 -> 19.635291 | J20: =K61 -> 18.202314 | K20: =K71 -> 18.031707
B21: PT.HOGA REKSA GARMENT | C21: =F21+I21 -> 2132.9814 | D21: =G21+J21 -> 2117.4424 | E21: =H21+K21 -> 3198.3873 | F21: =D52 -> 64.107488 | G21: =D62 -> 74.950319 | H21: =D72 -> 116.35485 | I21: =K52 -> 2068.8739 | J21: =K62 -> 2042.492 | K21: =K72 -> 3082.0324
B22: MFAFA Co., Ltd | C22: =F22+I22 -> 3.1390089 | D22: =G22+J22 -> 2.5755052 | E22: =H22+K22 -> 2.6038034 | F22: 0 | G22: 0 | H22: 0 | I22: =K53 -> 3.1390089 | J22: =K63 -> 2.5755052 | K22: =K73 -> 2.6038034
B23: * MFAFA Co., Ltd has been confirmed not to emit Scope 1 energy.
B25: GHG Emissions for Scope 1&2 by Energy Source (tCO2eq)
B27: Scope 1 | C27: Annual GHG Emissions (tCO2eq)
B28: Types of fuel | C28: 2022 | D28: 2023 | E28: 2024
B29: Total | C29: =SUM(C30:C35) -> 5807.3723 | D29: =SUM(D30:D35) -> 5472.6179 | E29: =SUM(E30:E35) -> 5415.5677
B30: {=_xlfn.UNIQUE('3-1. (Raw data) Scope 1'!AB6:AB79)} -> Automotive gasoline (petrol) | C30: =SUMIFS('3-1. (Raw data) Scope 1'!$AT$6:$AT$79,'3-1. (Raw data) Scope 1'!$Y$6:$Y$79,'2-2. Quantitative data_Market'!C$28,'3-1. (Raw data) Scope 1'!$AB$6:$AB$79,'2-2. Quantitative data_Market'!$B30) -> 1034.4686 | D30: =SUMIFS('3-1. (Raw data) Scope 1'!$AT$6:$AT$79,'3-1. (Raw data) Scope 1'!$Y$6:$Y$79,'2-2. Quantitative data_Market'!D$28,'3-1. (Raw data) Scope 1'!$AB$6:$AB$79,'2-2. Quantitative data_Market'!$B30) -> 1098.8887 | E30: =SUMIFS('3-1. (Raw data) Scope 1'!$AT$6:$AT$79,'3-1. (Raw data) Scope 1'!$Y$6:$Y$79,'2-2. Quantitative data_Market'!E$28,'3-1. (Raw data) Scope 1'!$AB$6:$AB$79,'2-2. Quantitative data_Market'!$B30) -> 945.71449
B31: Industrial Wastes | C31: =SUMIFS('3-1. (Raw data) Scope 1'!$AT$6:$AT$79,'3-1. (Raw data) Scope 1'!$Y$6:$Y$79,'2-2. Quantitative data_Market'!C$28,'3-1. (Raw data) Scope 1'!$AB$6:$AB$79,'2-2. Quantitative data_Market'!$B31) -> 4369.6399 | D31: =SUMIFS('3-1. (Raw data) Scope 1'!$AT$6:$AT$79,'3-1. (Raw data) Scope 1'!$Y$6:$Y$79,'2-2. Quantitative data_Market'!D$28,'3-1. (Raw data) Scope 1'!$AB$6:$AB$79,'2-2. Quantitative data_Market'!$B31) -> 3986.6566 | E31: =SUMIFS('3-1. (Raw data) Scope 1'!$AT$6:$AT$79,'3-1. (Raw data) Scope 1'!$Y$6:$Y$79,'2-2. Quantitative data_Market'!E$28,'3-1. (Raw data) Scope 1'!$AB$6:$AB$79,'2-2. Quantitative data_Market'!$B31) -> 4052.7375
B32: Biodiesel | C32: =SUMIFS('3-1. (Raw data) Scope 1'!$AT$6:$AT$79,'3-1. (Raw data) Scope 1'!$Y$6:$Y$79,'2-2. Quantitative data_Market'!C$28,'3-1. (Raw data) Scope 1'!$AB$6:$AB$79,'2-2. Quantitative data_Market'!$B32) -> 23.71627 | D32: =SUMIFS('3-1. (Raw data) Scope 1'!$AT$6:$AT$79,'3-1. (Raw data) Scope 1'!$Y$6:$Y$79,'2-2. Quantitative data_Market'!D$28,'3-1. (Raw data) Scope 1'!$AB$6:$AB$79,'2-2. Quantitative data_Market'!$B32) -> 26.422966 | E32: =SUMIFS('3-1. (Raw data) Scope 1'!$AT$6:$AT$79,'3-1. (Raw data) Scope 1'!$Y$6:$Y$79,'2-2. Quantitative data_Market'!E$28,'3-1. (Raw data) Scope 1'!$AB$6:$AB$79,'2-2. Quantitative data_Market'!$B32) -> 73.41294
B33: Liquefied Petroleum Gas (LPG) | C33: =SUMIFS('3-1. (Raw data) Scope 1'!$AT$6:$AT$79,'3-1. (Raw data) Scope 1'!$Y$6:$Y$79,'2-2. Quantitative data_Market'!C$28,'3-1. (Raw data) Scope 1'!$AB$6:$AB$79,'2-2. Quantitative data_Market'!$B33) -> 8.6025638 | D33: =SUMIFS('3-1. (Raw data) Scope 1'!$AT$6:$AT$79,'3-1. (Raw data) Scope 1'!$Y$6:$Y$79,'2-2. Quantitative data_Market'!D$28,'3-1. (Raw data) Scope 1'!$AB$6:$AB$79,'2-2. Quantitative data_Market'!$B33) -> 7.584198 | E33: =SUMIFS('3-1. (Raw data) Scope 1'!$AT$6:$AT$79,'3-1. (Raw data) Scope 1'!$Y$6:$Y$79,'2-2. Quantitative data_Market'!E$28,'3-1. (Raw data) Scope 1'!$AB$6:$AB$79,'2-2. Quantitative data_Market'!$B33) -> 7.477188
B34: Gas / Diesel oil | C34: =SUMIFS('3-1. (Raw data) Scope 1'!$AT$6:$AT$79,'3-1. (Raw data) Scope 1'!$Y$6:$Y$79,'2-2. Quantitative data_Market'!C$28,'3-1. (Raw data) Scope 1'!$AB$6:$AB$79,'2-2. Quantitative data_Market'!$B34) -> 51.544913 | D34: =SUMIFS('3-1. (Raw data) Scope 1'!$AT$6:$AT$79,'3-1. (Raw data) Scope 1'!$Y$6:$Y$79,'2-2. Quantitative data_Market'!D$28,'3-1. (Raw data) Scope 1'!$AB$6:$AB$79,'2-2. Quantitative data_Market'!$B34) -> 104.75457 | E34: =SUMIFS('3-1. (Raw data) Scope 1'!$AT$6:$AT$79,'3-1. (Raw data) Scope 1'!$Y$6:$Y$79,'2-2. Quantitative data_Market'!E$28,'3-1. (Raw data) Scope 1'!$AB$6:$AB$79,'2-2. Quantitative data_Market'!$B34) -> 48.579677
B35: Hydrofluorocarbons(HFCs) | C35: =SUMIFS('3-1. (Raw data) Scope 1'!$AT$6:$AT$79,'3-1. (Raw data) Scope 1'!$Y$6:$Y$79,'2-2. Quantitative data_Market'!C$28,'3-1. (Raw data) Scope 1'!$AB$6:$AB$79,'2-2. Quantitative data_Market'!$B35) -> 319.40005 | D35: =SUMIFS('3-1. (Raw data) Scope 1'!$AT$6:$AT$79,'3-1. (Raw data) Scope 1'!$Y$6:$Y$79,'2-2. Quantitative data_Market'!D$28,'3-1. (Raw data) Scope 1'!$AB$6:$AB$79,'2-2. Quantitative data_Market'!$B35) -> 248.3109 | E35: =SUMIFS('3-1. (Raw data) Scope 1'!$AT$6:$AT$79,'3-1. (Raw data) Scope 1'!$Y$6:$Y$79,'2-2. Quantitative data_Market'!E$28,'3-1. (Raw data) Scope 1'!$AB$6:$AB$79,'2-2. Quantitative data_Market'!$B35) -> 287.6459
B36: Scope 2 | C36: GHG Emissions (tCO2eq)
B37: Energy sources | C37: 2022 | D37: 2023 | E37: 2024
B38: Total | C38: =SUM(C39:C40) -> 11680.989 | D38: =SUM(D39:D40) -> 12204.329 | E38: =SUM(E39:E40) -> 13047.171
B39: Electricity | C39: =SUMIFS('3-2. (Raw data) Scope2_Location'!$AY:$AY,'3-2. (Raw data) Scope2_Location'!$AD:$AD,'2-2. Quantitative data_Market'!C$37,'3-2. (Raw data) Scope2_Location'!$AE:$AE,$B39) -> 11680.989 | D39: =SUMIFS('3-2. (Raw data) Scope2_Location'!$AY:$AY,'3-2. (Raw data) Scope2_Location'!$AD:$AD,'2-2. Quantitative data_Market'!D$37,'3-2. (Raw data) Scope2_Location'!$AE:$AE,$B39) -> 12204.329 | E39: =SUMIFS('3-3. (Raw data) Scope 2_Market'!$AY:$AY,'3-3. (Raw data) Scope 2_Market'!$AD:$AD,'2-2. Quantitative data_Market'!E$37,'3-3. (Raw data) Scope 2_Market'!$AE:$AE,$B39) -> 13047.171
B40: Steam | C40: =SUMIFS('3-3. (Raw data) Scope 2_Market'!$AY:$AY,'3-3. (Raw data) Scope 2_Market'!$AD:$AD,'2-2. Quantitative data_Market'!C$37,'3-3. (Raw data) Scope 2_Market'!$AE:$AE,$B40) -> 0 | D40: =SUMIFS('3-2. (Raw data) Scope2_Location'!$AY:$AY,'3-2. (Raw data) Scope2_Location'!$AD:$AD,'2-2. Quantitative data_Market'!D$37,'3-2. (Raw data) Scope2_Location'!$AE:$AE,$B40) -> 0 | E40: =SUMIFS('3-2. (Raw data) Scope2_Location'!$AY:$AY,'3-2. (Raw data) Scope2_Location'!$AD:$AD,'2-2. Quantitative data_Market'!E$37,'3-2. (Raw data) Scope2_Location'!$AE:$AE,$B40) -> 0
B42: GHG Emissions for Scope 1&2 by Fuel Type and Facility (tCO2eq)
A44: 2022년 | B44: 2022 | C44: Scope 1 + Scope 2 | D44: Scope 1 | K44: Scope 2
A45: 2022년 | D45: Scope 1 GHG Emissions by Facility | E45: {=_xlfn.TOROW(_xlfn.UNIQUE('3-1. (Raw data) Scope 1'!AB6:AB79))} -> Automotive gasoline (petrol) | F45: Industrial Wastes | G45: Biodiesel | H45: Liquefied Petroleum Gas (LPG) | I45: Gas / Diesel oil | J45: Hydrofluorocarbons(HFCs) | K45: Scope 2 GHG Emissions by Facility | L45: Electricity | M45: Electricity Consumption (MWh)
A46: 2022년 | B46: Total | C46: =D46+K46 -> 17488.362 | D46: =SUM(E46:J46) -> 5807.3723 | E46: =SUM(E47:E53) -> 1034.4686 | F46: =SUM(F47:F53) -> 4369.6399 | G46: =SUM(G47:G53) -> 23.71627 | H46: =SUM(H47:H53) -> 8.6025638 | I46: =SUM(I47:I53) -> 51.544913 | J46: =SUM(J47:J53) -> 319.40005 | K46: =SUM(K47:K53) -> 11680.989 | L46: =SUM(L47:L53) -> 11680.989 | M46: =SUM(M47:M53) -> 13614.07
A47: 2022년 | B47: {=_xlfn.UNIQUE('3-2. (Raw data) Scope2_Location'!$D$6:$D$33)} -> HOJEON LIMITED Co., Ltd | C47: =D47+K47 -> 235.99585 | D47: =SUM(E47:J47) -> 49.986937 | E47: =SUMIFS('3-1. (Raw data) Scope 1'!$AT$6:$AT$79,'3-1. (Raw data) Scope 1'!$Y$6:$Y$79,'2-2. Quantitative data_Market'!$B$44,'3-1. (Raw data) Scope 1'!$D$6:$D$79,'2-2. Quantitative data_Market'!$B47,'3-1. (Raw data) Scope 1'!$AB$6:$AB$79,'2-2. Quantitative data_Market'!E$45) -> 49.986937 | F47: =SUMIFS('3-1. (Raw data) Scope 1'!$AT$6:$AT$79,'3-1. (Raw data) Scope 1'!$Y$6:$Y$79,'2-2. Quantitative data_Market'!$B$44,'3-1. (Raw data) Scope 1'!$D$6:$D$79,'2-2. Quantitative data_Market'!$B47,'3-1. (Raw data) Scope 1'!$AB$6:$AB$79,'2-2. Quantitative data_Market'!F$45) -> 0 | G47: =SUMIFS('3-1. (Raw data) Scope 1'!$AT$6:$AT$79,'3-1. (Raw data) Scope 1'!$Y$6:$Y$79,'2-2. Quantitative data_Market'!$B$44,'3-1. (Raw data) Scope 1'!$D$6:$D$79,'2-2. Quantitative data_Market'!$B47,'3-1. (Raw data) Scope 1'!$AB$6:$AB$79,'2-2. Quantitative data_Market'!G$45) -> 0 | H47: =SUMIFS('3-1. (Raw data) Scope 1'!$AT$6:$AT$79,'3-1. (Raw data) Scope 1'!$Y$6:$Y$79,'2-2. Quantitative data_Market'!$B$44,'3-1. (Raw data) Scope 1'!$D$6:$D$79,'2-2. Quantitative data_Market'!$B47,'3-1. (Raw data) Scope 1'!$AB$6:$AB$79,'2-2. Quantitative data_Market'!H$45) -> 0 | I47: =SUMIFS('3-1. (Raw data) Scope 1'!$AT$6:$AT$79,'3-1. (Raw data) Scope 1'!$Y$6:$Y$79,'2-2. Quantitative data_Market'!$B$44,'3-1. (Raw data) Scope 1'!$D$6:$D$79,'2-2. Quantitative data_Market'!$B47,'3-1. (Raw data) Scope 1'!$AB$6:$AB$79,'2-2. Quantitative data_Market'!I$45) -> 0 | J47: =SUMIFS('3-1. (Raw data) Scope 1'!$AT$6:$AT$79,'3-1. (Raw data) Scope 1'!$Y$6:$Y$79,'2-2. Quantitative data_Market'!$B$44,'3-1. (Raw data) Scope 1'!$D$6:$D$79,'2-2. Quantitative data_Market'!$B47,'3-1. (Raw data) Scope 1'!$AB$6:$AB$79,'2-2. Quantitative data_Market'!J$45) -> 0 | K47: =SUMIFS('3-2. (Raw data) Scope2_Location'!$AY$6:$AY$33,'3-2. (Raw data) Scope2_Location'!$AD$6:$AD$33,'2-2. Quantitative data_Market'!B$44,'3-2. (Raw data) Scope2_Location'!$D$6:$D$33,'2-2. Quantitative data_Market'!$B47) -> 186.00891 | L47: =SUMIFS('3-2. (Raw data) Scope2_Location'!$AY$6:$AY$33,'3-2. (Raw data) Scope2_Location'!$AD$6:$AD$33,'2-2. Quantitative data_Market'!B$44,'3-2. (Raw data) Scope2_Location'!$D$6:$D$33,'2-2. Quantitative data_Market'!$B47) -> 186.00891 | M47: =SUMIFS('3-2. (Raw data) Scope2_Location'!$AR$6:$AR$33,'3-2. (Raw data) Scope2_Location'!$AD$6:$AD$33,'2-2. Quantitative data_Market'!B$44,'3-2. (Raw data) Scope2_Location'!$D$6:$D$33,'2-2. Quantitative data_Market'!$B47) -> 398.33487
A48: 2022년 | B48: KAHOINDAH CITRAGARMENT | C48: =D48+K48 -> 2538.3389 | D48: =SUM(E48:J48) -> 1092.0335 | E48: =SUMIFS('3-1. (Raw data) Scope 1'!$AT$6:$AT$79,'3-1. (Raw data) Scope 1'!$Y$6:$Y$79,'2-2. Quantitative data_Market'!$B$44,'3-1. (Raw data) Scope 1'!$D$6:$D$79,'2-2. Quantitative data_Market'!$B48,'3-1. (Raw data) Scope 1'!$AB$6:$AB$79,'2-2. Quantitative data_Market'!E$45) -> 69.067883 | F48: =SUMIFS('3-1. (Raw data) Scope 1'!$AT$6:$AT$79,'3-1. (Raw data) Scope 1'!$Y$6:$Y$79,'2-2. Quantitative data_Market'!$B$44,'3-1. (Raw data) Scope 1'!$D$6:$D$79,'2-2. Quantitative data_Market'!$B48,'3-1. (Raw data) Scope 1'!$AB$6:$AB$79,'2-2. Quantitative data_Market'!F$45) -> 1019.5213 | G48: =SUMIFS('3-1. (Raw data) Scope 1'!$AT$6:$AT$79,'3-1. (Raw data) Scope 1'!$Y$6:$Y$79,'2-2. Quantitative data_Market'!$B$44,'3-1. (Raw data) Scope 1'!$D$6:$D$79,'2-2. Quantitative data_Market'!$B48,'3-1. (Raw data) Scope 1'!$AB$6:$AB$79,'2-2. Quantitative data_Market'!G$45) -> 2.512375 | H48: =SUMIFS('3-1. (Raw data) Scope 1'!$AT$6:$AT$79,'3-1. (Raw data) Scope 1'!$Y$6:$Y$79,'2-2. Quantitative data_Market'!$B$44,'3-1. (Raw data) Scope 1'!$D$6:$D$79,'2-2. Quantitative data_Market'!$B48,'3-1. (Raw data) Scope 1'!$AB$6:$AB$79,'2-2. Quantitative data_Market'!H$45) -> 0.9320059 | I48: =SUMIFS('3-1. (Raw data) Scope 1'!$AT$6:$AT$79,'3-1. (Raw data) Scope 1'!$Y$6:$Y$79,'2-2. Quantitative data_Market'!$B$44,'3-1. (Raw data) Scope 1'!$D$6:$D$79,'2-2. Quantitative data_Market'!$B48,'3-1. (Raw data) Scope 1'!$AB$6:$AB$79,'2-2. Quantitative data_Market'!I$45) -> 0 | J48: =SUMIFS('3-1. (Raw data) Scope 1'!$AT$6:$AT$79,'3-1. (Raw data) Scope 1'!$Y$6:$Y$79,'2-2. Quantitative data_Market'!$B$44,'3-1. (Raw data) Scope 1'!$D$6:$D$79,'2-2. Quantitative data_Market'!$B48,'3-1. (Raw data) Scope 1'!$AB$6:$AB$79,'2-2. Quantitative data_Market'!J$45) -> 0 | K48: =SUMIFS('3-2. (Raw data) Scope2_Location'!$AY$6:$AY$33,'3-2. (Raw data) Scope2_Location'!$AD$6:$AD$33,'2-2. Quantitative data_Market'!B$44,'3-2. (Raw data) Scope2_Location'!$D$6:$D$33,'2-2. Quantitative data_Market'!$B48) -> 1446.3054 | L48: =SUMIFS('3-2. (Raw data) Scope2_Location'!$AY$6:$AY$33,'3-2. (Raw data) Scope2_Location'!$AD$6:$AD$33,'2-2. Quantitative data_Market'!B$44,'3-2. (Raw data) Scope2_Location'!$D$6:$D$33,'2-2. Quantitative data_Market'!$B48) -> 1446.3054 | M48: =SUMIFS('3-2. (Raw data) Scope2_Location'!$AR$6:$AR$33,'3-2. (Raw data) Scope2_Location'!$AD$6:$AD$33,'2-2. Quantitative data_Market'!B$44,'3-2. (Raw data) Scope2_Location'!$D$6:$D$33,'2-2. Quantitative data_Market'!$B48) -> 1662.42
A49: 2022년 | B49: PT. YONGJIN JAVASUKA GARMENT (1공장) | C49: =D49+K49 -> 2622.4944 | D49: =SUM(E49:J49) -> 1478.1033 | E49: =SUMIFS('3-1. (Raw data) Scope 1'!$AT$6:$AT$79,'3-1. (Raw data) Scope 1'!$Y$6:$Y$79,'2-2. Quantitative data_Market'!$B$44,'3-1. (Raw data) Scope 1'!$D$6:$D$79,'2-2. Quantitative data_Market'!$B49,'3-1. (Raw data) Scope 1'!$AB$6:$AB$79,'2-2. Quantitative data_Market'!E$45) -> 164.92964 | F49: =SUMIFS('3-1. (Raw data) Scope 1'!$AT$6:$AT$79,'3-1. (Raw data) Scope 1'!$Y$6:$Y$79,'2-2. Quantitative data_Market'!$B$44,'3-1. (Raw data) Scope 1'!$D$6:$D$79,'2-2. Quantitative data_Market'!$B49,'3-1. (Raw data) Scope 1'!$AB$6:$AB$79,'2-2. Quantitative data_Market'!F$45) -> 1149.5978 | G49: =SUMIFS('3-1. (Raw data) Scope 1'!$AT$6:$AT$79,'3-1. (Raw data) Scope 1'!$Y$6:$Y$79,'2-2. Quantitative data_Market'!$B$44,'3-1. (Raw data) Scope 1'!$D$6:$D$79,'2-2. Quantitative data_Market'!$B49,'3-1. (Raw data) Scope 1'!$AB$6:$AB$79,'2-2. Quantitative data_Market'!G$45) -> 0 | H49: =SUMIFS('3-1. (Raw data) Scope 1'!$AT$6:$AT$79,'3-1. (Raw data) Scope 1'!$Y$6:$Y$79,'2-2. Quantitative data_Market'!$B$44,'3-1. (Raw data) Scope 1'!$D$6:$D$79,'2-2. Quantitative data_Market'!$B49,'3-1. (Raw data) Scope 1'!$AB$6:$AB$79,'2-2. Quantitative data_Market'!H$45) -> 2.6945426 | I49: =SUMIFS('3-1. (Raw data) Scope 1'!$AT$6:$AT$79,'3-1. (Raw data) Scope 1'!$Y$6:$Y$79,'2-2. Quantitative data_Market'!$B$44,'3-1. (Raw data) Scope 1'!$D$6:$D$79,'2-2. Quantitative data_Market'!$B49,'3-1. (Raw data) Scope 1'!$AB$6:$AB$79,'2-2. Quantitative data_Market'!I$45) -> 4.4519004 | J49: =SUMIFS('3-1. (Raw data) Scope 1'!$AT$6:$AT$79,'3-1. (Raw data) Scope 1'!$Y$6:$Y$79,'2-2. Quantitative data_Market'!$B$44,'3-1. (Raw data) Scope 1'!$D$6:$D$79,'2-2. Quantitative data_Market'!$B49,'3-1. (Raw data) Scope 1'!$AB$6:$AB$79,'2-2. Quantitative data_Market'!J$45) -> 156.42945 | K49: =SUMIFS('3-2. (Raw data) Scope2_Location'!$AY$6:$AY$33,'3-2. (Raw data) Scope2_Location'!$AD$6:$AD$33,'2-2. Quantitative data_Market'!B$44,'3-2. (Raw data) Scope2_Location'!$D$6:$D$33,'2-2. Quantitative data_Market'!$B49) -> 1144.391 | L49: =SUMIFS('3-2. (Raw data) Scope2_Location'!$AY$6:$AY$33,'3-2. (Raw data) Scope2_Location'!$AD$6:$AD$33,'2-2. Quantitative data_Market'!B$44,'3-2. (Raw data) Scope2_Location'!$D$6:$D$33,'2-2. Quantitative data_Market'!$B49) -> 1144.391 | M49: =SUMIFS('3-2. (Raw data) Scope2_Location'!$AR$6:$AR$33,'3-2. (Raw data) Scope2_Location'!$AD$6:$AD$33,'2-2. Quantitative data_Market'!B$44,'3-2. (Raw data) Scope2_Location'!$D$6:$D$33,'2-2. Quantitative data_Market'!$B49) -> 1315.392
A50: 2022년 | B50: PT. YONGJIN JAVASUKA GARMENT (2,3공장) | C50: =D50+K50 -> 9864.3183 | D50: =SUM(E50:J50) -> 3051.6824 | E50: =SUMIFS('3-1. (Raw data) Scope 1'!$AT$6:$AT$79,'3-1. (Raw data) Scope 1'!$Y$6:$Y$79,'2-2. Quantitative data_Market'!$B$44,'3-1. (Raw data) Scope 1'!$D$6:$D$79,'2-2. Quantitative data_Market'!$B50,'3-1. (Raw data) Scope 1'!$AB$6:$AB$79,'2-2. Quantitative data_Market'!E$45) -> 636.12194 | F50: =SUMIFS('3-1. (Raw data) Scope 1'!$AT$6:$AT$79,'3-1. (Raw data) Scope 1'!$Y$6:$Y$79,'2-2. Quantitative data_Market'!$B$44,'3-1. (Raw data) Scope 1'!$D$6:$D$79,'2-2. Quantitative data_Market'!$B50,'3-1. (Raw data) Scope 1'!$AB$6:$AB$79,'2-2. Quantitative data_Market'!F$45) -> 2200.5209 | G50: =SUMIFS('3-1. (Raw data) Scope 1'!$AT$6:$AT$79,'3-1. (Raw data) Scope 1'!$Y$6:$Y$79,'2-2. Quantitative data_Market'!$B$44,'3-1. (Raw data) Scope 1'!$D$6:$D$79,'2-2. Quantitative data_Market'!$B50,'3-1. (Raw data) Scope 1'!$AB$6:$AB$79,'2-2. Quantitative data_Market'!G$45) -> 0 | H50: =SUMIFS('3-1. (Raw data) Scope 1'!$AT$6:$AT$79,'3-1. (Raw data) Scope 1'!$Y$6:$Y$79,'2-2. Quantitative data_Market'!$B$44,'3-1. (Raw data) Scope 1'!$D$6:$D$79,'2-2. Quantitative data_Market'!$B50,'3-1. (Raw data) Scope 1'!$AB$6:$AB$79,'2-2. Quantitative data_Market'!H$45) -> 4.9760153 | I50: =SUMIFS('3-1. (Raw data) Scope 1'!$AT$6:$AT$79,'3-1. (Raw data) Scope 1'!$Y$6:$Y$79,'2-2. Quantitative data_Market'!$B$44,'3-1. (Raw data) Scope 1'!$D$6:$D$79,'2-2. Quantitative data_Market'!$B50,'3-1. (Raw data) Scope 1'!$AB$6:$AB$79,'2-2. Quantitative data_Market'!I$45) -> 47.093012 | J50: =SUMIFS('3-1. (Raw data) Scope 1'!$AT$6:$AT$79,'3-1. (Raw data) Scope 1'!$Y$6:$Y$79,'2-2. Quantitative data_Market'!$B$44,'3-1. (Raw data) Scope 1'!$D$6:$D$79,'2-2. Quantitative data_Market'!$B50,'3-1. (Raw data) Scope 1'!$AB$6:$AB$79,'2-2. Quantitative data_Market'!J$45) -> 162.9706 | K50: =SUMIFS('3-2. (Raw data) Scope2_Location'!$AY$6:$AY$33,'3-2. (Raw data) Scope2_Location'!$AD$6:$AD$33,'2-2. Quantitative data_Market'!B$44,'3-2. (Raw data) Scope2_Location'!$D$6:$D$33,'2-2. Quantitative data_Market'!$B50) -> 6812.6359 | L50: =SUMIFS('3-2. (Raw data) Scope2_Location'!$AY$6:$AY$33,'3-2. (Raw data) Scope2_Location'!$AD$6:$AD$33,'2-2. Quantitative data_Market'!B$44,'3-2. (Raw data) Scope2_Location'!$D$6:$D$33,'2-2. Quantitative data_Market'!$B50) -> 6812.6359 | M50: =SUMIFS('3-2. (Raw data) Scope2_Location'!$AR$6:$AR$33,'3-2. (Raw data) Scope2_Location'!$AD$6:$AD$33,'2-2. Quantitative data_Market'!B$44,'3-2. (Raw data) Scope2_Location'!$D$6:$D$33,'2-2. Quantitative data_Market'!$B50) -> 7830.616
A51: 2022년 | B51: PT. HJL INDO NETWORKS | C51: =D51+K51 -> 91.09388 | D51: =SUM(E51:J51) -> 71.458589 | E51: =SUMIFS('3-1. (Raw data) Scope 1'!$AT$6:$AT$79,'3-1. (Raw data) Scope 1'!$Y$6:$Y$79,'2-2. Quantitative data_Market'!$B$44,'3-1. (Raw data) Scope 1'!$D$6:$D$79,'2-2. Quantitative data_Market'!$B51,'3-1. (Raw data) Scope 1'!$AB$6:$AB$79,'2-2. Quantitative data_Market'!E$45) -> 71.458589 | F51: =SUMIFS('3-1. (Raw data) Scope 1'!$AT$6:$AT$79,'3-1. (Raw data) Scope 1'!$Y$6:$Y$79,'2-2. Quantitative data_Market'!$B$44,'3-1. (Raw data) Scope 1'!$D$6:$D$79,'2-2. Quantitative data_Market'!$B51,'3-1. (Raw data) Scope 1'!$AB$6:$AB$79,'2-2. Quantitative data_Market'!F$45) -> 0 | G51: =SUMIFS('3-1. (Raw data) Scope 1'!$AT$6:$AT$79,'3-1. (Raw data) Scope 1'!$Y$6:$Y$79,'2-2. Quantitative data_Market'!$B$44,'3-1. (Raw data) Scope 1'!$D$6:$D$79,'2-2. Quantitative data_Market'!$B51,'3-1. (Raw data) Scope 1'!$AB$6:$AB$79,'2-2. Quantitative data_Market'!G$45) -> 0 | H51: =SUMIFS('3-1. (Raw data) Scope 1'!$AT$6:$AT$79,'3-1. (Raw data) Scope 1'!$Y$6:$Y$79,'2-2. Quantitative data_Market'!$B$44,'3-1. (Raw data) Scope 1'!$D$6:$D$79,'2-2. Quantitative data_Market'!$B51,'3-1. (Raw data) Scope 1'!$AB$6:$AB$79,'2-2. Quantitative data_Market'!H$45) -> 0 | I51: =SUMIFS('3-1. (Raw data) Scope 1'!$AT$6:$AT$79,'3-1. (Raw data) Scope 1'!$Y$6:$Y$79,'2-2. Quantitative data_Market'!$B$44,'3-1. (Raw data) Scope 1'!$D$6:$D$79,'2-2. Quantitative data_Market'!$B51,'3-1. (Raw data) Scope 1'!$AB$6:$AB$79,'2-2. Quantitative data_Market'!I$45) -> 0 | J51: =SUMIFS('3-1. (Raw data) Scope 1'!$AT$6:$AT$79,'3-1. (Raw data) Scope 1'!$Y$6:$Y$79,'2-2. Quantitative data_Market'!$B$44,'3-1. (Raw data) Scope 1'!$D$6:$D$79,'2-2. Quantitative data_Market'!$B51,'3-1. (Raw data) Scope 1'!$AB$6:$AB$79,'2-2. Quantitative data_Market'!J$45) -> 0 | K51: =SUMIFS('3-2. (Raw data) Scope2_Location'!$AY$6:$AY$33,'3-2. (Raw data) Scope2_Location'!$AD$6:$AD$33,'2-2. Quantitative data_Market'!B$44,'3-2. (Raw data) Scope2_Location'!$D$6:$D$33,'2-2. Quantitative data_Market'!$B51) -> 19.635291 | L51: =SUMIFS('3-2. (Raw data) Scope2_Location'!$AY$6:$AY$33,'3-2. (Raw data) Scope2_Location'!$AD$6:$AD$33,'2-2. Quantitative data_Market'!B$44,'3-2. (Raw data) Scope2_Location'!$D$6:$D$33,'2-2. Quantitative data_Market'!$B51) -> 19.635291 | M51: =SUMIFS('3-2. (Raw data) Scope2_Location'!$AR$6:$AR$33,'3-2. (Raw data) Scope2_Location'!$AD$6:$AD$33,'2-2. Quantitative data_Market'!B$44,'3-2. (Raw data) Scope2_Location'!$D$6:$D$33,'2-2. Quantitative data_Market'!$B51) -> 22.5693
A52: 2022년 | B52: PT.HOGA REKSA GARMENT | C52: =D52+K52 -> 2132.9814 | D52: =SUM(E52:J52) -> 64.107488 | E52: =SUMIFS('3-1. (Raw data) Scope 1'!$AT$6:$AT$79,'3-1. (Raw data) Scope 1'!$Y$6:$Y$79,'2-2. Quantitative data_Market'!$B$44,'3-1. (Raw data) Scope 1'!$D$6:$D$79,'2-2. Quantitative data_Market'!$B52,'3-1. (Raw data) Scope 1'!$AB$6:$AB$79,'2-2. Quantitative data_Market'!E$45) -> 42.903594 | F52: =SUMIFS('3-1. (Raw data) Scope 1'!$AT$6:$AT$79,'3-1. (Raw data) Scope 1'!$Y$6:$Y$79,'2-2. Quantitative data_Market'!$B$44,'3-1. (Raw data) Scope 1'!$D$6:$D$79,'2-2. Quantitative data_Market'!$B52,'3-1. (Raw data) Scope 1'!$AB$6:$AB$79,'2-2. Quantitative data_Market'!F$45) -> 0 | G52: =SUMIFS('3-1. (Raw data) Scope 1'!$AT$6:$AT$79,'3-1. (Raw data) Scope 1'!$Y$6:$Y$79,'2-2. Quantitative data_Market'!$B$44,'3-1. (Raw data) Scope 1'!$D$6:$D$79,'2-2. Quantitative data_Market'!$B52,'3-1. (Raw data) Scope 1'!$AB$6:$AB$79,'2-2. Quantitative data_Market'!G$45) -> 21.203895 | H52: =SUMIFS('3-1. (Raw data) Scope 1'!$AT$6:$AT$79,'3-1. (Raw data) Scope 1'!$Y$6:$Y$79,'2-2. Quantitative data_Market'!$B$44,'3-1. (Raw data) Scope 1'!$D$6:$D$79,'2-2. Quantitative data_Market'!$B52,'3-1. (Raw data) Scope 1'!$AB$6:$AB$79,'2-2. Quantitative data_Market'!H$45) -> 0 | I52: =SUMIFS('3-1. (Raw data) Scope 1'!$AT$6:$AT$79,'3-1. (Raw data) Scope 1'!$Y$6:$Y$79,'2-2. Quantitative data_Market'!$B$44,'3-1. (Raw data) Scope 1'!$D$6:$D$79,'2-2. Quantitative data_Market'!$B52,'3-1. (Raw data) Scope 1'!$AB$6:$AB$79,'2-2. Quantitative data_Market'!I$45) -> 0 | J52: =SUMIFS('3-1. (Raw data) Scope 1'!$AT$6:$AT$79,'3-1. (Raw data) Scope 1'!$Y$6:$Y$79,'2-2. Quantitative data_Market'!$B$44,'3-1. (Raw data) Scope 1'!$D$6:$D$79,'2-2. Quantitative data_Market'!$B52,'3-1. (Raw data) Scope 1'!$AB$6:$AB$79,'2-2. Quantitative data_Market'!J$45) -> 0 | K52: =SUMIFS('3-2. (Raw data) Scope2_Location'!$AY$6:$AY$33,'3-2. (Raw data) Scope2_Location'!$AD$6:$AD$33,'2-2. Quantitative data_Market'!B$44,'3-2. (Raw data) Scope2_Location'!$D$6:$D$33,'2-2. Quantitative data_Market'!$B52) -> 2068.8739 | L52: =SUMIFS('3-2. (Raw data) Scope2_Location'!$AY$6:$AY$33,'3-2. (Raw data) Scope2_Location'!$AD$6:$AD$33,'2-2. Quantitative data_Market'!B$44,'3-2. (Raw data) Scope2_Location'!$D$6:$D$33,'2-2. Quantitative data_Market'!$B52) -> 2068.8739 | M52: =SUMIFS('3-2. (Raw data) Scope2_Location'!$AR$6:$AR$33,'3-2. (Raw data) Scope2_Location'!$AD$6:$AD$33,'2-2. Quantitative data_Market'!B$44,'3-2. (Raw data) Scope2_Location'!$D$6:$D$33,'2-2. Quantitative data_Market'!$B52) -> 2378.016
A53: 2022년 | B53: MFAFA Co., Ltd | C53: =D53+K53 -> 3.1390089 | D53: =SUM(E53:J53) -> 0 | E53: =SUMIFS('3-1. (Raw data) Scope 1'!$AT$6:$AT$79,'3-1. (Raw data) Scope 1'!$Y$6:$Y$79,'2-2. Quantitative data_Market'!$B$44,'3-1. (Raw data) Scope 1'!$D$6:$D$79,'2-2. Quantitative data_Market'!$B53,'3-1. (Raw data) Scope 1'!$AB$6:$AB$79,'2-2. Quantitative data_Market'!E$45) -> 0 | F53: =SUMIFS('3-1. (Raw data) Scope 1'!$AT$6:$AT$79,'3-1. (Raw data) Scope 1'!$Y$6:$Y$79,'2-2. Quantitative data_Market'!$B$44,'3-1. (Raw data) Scope 1'!$D$6:$D$79,'2-2. Quantitative data_Market'!$B53,'3-1. (Raw data) Scope 1'!$AB$6:$AB$79,'2-2. Quantitative data_Market'!F$45) -> 0 | G53: =SUMIFS('3-1. (Raw data) Scope 1'!$AT$6:$AT$79,'3-1. (Raw data) Scope 1'!$Y$6:$Y$79,'2-2. Quantitative data_Market'!$B$44,'3-1. (Raw data) Scope 1'!$D$6:$D$79,'2-2. Quantitative data_Market'!$B53,'3-1. (Raw data) Scope 1'!$AB$6:$AB$79,'2-2. Quantitative data_Market'!G$45) -> 0 | H53: =SUMIFS('3-1. (Raw data) Scope 1'!$AT$6:$AT$79,'3-1. (Raw data) Scope 1'!$Y$6:$Y$79,'2-2. Quantitative data_Market'!$B$44,'3-1. (Raw data) Scope 1'!$D$6:$D$79,'2-2. Quantitative data_Market'!$B53,'3-1. (Raw data) Scope 1'!$AB$6:$AB$79,'2-2. Quantitative data_Market'!H$45) -> 0 | I53: =SUMIFS('3-1. (Raw data) Scope 1'!$AT$6:$AT$79,'3-1. (Raw data) Scope 1'!$Y$6:$Y$79,'2-2. Quantitative data_Market'!$B$44,'3-1. (Raw data) Scope 1'!$D$6:$D$79,'2-2. Quantitative data_Market'!$B53,'3-1. (Raw data) Scope 1'!$AB$6:$AB$79,'2-2. Quantitative data_Market'!I$45) -> 0 | J53: =SUMIFS('3-1. (Raw data) Scope 1'!$AT$6:$AT$79,'3-1. (Raw data) Scope 1'!$Y$6:$Y$79,'2-2. Quantitative data_Market'!$B$44,'3-1. (Raw data) Scope 1'!$D$6:$D$79,'2-2. Quantitative data_Market'!$B53,'3-1. (Raw data) Scope 1'!$AB$6:$AB$79,'2-2. Quantitative data_Market'!J$45) -> 0 | K53: =SUMIFS('3-2. (Raw data) Scope2_Location'!$AY$6:$AY$33,'3-2. (Raw data) Scope2_Location'!$AD$6:$AD$33,'2-2. Quantitative data_Market'!B$44,'3-2. (Raw data) Scope2_Location'!$D$6:$D$33,'2-2. Quantitative data_Market'!$B53) -> 3.1390089 | L53: =SUMIFS('3-2. (Raw data) Scope2_Location'!$AY$6:$AY$33,'3-2. (Raw data) Scope2_Location'!$AD$6:$AD$33,'2-2. Quantitative data_Market'!B$44,'3-2. (Raw data) Scope2_Location'!$D$6:$D$33,'2-2. Quantitative data_Market'!$B53) -> 3.1390089 | M53: =SUMIFS('3-2. (Raw data) Scope2_Location'!$AR$6:$AR$33,'3-2. (Raw data) Scope2_Location'!$AD$6:$AD$33,'2-2. Quantitative data_Market'!B$44,'3-2. (Raw data) Scope2_Location'!$D$6:$D$33,'2-2. Quantitative data_Market'!$B53) -> 6.7221333
A54: 2023년 | B54: 2023 | C54: Scope 1 + Scope 2 | D54: Scope 1 | K54: Scope 2
A55: 2023년 | D55: Scope 1 GHG Emissions by Facility | E55: {=_xlfn.TOROW(_xlfn.UNIQUE('3-1. (Raw data) Scope 1'!AB6:AB79))} -> Automotive gasoline (petrol) | F55: Industrial Wastes | G55: Biodiesel | H55: Liquefied Petroleum Gas (LPG) | I55: Gas / Diesel oil | J55: Hydrofluorocarbons(HFCs) | K55: Scope 2 GHG Emissions by Facility | L55: Electricity | M55: Electricity Consumption (MWh)
A56: 2023년 | B56: Total | C56: =D56+K56 -> 17676.947 | D56: =SUM(E56:J56) -> 5472.6179 | E56: =SUM(E57:E63) -> 1098.8887 | F56: =SUM(F57:F63) -> 3986.6566 | G56: =SUM(G57:G63) -> 26.422966 | H56: =SUM(H57:H63) -> 7.584198 | I56: =SUM(I57:I63) -> 104.75457 | J56: =SUM(J57:J63) -> 248.3109 | K56: =SUM(K57:K63) -> 12204.329 | L56: =SUM(L57:L63) -> 12204.329 | M56: =SUM(M57:M63) -> 14208.297
A57: 2023년 | B57: {=_xlfn.UNIQUE('3-2. (Raw data) Scope2_Location'!$D$6:$D$33)} -> HOJEON LIMITED Co., Ltd | C57: =D57+K57 -> 239.15711 | D57: =SUM(E57:J57) -> 59.95623 | E57: =SUMIFS('3-1. (Raw data) Scope 1'!$AT$6:$AT$79,'3-1. (Raw data) Scope 1'!$Y$6:$Y$79,'2-2. Quantitative data_Market'!$B$54,'3-1. (Raw data) Scope 1'!$D$6:$D$79,'2-2. Quantitative data_Market'!$B57,'3-1. (Raw data) Scope 1'!$AB$6:$AB$79,'2-2. Quantitative data_Market'!E$55) -> 59.95623 | F57: =SUMIFS('3-1. (Raw data) Scope 1'!$AT$6:$AT$79,'3-1. (Raw data) Scope 1'!$Y$6:$Y$79,'2-2. Quantitative data_Market'!$B$54,'3-1. (Raw data) Scope 1'!$D$6:$D$79,'2-2. Quantitative data_Market'!$B57,'3-1. (Raw data) Scope 1'!$AB$6:$AB$79,'2-2. Quantitative data_Market'!F$55) -> 0 | G57: =SUMIFS('3-1. (Raw data) Scope 1'!$AT$6:$AT$79,'3-1. (Raw data) Scope 1'!$Y$6:$Y$79,'2-2. Quantitative data_Market'!$B$54,'3-1. (Raw data) Scope 1'!$D$6:$D$79,'2-2. Quantitative data_Market'!$B57,'3-1. (Raw data) Scope 1'!$AB$6:$AB$79,'2-2. Quantitative data_Market'!G$55) -> 0 | H57: =SUMIFS('3-1. (Raw data) Scope 1'!$AT$6:$AT$79,'3-1. (Raw data) Scope 1'!$Y$6:$Y$79,'2-2. Quantitative data_Market'!$B$54,'3-1. (Raw data) Scope 1'!$D$6:$D$79,'2-2. Quantitative data_Market'!$B57,'3-1. (Raw data) Scope 1'!$AB$6:$AB$79,'2-2. Quantitative data_Market'!H$55) -> 0 | I57: =SUMIFS('3-1. (Raw data) Scope 1'!$AT$6:$AT$79,'3-1. (Raw data) Scope 1'!$Y$6:$Y$79,'2-2. Quantitative data_Market'!$B$54,'3-1. (Raw data) Scope 1'!$D$6:$D$79,'2-2. Quantitative data_Market'!$B57,'3-1. (Raw data) Scope 1'!$AB$6:$AB$79,'2-2. Quantitative data_Market'!I$55) -> 0 | J57: =SUMIFS('3-1. (Raw data) Scope 1'!$AT$6:$AT$79,'3-1. (Raw data) Scope 1'!$Y$6:$Y$79,'2-2. Quantitative data_Market'!$B$54,'3-1. (Raw data) Scope 1'!$D$6:$D$79,'2-2. Quantitative data_Market'!$B57,'3-1. (Raw data) Scope 1'!$AB$6:$AB$79,'2-2. Quantitative data_Market'!J$55) -> 0 | K57: =SUMIFS('3-2. (Raw data) Scope2_Location'!$AY$6:$AY$33,'3-2. (Raw data) Scope2_Location'!$AD$6:$AD$33,'2-2. Quantitative data_Market'!$B$54,'3-2. (Raw data) Scope2_Location'!$D$6:$D$33,'2-2. Quantitative data_Market'!$B57) -> 179.20088 | L57: =SUMIFS('3-2. (Raw data) Scope2_Location'!$AY$6:$AY$33,'3-2. (Raw data) Scope2_Location'!$AD$6:$AD$33,'2-2. Quantitative data_Market'!$B$54,'3-2. (Raw data) Scope2_Location'!$D$6:$D$33,'2-2. Quantitative data_Market'!$B57) -> 179.20088 | M57: =SUMIFS('3-2. (Raw data) Scope2_Location'!$AR$6:$AR$33,'3-2. (Raw data) Scope2_Location'!$AD$6:$AD$33,'2-2. Quantitative data_Market'!B$54,'3-2. (Raw data) Scope2_Location'!$D$6:$D$33,'2-2. Quantitative data_Market'!$B57) -> 383.7556
A58: 2023년 | B58: KAHOINDAH CITRAGARMENT | C58: =D58+K58 -> 2386.1475 | D58: =SUM(E58:J58) -> 1049.9841 | E58: =SUMIFS('3-1. (Raw data) Scope 1'!$AT$6:$AT$79,'3-1. (Raw data) Scope 1'!$Y$6:$Y$79,'2-2. Quantitative data_Market'!$B$54,'3-1. (Raw data) Scope 1'!$D$6:$D$79,'2-2. Quantitative data_Market'!$B58,'3-1. (Raw data) Scope 1'!$AB$6:$AB$79,'2-2. Quantitative data_Market'!E$55) -> 64.022518 | F58: =SUMIFS('3-1. (Raw data) Scope 1'!$AT$6:$AT$79,'3-1. (Raw data) Scope 1'!$Y$6:$Y$79,'2-2. Quantitative data_Market'!$B$54,'3-1. (Raw data) Scope 1'!$D$6:$D$79,'2-2. Quantitative data_Market'!$B58,'3-1. (Raw data) Scope 1'!$AB$6:$AB$79,'2-2. Quantitative data_Market'!F$55) -> 982.67677 | G58: =SUMIFS('3-1. (Raw data) Scope 1'!$AT$6:$AT$79,'3-1. (Raw data) Scope 1'!$Y$6:$Y$79,'2-2. Quantitative data_Market'!$B$54,'3-1. (Raw data) Scope 1'!$D$6:$D$79,'2-2. Quantitative data_Market'!$B58,'3-1. (Raw data) Scope 1'!$AB$6:$AB$79,'2-2. Quantitative data_Market'!G$55) -> 2.4961662 | H58: =SUMIFS('3-1. (Raw data) Scope 1'!$AT$6:$AT$79,'3-1. (Raw data) Scope 1'!$Y$6:$Y$79,'2-2. Quantitative data_Market'!$B$54,'3-1. (Raw data) Scope 1'!$D$6:$D$79,'2-2. Quantitative data_Market'!$B58,'3-1. (Raw data) Scope 1'!$AB$6:$AB$79,'2-2. Quantitative data_Market'!H$55) -> 0.78862037 | I58: =SUMIFS('3-1. (Raw data) Scope 1'!$AT$6:$AT$79,'3-1. (Raw data) Scope 1'!$Y$6:$Y$79,'2-2. Quantitative data_Market'!$B$54,'3-1. (Raw data) Scope 1'!$D$6:$D$79,'2-2. Quantitative data_Market'!$B58,'3-1. (Raw data) Scope 1'!$AB$6:$AB$79,'2-2. Quantitative data_Market'!I$55) -> 0 | J58: =SUMIFS('3-1. (Raw data) Scope 1'!$AT$6:$AT$79,'3-1. (Raw data) Scope 1'!$Y$6:$Y$79,'2-2. Quantitative data_Market'!$B$54,'3-1. (Raw data) Scope 1'!$D$6:$D$79,'2-2. Quantitative data_Market'!$B58,'3-1. (Raw data) Scope 1'!$AB$6:$AB$79,'2-2. Quantitative data_Market'!J$55) -> 0 | K58: =SUMIFS('3-2. (Raw data) Scope2_Location'!$AY$6:$AY$33,'3-2. (Raw data) Scope2_Location'!$AD$6:$AD$33,'2-2. Quantitative data_Market'!$B$54,'3-2. (Raw data) Scope2_Location'!$D$6:$D$33,'2-2. Quantitative data_Market'!$B58) -> 1336.1634 | L58: =SUMIFS('3-2. (Raw data) Scope2_Location'!$AY$6:$AY$33,'3-2. (Raw data) Scope2_Location'!$AD$6:$AD$33,'2-2. Quantitative data_Market'!$B$54,'3-2. (Raw data) Scope2_Location'!$D$6:$D$33,'2-2. Quantitative data_Market'!$B58) -> 1336.1634 | M58: =SUMIFS('3-2. (Raw data) Scope2_Location'!$AR$6:$AR$33,'3-2. (Raw data) Scope2_Location'!$AD$6:$AD$33,'2-2. Quantitative data_Market'!B$54,'3-2. (Raw data) Scope2_Location'!$D$6:$D$33,'2-2. Quantitative data_Market'!$B58) -> 1535.82
A59: 2023년 | B59: PT. YONGJIN JAVASUKA GARMENT (1공장) | C59: =D59+K59 -> 2504.7999 | D59: =SUM(E59:J59) -> 1377.433 | E59: =SUMIFS('3-1. (Raw data) Scope 1'!$AT$6:$AT$79,'3-1. (Raw data) Scope 1'!$Y$6:$Y$79,'2-2. Quantitative data_Market'!$B$54,'3-1. (Raw data) Scope 1'!$D$6:$D$79,'2-2. Quantitative data_Market'!$B59,'3-1. (Raw data) Scope 1'!$AB$6:$AB$79,'2-2. Quantitative data_Market'!E$55) -> 189.67944 | F59: =SUMIFS('3-1. (Raw data) Scope 1'!$AT$6:$AT$79,'3-1. (Raw data) Scope 1'!$Y$6:$Y$79,'2-2. Quantitative data_Market'!$B$54,'3-1. (Raw data) Scope 1'!$D$6:$D$79,'2-2. Quantitative data_Market'!$B59,'3-1. (Raw data) Scope 1'!$AB$6:$AB$79,'2-2. Quantitative data_Market'!F$55) -> 1119.3328 | G59: =SUMIFS('3-1. (Raw data) Scope 1'!$AT$6:$AT$79,'3-1. (Raw data) Scope 1'!$Y$6:$Y$79,'2-2. Quantitative data_Market'!$B$54,'3-1. (Raw data) Scope 1'!$D$6:$D$79,'2-2. Quantitative data_Market'!$B59,'3-1. (Raw data) Scope 1'!$AB$6:$AB$79,'2-2. Quantitative data_Market'!G$55) -> 0 | H59: =SUMIFS('3-1. (Raw data) Scope 1'!$AT$6:$AT$79,'3-1. (Raw data) Scope 1'!$Y$6:$Y$79,'2-2. Quantitative data_Market'!$B$54,'3-1. (Raw data) Scope 1'!$D$6:$D$79,'2-2. Quantitative data_Market'!$B59,'3-1. (Raw data) Scope 1'!$AB$6:$AB$79,'2-2. Quantitative data_Market'!H$55) -> 2.6317815 | I59: =SUMIFS('3-1. (Raw data) Scope 1'!$AT$6:$AT$79,'3-1. (Raw data) Scope 1'!$Y$6:$Y$79,'2-2. Quantitative data_Market'!$B$54,'3-1. (Raw data) Scope 1'!$D$6:$D$79,'2-2. Quantitative data_Market'!$B59,'3-1. (Raw data) Scope 1'!$AB$6:$AB$79,'2-2. Quantitative data_Market'!I$55) -> 5.9358673 | J59: =SUMIFS('3-1. (Raw data) Scope 1'!$AT$6:$AT$79,'3-1. (Raw data) Scope 1'!$Y$6:$Y$79,'2-2. Quantitative data_Market'!$B$54,'3-1. (Raw data) Scope 1'!$D$6:$D$79,'2-2. Quantitative data_Market'!$B59,'3-1. (Raw data) Scope 1'!$AB$6:$AB$79,'2-2. Quantitative data_Market'!J$55) -> 59.85315 | K59: =SUMIFS('3-2. (Raw data) Scope2_Location'!$AY$6:$AY$33,'3-2. (Raw data) Scope2_Location'!$AD$6:$AD$33,'2-2. Quantitative data_Market'!$B$54,'3-2. (Raw data) Scope2_Location'!$D$6:$D$33,'2-2. Quantitative data_Market'!$B59) -> 1127.3669 | L59: =SUMIFS('3-2. (Raw data) Scope2_Location'!$AY$6:$AY$33,'3-2. (Raw data) Scope2_Location'!$AD$6:$AD$33,'2-2. Quantitative data_Market'!$B$54,'3-2. (Raw data) Scope2_Location'!$D$6:$D$33,'2-2. Quantitative data_Market'!$B59) -> 1127.3669 | M59: =SUMIFS('3-2. (Raw data) Scope2_Location'!$AR$6:$AR$33,'3-2. (Raw data) Scope2_Location'!$AD$6:$AD$33,'2-2. Quantitative data_Market'!B$54,'3-2. (Raw data) Scope2_Location'!$D$6:$D$33,'2-2. Quantitative data_Market'!$B59) -> 1295.824
A60: 2023년 | B60: PT. YONGJIN JAVASUKA GARMENT (2,3공장) | C60: =D60+K60 -> 10307.784 | D60: =SUM(E60:J60) -> 2809.4554 | E60: =SUMIFS('3-1. (Raw data) Scope 1'!$AT$6:$AT$79,'3-1. (Raw data) Scope 1'!$Y$6:$Y$79,'2-2. Quantitative data_Market'!$B$54,'3-1. (Raw data) Scope 1'!$D$6:$D$79,'2-2. Quantitative data_Market'!$B60,'3-1. (Raw data) Scope 1'!$AB$6:$AB$79,'2-2. Quantitative data_Market'!E$55) -> 633.36815 | F60: =SUMIFS('3-1. (Raw data) Scope 1'!$AT$6:$AT$79,'3-1. (Raw data) Scope 1'!$Y$6:$Y$79,'2-2. Quantitative data_Market'!$B$54,'3-1. (Raw data) Scope 1'!$D$6:$D$79,'2-2. Quantitative data_Market'!$B60,'3-1. (Raw data) Scope 1'!$AB$6:$AB$79,'2-2. Quantitative data_Market'!F$55) -> 1884.647 | G60: =SUMIFS('3-1. (Raw data) Scope 1'!$AT$6:$AT$79,'3-1. (Raw data) Scope 1'!$Y$6:$Y$79,'2-2. Quantitative data_Market'!$B$54,'3-1. (Raw data) Scope 1'!$D$6:$D$79,'2-2. Quantitative data_Market'!$B60,'3-1. (Raw data) Scope 1'!$AB$6:$AB$79,'2-2. Quantitative data_Market'!G$55) -> 0 | H60: =SUMIFS('3-1. (Raw data) Scope 1'!$AT$6:$AT$79,'3-1. (Raw data) Scope 1'!$Y$6:$Y$79,'2-2. Quantitative data_Market'!$B$54,'3-1. (Raw data) Scope 1'!$D$6:$D$79,'2-2. Quantitative data_Market'!$B60,'3-1. (Raw data) Scope 1'!$AB$6:$AB$79,'2-2. Quantitative data_Market'!H$55) -> 4.1637961 | I60: =SUMIFS('3-1. (Raw data) Scope 1'!$AT$6:$AT$79,'3-1. (Raw data) Scope 1'!$Y$6:$Y$79,'2-2. Quantitative data_Market'!$B$54,'3-1. (Raw data) Scope 1'!$D$6:$D$79,'2-2. Quantitative data_Market'!$B60,'3-1. (Raw data) Scope 1'!$AB$6:$AB$79,'2-2. Quantitative data_Market'!I$55) -> 98.818699 | J60: =SUMIFS('3-1. (Raw data) Scope 1'!$AT$6:$AT$79,'3-1. (Raw data) Scope 1'!$Y$6:$Y$79,'2-2. Quantitative data_Market'!$B$54,'3-1. (Raw data) Scope 1'!$D$6:$D$79,'2-2. Quantitative data_Market'!$B60,'3-1. (Raw data) Scope 1'!$AB$6:$AB$79,'2-2. Quantitative data_Market'!J$55) -> 188.45775 | K60: =SUMIFS('3-2. (Raw data) Scope2_Location'!$AY$6:$AY$33,'3-2. (Raw data) Scope2_Location'!$AD$6:$AD$33,'2-2. Quantitative data_Market'!$B$54,'3-2. (Raw data) Scope2_Location'!$D$6:$D$33,'2-2. Quantitative data_Market'!$B60) -> 7498.3282 | L60: =SUMIFS('3-2. (Raw data) Scope2_Location'!$AY$6:$AY$33,'3-2. (Raw data) Scope2_Location'!$AD$6:$AD$33,'2-2. Quantitative data_Market'!$B$54,'3-2. (Raw data) Scope2_Location'!$D$6:$D$33,'2-2. Quantitative data_Market'!$B60) -> 7498.3282 | M60: =SUMIFS('3-2. (Raw data) Scope2_Location'!$AR$6:$AR$33,'3-2. (Raw data) Scope2_Location'!$AD$6:$AD$33,'2-2. Quantitative data_Market'!B$54,'3-2. (Raw data) Scope2_Location'!$D$6:$D$33,'2-2. Quantitative data_Market'!$B60) -> 8618.768
A61: 2023년 | B61: PT. HJL INDO NETWORKS | C61: =D61+K61 -> 119.04118 | D61: =SUM(E61:J61) -> 100.83886 | E61: =SUMIFS('3-1. (Raw data) Scope 1'!$AT$6:$AT$79,'3-1. (Raw data) Scope 1'!$Y$6:$Y$79,'2-2. Quantitative data_Market'!$B$54,'3-1. (Raw data) Scope 1'!$D$6:$D$79,'2-2. Quantitative data_Market'!$B61,'3-1. (Raw data) Scope 1'!$AB$6:$AB$79,'2-2. Quantitative data_Market'!E$55) -> 100.83886 | F61: =SUMIFS('3-1. (Raw data) Scope 1'!$AT$6:$AT$79,'3-1. (Raw data) Scope 1'!$Y$6:$Y$79,'2-2. Quantitative data_Market'!$B$54,'3-1. (Raw data) Scope 1'!$D$6:$D$79,'2-2. Quantitative data_Market'!$B61,'3-1. (Raw data) Scope 1'!$AB$6:$AB$79,'2-2. Quantitative data_Market'!F$55) -> 0 | G61: =SUMIFS('3-1. (Raw data) Scope 1'!$AT$6:$AT$79,'3-1. (Raw data) Scope 1'!$Y$6:$Y$79,'2-2. Quantitative data_Market'!$B$54,'3-1. (Raw data) Scope 1'!$D$6:$D$79,'2-2. Quantitative data_Market'!$B61,'3-1. (Raw data) Scope 1'!$AB$6:$AB$79,'2-2. Quantitative data_Market'!G$55) -> 0 | H61: =SUMIFS('3-1. (Raw data) Scope 1'!$AT$6:$AT$79,'3-1. (Raw data) Scope 1'!$Y$6:$Y$79,'2-2. Quantitative data_Market'!$B$54,'3-1. (Raw data) Scope 1'!$D$6:$D$79,'2-2. Quantitative data_Market'!$B61,'3-1. (Raw data) Scope 1'!$AB$6:$AB$79,'2-2. Quantitative data_Market'!H$55) -> 0 | I61: =SUMIFS('3-1. (Raw data) Scope 1'!$AT$6:$AT$79,'3-1. (Raw data) Scope 1'!$Y$6:$Y$79,'2-2. Quantitative data_Market'!$B$54,'3-1. (Raw data) Scope 1'!$D$6:$D$79,'2-2. Quantitative data_Market'!$B61,'3-1. (Raw data) Scope 1'!$AB$6:$AB$79,'2-2. Quantitative data_Market'!I$55) -> 0 | J61: =SUMIFS('3-1. (Raw data) Scope 1'!$AT$6:$AT$79,'3-1. (Raw data) Scope 1'!$Y$6:$Y$79,'2-2. Quantitative data_Market'!$B$54,'3-1. (Raw data) Scope 1'!$D$6:$D$79,'2-2. Quantitative data_Market'!$B61,'3-1. (Raw data) Scope 1'!$AB$6:$AB$79,'2-2. Quantitative data_Market'!J$55) -> 0 | K61: =SUMIFS('3-2. (Raw data) Scope2_Location'!$AY$6:$AY$33,'3-2. (Raw data) Scope2_Location'!$AD$6:$AD$33,'2-2. Quantitative data_Market'!$B$54,'3-2. (Raw data) Scope2_Location'!$D$6:$D$33,'2-2. Quantitative data_Market'!$B61) -> 18.202314 | L61: =SUMIFS('3-2. (Raw data) Scope2_Location'!$AY$6:$AY$33,'3-2. (Raw data) Scope2_Location'!$AD$6:$AD$33,'2-2. Quantitative data_Market'!$B$54,'3-2. (Raw data) Scope2_Location'!$D$6:$D$33,'2-2. Quantitative data_Market'!$B61) -> 18.202314 | M61: =SUMIFS('3-2. (Raw data) Scope2_Location'!$AR$6:$AR$33,'3-2. (Raw data) Scope2_Location'!$AD$6:$AD$33,'2-2. Quantitative data_Market'!B$54,'3-2. (Raw data) Scope2_Location'!$D$6:$D$33,'2-2. Quantitative data_Market'!$B61) -> 20.9222
A62: 2023년 | B62: PT.HOGA REKSA GARMENT | C62: =D62+K62 -> 2117.4424 | D62: =SUM(E62:J62) -> 74.950319 | E62: =SUMIFS('3-1. (Raw data) Scope 1'!$AT$6:$AT$79,'3-1. (Raw data) Scope 1'!$Y$6:$Y$79,'2-2. Quantitative data_Market'!$B$54,'3-1. (Raw data) Scope 1'!$D$6:$D$79,'2-2. Quantitative data_Market'!$B62,'3-1. (Raw data) Scope 1'!$AB$6:$AB$79,'2-2. Quantitative data_Market'!E$55) -> 51.023519 | F62: =SUMIFS('3-1. (Raw data) Scope 1'!$AT$6:$AT$79,'3-1. (Raw data) Scope 1'!$Y$6:$Y$79,'2-2. Quantitative data_Market'!$B$54,'3-1. (Raw data) Scope 1'!$D$6:$D$79,'2-2. Quantitative data_Market'!$B62,'3-1. (Raw data) Scope 1'!$AB$6:$AB$79,'2-2. Quantitative data_Market'!F$55) -> 0 | G62: =SUMIFS('3-1. (Raw data) Scope 1'!$AT$6:$AT$79,'3-1. (Raw data) Scope 1'!$Y$6:$Y$79,'2-2. Quantitative data_Market'!$B$54,'3-1. (Raw data) Scope 1'!$D$6:$D$79,'2-2. Quantitative data_Market'!$B62,'3-1. (Raw data) Scope 1'!$AB$6:$AB$79,'2-2. Quantitative data_Market'!G$55) -> 23.9268 | H62: =SUMIFS('3-1. (Raw data) Scope 1'!$AT$6:$AT$79,'3-1. (Raw data) Scope 1'!$Y$6:$Y$79,'2-2. Quantitative data_Market'!$B$54,'3-1. (Raw data) Scope 1'!$D$6:$D$79,'2-2. Quantitative data_Market'!$B62,'3-1. (Raw data) Scope 1'!$AB$6:$AB$79,'2-2. Quantitative data_Market'!H$55) -> 0 | I62: =SUMIFS('3-1. (Raw data) Scope 1'!$AT$6:$AT$79,'3-1. (Raw data) Scope 1'!$Y$6:$Y$79,'2-2. Quantitative data_Market'!$B$54,'3-1. (Raw data) Scope 1'!$D$6:$D$79,'2-2. Quantitative data_Market'!$B62,'3-1. (Raw data) Scope 1'!$AB$6:$AB$79,'2-2. Quantitative data_Market'!I$55) -> 0 | J62: =SUMIFS('3-1. (Raw data) Scope 1'!$AT$6:$AT$79,'3-1. (Raw data) Scope 1'!$Y$6:$Y$79,'2-2. Quantitative data_Market'!$B$54,'3-1. (Raw data) Scope 1'!$D$6:$D$79,'2-2. Quantitative data_Market'!$B62,'3-1. (Raw data) Scope 1'!$AB$6:$AB$79,'2-2. Quantitative data_Market'!J$55) -> 0 | K62: =SUMIFS('3-2. (Raw data) Scope2_Location'!$AY$6:$AY$33,'3-2. (Raw data) Scope2_Location'!$AD$6:$AD$33,'2-2. Quantitative data_Market'!$B$54,'3-2. (Raw data) Scope2_Location'!$D$6:$D$33,'2-2. Quantitative data_Market'!$B62) -> 2042.492 | L62: =SUMIFS('3-2. (Raw data) Scope2_Location'!$AY$6:$AY$33,'3-2. (Raw data) Scope2_Location'!$AD$6:$AD$33,'2-2. Quantitative data_Market'!$B$54,'3-2. (Raw data) Scope2_Location'!$D$6:$D$33,'2-2. Quantitative data_Market'!$B62) -> 2042.492 | M62: =SUMIFS('3-2. (Raw data) Scope2_Location'!$AR$6:$AR$33,'3-2. (Raw data) Scope2_Location'!$AD$6:$AD$33,'2-2. Quantitative data_Market'!B$54,'3-2. (Raw data) Scope2_Location'!$D$6:$D$33,'2-2. Quantitative data_Market'!$B62) -> 2347.692
A63: 2023년 | B63: MFAFA Co., Ltd | C63: =D63+K63 -> 2.5755052 | D63: =SUM(E63:J63) -> 0 | E63: =SUMIFS('3-1. (Raw data) Scope 1'!$AT$6:$AT$79,'3-1. (Raw data) Scope 1'!$Y$6:$Y$79,'2-2. Quantitative data_Market'!$B$54,'3-1. (Raw data) Scope 1'!$D$6:$D$79,'2-2. Quantitative data_Market'!$B63,'3-1. (Raw data) Scope 1'!$AB$6:$AB$79,'2-2. Quantitative data_Market'!E$55) -> 0 | F63: =SUMIFS('3-1. (Raw data) Scope 1'!$AT$6:$AT$79,'3-1. (Raw data) Scope 1'!$Y$6:$Y$79,'2-2. Quantitative data_Market'!$B$54,'3-1. (Raw data) Scope 1'!$D$6:$D$79,'2-2. Quantitative data_Market'!$B63,'3-1. (Raw data) Scope 1'!$AB$6:$AB$79,'2-2. Quantitative data_Market'!F$55) -> 0 | G63: =SUMIFS('3-1. (Raw data) Scope 1'!$AT$6:$AT$79,'3-1. (Raw data) Scope 1'!$Y$6:$Y$79,'2-2. Quantitative data_Market'!$B$54,'3-1. (Raw data) Scope 1'!$D$6:$D$79,'2-2. Quantitative data_Market'!$B63,'3-1. (Raw data) Scope 1'!$AB$6:$AB$79,'2-2. Quantitative data_Market'!G$55) -> 0 | H63: =SUMIFS('3-1. (Raw data) Scope 1'!$AT$6:$AT$79,'3-1. (Raw data) Scope 1'!$Y$6:$Y$79,'2-2. Quantitative data_Market'!$B$54,'3-1. (Raw data) Scope 1'!$D$6:$D$79,'2-2. Quantitative data_Market'!$B63,'3-1. (Raw data) Scope 1'!$AB$6:$AB$79,'2-2. Quantitative data_Market'!H$55) -> 0 | I63: =SUMIFS('3-1. (Raw data) Scope 1'!$AT$6:$AT$79,'3-1. (Raw data) Scope 1'!$Y$6:$Y$79,'2-2. Quantitative data_Market'!$B$54,'3-1. (Raw data) Scope 1'!$D$6:$D$79,'2-2. Quantitative data_Market'!$B63,'3-1. (Raw data) Scope 1'!$AB$6:$AB$79,'2-2. Quantitative data_Market'!I$55) -> 0 | J63: =SUMIFS('3-1. (Raw data) Scope 1'!$AT$6:$AT$79,'3-1. (Raw data) Scope 1'!$Y$6:$Y$79,'2-2. Quantitative data_Market'!$B$54,'3-1. (Raw data) Scope 1'!$D$6:$D$79,'2-2. Quantitative data_Market'!$B63,'3-1. (Raw data) Scope 1'!$AB$6:$AB$79,'2-2. Quantitative data_Market'!J$55) -> 0 | K63: =SUMIFS('3-2. (Raw data) Scope2_Location'!$AY$6:$AY$33,'3-2. (Raw data) Scope2_Location'!$AD$6:$AD$33,'2-2. Quantitative data_Market'!$B$54,'3-2. (Raw data) Scope2_Location'!$D$6:$D$33,'2-2. Quantitative data_Market'!$B63) -> 2.5755052 | L63: =SUMIFS('3-2. (Raw data) Scope2_Location'!$AY$6:$AY$33,'3-2. (Raw data) Scope2_Location'!$AD$6:$AD$33,'2-2. Quantitative data_Market'!$B$54,'3-2. (Raw data) Scope2_Location'!$D$6:$D$33,'2-2. Quantitative data_Market'!$B63) -> 2.5755052 | M63: =SUMIFS('3-2. (Raw data) Scope2_Location'!$AR$6:$AR$33,'3-2. (Raw data) Scope2_Location'!$AD$6:$AD$33,'2-2. Quantitative data_Market'!B$54,'3-2. (Raw data) Scope2_Location'!$D$6:$D$33,'2-2. Quantitative data_Market'!$B63) -> 5.5154
A64: 2024년 | B64: 2024 | C64: Scope 1 + Scope 2 | D64: Scope 1 | K64: Scope 2
A65: 2024년 | D65: Scope 1 GHG Emissions by Facility | E65: {=_xlfn.TOROW(_xlfn.UNIQUE('3-1. (Raw data) Scope 1'!AB6:AB79))} -> Automotive gasoline (petrol) | F65: Industrial Wastes | G65: Biodiesel | H65: Liquefied Petroleum Gas (LPG) | I65: Gas / Diesel oil | J65: Hydrofluorocarbons(HFCs) | K65: Scope 2 GHG Emissions by Facility | L65: Electricity | M65: Electricity Consumption (MWh)
A66: 2024년 | B66: Total | C66: =D66+K66 -> 17134.191 | D66: =SUM(E66:J66) -> 5415.5677 | E66: =SUM(E67:E73) -> 945.71449 | F66: =SUM(F67:F73) -> 4052.7375 | G66: =SUM(G67:G73) -> 73.41294 | H66: =SUM(H67:H73) -> 7.477188 | I66: =SUM(I67:I73) -> 48.579677 | J66: =SUM(J67:J73) -> 287.6459 | K66: =SUM(K67:K73) -> 11718.623 | L66: =SUM(L67:L73) -> 11718.623 | M66: =SUM(M67:M73) -> 16374.658
A67: 2024년 | B67: {=_xlfn.UNIQUE('3-2. (Raw data) Scope2_Location'!$D$6:$D$33)} -> HOJEON LIMITED Co., Ltd | C67: =D67+K67 -> 242.87393 | D67: =SUM(E67:J67) -> 58.215798 | E67: =SUMIFS('3-1. (Raw data) Scope 1'!$AT$6:$AT$79,'3-1. (Raw data) Scope 1'!$Y$6:$Y$79,'2-2. Quantitative data_Market'!$B$64,'3-1. (Raw data) Scope 1'!$D$6:$D$79,'2-2. Quantitative data_Market'!$B67,'3-1. (Raw data) Scope 1'!$AB$6:$AB$79,'2-2. Quantitative data_Market'!E$65) -> 58.215798 | F67: =SUMIFS('3-1. (Raw data) Scope 1'!$AT$6:$AT$79,'3-1. (Raw data) Scope 1'!$Y$6:$Y$79,'2-2. Quantitative data_Market'!$B$64,'3-1. (Raw data) Scope 1'!$D$6:$D$79,'2-2. Quantitative data_Market'!$B67,'3-1. (Raw data) Scope 1'!$AB$6:$AB$79,'2-2. Quantitative data_Market'!F$65) -> 0 | G67: =SUMIFS('3-1. (Raw data) Scope 1'!$AT$6:$AT$79,'3-1. (Raw data) Scope 1'!$Y$6:$Y$79,'2-2. Quantitative data_Market'!$B$64,'3-1. (Raw data) Scope 1'!$D$6:$D$79,'2-2. Quantitative data_Market'!$B67,'3-1. (Raw data) Scope 1'!$AB$6:$AB$79,'2-2. Quantitative data_Market'!G$65) -> 0 | H67: =SUMIFS('3-1. (Raw data) Scope 1'!$AT$6:$AT$79,'3-1. (Raw data) Scope 1'!$Y$6:$Y$79,'2-2. Quantitative data_Market'!$B$64,'3-1. (Raw data) Scope 1'!$D$6:$D$79,'2-2. Quantitative data_Market'!$B67,'3-1. (Raw data) Scope 1'!$AB$6:$AB$79,'2-2. Quantitative data_Market'!H$65) -> 0 | I67: =SUMIFS('3-1. (Raw data) Scope 1'!$AT$6:$AT$79,'3-1. (Raw data) Scope 1'!$Y$6:$Y$79,'2-2. Quantitative data_Market'!$B$64,'3-1. (Raw data) Scope 1'!$D$6:$D$79,'2-2. Quantitative data_Market'!$B67,'3-1. (Raw data) Scope 1'!$AB$6:$AB$79,'2-2. Quantitative data_Market'!I$65) -> 0 | J67: =SUMIFS('3-1. (Raw data) Scope 1'!$AT$6:$AT$79,'3-1. (Raw data) Scope 1'!$Y$6:$Y$79,'2-2. Quantitative data_Market'!$B$64,'3-1. (Raw data) Scope 1'!$D$6:$D$79,'2-2. Quantitative data_Market'!$B67,'3-1. (Raw data) Scope 1'!$AB$6:$AB$79,'2-2. Quantitative data_Market'!J$65) -> 0 | K67: =SUMIFS('3-3. (Raw data) Scope 2_Market'!$AY$6:$AY$33,'3-3. (Raw data) Scope 2_Market'!$AD$6:$AD$33,'2-2. Quantitative data_Market'!$B$64,'3-3. (Raw data) Scope 2_Market'!$D$6:$D$33,'2-2. Quantitative data_Market'!$B67) -> 184.65813 | L67: =SUMIFS('3-3. (Raw data) Scope 2_Market'!$AY$6:$AY$33,'3-3. (Raw data) Scope 2_Market'!$AD$6:$AD$33,'2-2. Quantitative data_Market'!$B$64,'3-3. (Raw data) Scope 2_Market'!$D$6:$D$33,'2-2. Quantitative data_Market'!$B67) -> 184.65813 | M67: =SUMIFS('3-2. (Raw data) Scope2_Location'!$AR$6:$AR$33,'3-2. (Raw data) Scope2_Location'!$AD$6:$AD$33,'2-2. Quantitative data_Market'!B$64,'3-2. (Raw data) Scope2_Location'!$D$6:$D$33,'2-2. Quantitative data_Market'!$B67) -> 395.44221
A68: 2024년 | B68: KAHOINDAH CITRAGARMENT | C68: =D68+K68 -> 877.44929 | D68: =SUM(E68:J68) -> 877.44929 | E68: =SUMIFS('3-1. (Raw data) Scope 1'!$AT$6:$AT$79,'3-1. (Raw data) Scope 1'!$Y$6:$Y$79,'2-2. Quantitative data_Market'!$B$64,'3-1. (Raw data) Scope 1'!$D$6:$D$79,'2-2. Quantitative data_Market'!$B68,'3-1. (Raw data) Scope 1'!$AB$6:$AB$79,'2-2. Quantitative data_Market'!E$65) -> 46.591949 | F68: =SUMIFS('3-1. (Raw data) Scope 1'!$AT$6:$AT$79,'3-1. (Raw data) Scope 1'!$Y$6:$Y$79,'2-2. Quantitative data_Market'!$B$64,'3-1. (Raw data) Scope 1'!$D$6:$D$79,'2-2. Quantitative data_Market'!$B68,'3-1. (Raw data) Scope 1'!$AB$6:$AB$79,'2-2. Quantitative data_Market'!F$65) -> 827.64421 | G68: =SUMIFS('3-1. (Raw data) Scope 1'!$AT$6:$AT$79,'3-1. (Raw data) Scope 1'!$Y$6:$Y$79,'2-2. Quantitative data_Market'!$B$64,'3-1. (Raw data) Scope 1'!$D$6:$D$79,'2-2. Quantitative data_Market'!$B68,'3-1. (Raw data) Scope 1'!$AB$6:$AB$79,'2-2. Quantitative data_Market'!G$65) -> 2.7112741 | H68: =SUMIFS('3-1. (Raw data) Scope 1'!$AT$6:$AT$79,'3-1. (Raw data) Scope 1'!$Y$6:$Y$79,'2-2. Quantitative data_Market'!$B$64,'3-1. (Raw data) Scope 1'!$D$6:$D$79,'2-2. Quantitative data_Market'!$B68,'3-1. (Raw data) Scope 1'!$AB$6:$AB$79,'2-2. Quantitative data_Market'!H$65) -> 0.50184933 | I68: =SUMIFS('3-1. (Raw data) Scope 1'!$AT$6:$AT$79,'3-1. (Raw data) Scope 1'!$Y$6:$Y$79,'2-2. Quantitative data_Market'!$B$64,'3-1. (Raw data) Scope 1'!$D$6:$D$79,'2-2. Quantitative data_Market'!$B68,'3-1. (Raw data) Scope 1'!$AB$6:$AB$79,'2-2. Quantitative data_Market'!I$65) -> 0 | J68: =SUMIFS('3-1. (Raw data) Scope 1'!$AT$6:$AT$79,'3-1. (Raw data) Scope 1'!$Y$6:$Y$79,'2-2. Quantitative data_Market'!$B$64,'3-1. (Raw data) Scope 1'!$D$6:$D$79,'2-2. Quantitative data_Market'!$B68,'3-1. (Raw data) Scope 1'!$AB$6:$AB$79,'2-2. Quantitative data_Market'!J$65) -> 0 | K68: =SUMIFS('3-3. (Raw data) Scope 2_Market'!$AY$6:$AY$33,'3-3. (Raw data) Scope 2_Market'!$AD$6:$AD$33,'2-2. Quantitative data_Market'!$B$64,'3-3. (Raw data) Scope 2_Market'!$D$6:$D$33,'2-2. Quantitative data_Market'!$B68) -> 0 | L68: =SUMIFS('3-3. (Raw data) Scope 2_Market'!$AY$6:$AY$33,'3-3. (Raw data) Scope 2_Market'!$AD$6:$AD$33,'2-2. Quantitative data_Market'!$B$64,'3-3. (Raw data) Scope 2_Market'!$D$6:$D$33,'2-2. Quantitative data_Market'!$B68) -> 0 | M68: =SUMIFS('3-2. (Raw data) Scope2_Location'!$AR$6:$AR$33,'3-2. (Raw data) Scope2_Location'!$AD$6:$AD$33,'2-2. Quantitative data_Market'!B$64,'3-2. (Raw data) Scope2_Location'!$D$6:$D$33,'2-2. Quantitative data_Market'!$B68) -> 1527.066
A69: 2024년 | B69: PT. YONGJIN JAVASUKA GARMENT (1공장) | C69: =D69+K69 -> 2549.6847 | D69: =SUM(E69:J69) -> 1334.7981 | E69: =SUMIFS('3-1. (Raw data) Scope 1'!$AT$6:$AT$79,'3-1. (Raw data) Scope 1'!$Y$6:$Y$79,'2-2. Quantitative data_Market'!$B$64,'3-1. (Raw data) Scope 1'!$D$6:$D$79,'2-2. Quantitative data_Market'!$B69,'3-1. (Raw data) Scope 1'!$AB$6:$AB$79,'2-2. Quantitative data_Market'!E$65) -> 140.07552 | F69: =SUMIFS('3-1. (Raw data) Scope 1'!$AT$6:$AT$79,'3-1. (Raw data) Scope 1'!$Y$6:$Y$79,'2-2. Quantitative data_Market'!$B$64,'3-1. (Raw data) Scope 1'!$D$6:$D$79,'2-2. Quantitative data_Market'!$B69,'3-1. (Raw data) Scope 1'!$AB$6:$AB$79,'2-2. Quantitative data_Market'!F$65) -> 1149.1249 | G69: =SUMIFS('3-1. (Raw data) Scope 1'!$AT$6:$AT$79,'3-1. (Raw data) Scope 1'!$Y$6:$Y$79,'2-2. Quantitative data_Market'!$B$64,'3-1. (Raw data) Scope 1'!$D$6:$D$79,'2-2. Quantitative data_Market'!$B69,'3-1. (Raw data) Scope 1'!$AB$6:$AB$79,'2-2. Quantitative data_Market'!G$65) -> 0 | H69: =SUMIFS('3-1. (Raw data) Scope 1'!$AT$6:$AT$79,'3-1. (Raw data) Scope 1'!$Y$6:$Y$79,'2-2. Quantitative data_Market'!$B$64,'3-1. (Raw data) Scope 1'!$D$6:$D$79,'2-2. Quantitative data_Market'!$B69,'3-1. (Raw data) Scope 1'!$AB$6:$AB$79,'2-2. Quantitative data_Market'!H$65) -> 2.6041798 | I69: =SUMIFS('3-1. (Raw data) Scope 1'!$AT$6:$AT$79,'3-1. (Raw data) Scope 1'!$Y$6:$Y$79,'2-2. Quantitative data_Market'!$B$64,'3-1. (Raw data) Scope 1'!$D$6:$D$79,'2-2. Quantitative data_Market'!$B69,'3-1. (Raw data) Scope 1'!$AB$6:$AB$79,'2-2. Quantitative data_Market'!I$65) -> 9.1196506 | J69: =SUMIFS('3-1. (Raw data) Scope 1'!$AT$6:$AT$79,'3-1. (Raw data) Scope 1'!$Y$6:$Y$79,'2-2. Quantitative data_Market'!$B$64,'3-1. (Raw data) Scope 1'!$D$6:$D$79,'2-2. Quantitative data_Market'!$B69,'3-1. (Raw data) Scope 1'!$AB$6:$AB$79,'2-2. Quantitative data_Market'!J$65) -> 33.8738 | K69: =SUMIFS('3-3. (Raw data) Scope 2_Market'!$AY$6:$AY$33,'3-3. (Raw data) Scope 2_Market'!$AD$6:$AD$33,'2-2. Quantitative data_Market'!$B$64,'3-3. (Raw data) Scope 2_Market'!$D$6:$D$33,'2-2. Quantitative data_Market'!$B69) -> 1214.8866 | L69: =SUMIFS('3-3. (Raw data) Scope 2_Market'!$AY$6:$AY$33,'3-3. (Raw data) Scope 2_Market'!$AD$6:$AD$33,'2-2. Quantitative data_Market'!$B$64,'3-3. (Raw data) Scope 2_Market'!$D$6:$D$33,'2-2. Quantitative data_Market'!$B69) -> 1214.8866 | M69: =SUMIFS('3-2. (Raw data) Scope2_Location'!$AR$6:$AR$33,'3-2. (Raw data) Scope2_Location'!$AD$6:$AD$33,'2-2. Quantitative data_Market'!B$64,'3-2. (Raw data) Scope2_Location'!$D$6:$D$33,'2-2. Quantitative data_Market'!$B69) -> 1546.4214
A70: 2024년 | B70: PT. YONGJIN JAVASUKA GARMENT (2,3공장) | C70: =D70+K70 -> 10134.755 | D70: =SUM(E70:J70) -> 2918.3443 | E70: =SUMIFS('3-1. (Raw data) Scope 1'!$AT$6:$AT$79,'3-1. (Raw data) Scope 1'!$Y$6:$Y$79,'2-2. Quantitative data_Market'!$B$64,'3-1. (Raw data) Scope 1'!$D$6:$D$79,'2-2. Quantitative data_Market'!$B70,'3-1. (Raw data) Scope 1'!$AB$6:$AB$79,'2-2. Quantitative data_Market'!E$65) -> 544.77263 | F70: =SUMIFS('3-1. (Raw data) Scope 1'!$AT$6:$AT$79,'3-1. (Raw data) Scope 1'!$Y$6:$Y$79,'2-2. Quantitative data_Market'!$B$64,'3-1. (Raw data) Scope 1'!$D$6:$D$79,'2-2. Quantitative data_Market'!$B70,'3-1. (Raw data) Scope 1'!$AB$6:$AB$79,'2-2. Quantitative data_Market'!F$65) -> 2075.9684 | G70: =SUMIFS('3-1. (Raw data) Scope 1'!$AT$6:$AT$79,'3-1. (Raw data) Scope 1'!$Y$6:$Y$79,'2-2. Quantitative data_Market'!$B$64,'3-1. (Raw data) Scope 1'!$D$6:$D$79,'2-2. Quantitative data_Market'!$B70,'3-1. (Raw data) Scope 1'!$AB$6:$AB$79,'2-2. Quantitative data_Market'!G$65) -> 0 | H70: =SUMIFS('3-1. (Raw data) Scope 1'!$AT$6:$AT$79,'3-1. (Raw data) Scope 1'!$Y$6:$Y$79,'2-2. Quantitative data_Market'!$B$64,'3-1. (Raw data) Scope 1'!$D$6:$D$79,'2-2. Quantitative data_Market'!$B70,'3-1. (Raw data) Scope 1'!$AB$6:$AB$79,'2-2. Quantitative data_Market'!H$65) -> 4.3711589 | I70: =SUMIFS('3-1. (Raw data) Scope 1'!$AT$6:$AT$79,'3-1. (Raw data) Scope 1'!$Y$6:$Y$79,'2-2. Quantitative data_Market'!$B$64,'3-1. (Raw data) Scope 1'!$D$6:$D$79,'2-2. Quantitative data_Market'!$B70,'3-1. (Raw data) Scope 1'!$AB$6:$AB$79,'2-2. Quantitative data_Market'!I$65) -> 39.460027 | J70: =SUMIFS('3-1. (Raw data) Scope 1'!$AT$6:$AT$79,'3-1. (Raw data) Scope 1'!$Y$6:$Y$79,'2-2. Quantitative data_Market'!$B$64,'3-1. (Raw data) Scope 1'!$D$6:$D$79,'2-2. Quantitative data_Market'!$B70,'3-1. (Raw data) Scope 1'!$AB$6:$AB$79,'2-2. Quantitative data_Market'!J$65) -> 253.7721 | K70: =SUMIFS('3-3. (Raw data) Scope 2_Market'!$AY$6:$AY$33,'3-3. (Raw data) Scope 2_Market'!$AD$6:$AD$33,'2-2. Quantitative data_Market'!$B$64,'3-3. (Raw data) Scope 2_Market'!$D$6:$D$33,'2-2. Quantitative data_Market'!$B70) -> 7216.4106 | L70: =SUMIFS('3-3. (Raw data) Scope 2_Market'!$AY$6:$AY$33,'3-3. (Raw data) Scope 2_Market'!$AD$6:$AD$33,'2-2. Quantitative data_Market'!$B$64,'3-3. (Raw data) Scope 2_Market'!$D$6:$D$33,'2-2. Quantitative data_Market'!$B70) -> 7216.4106 | M70: =SUMIFS('3-2. (Raw data) Scope2_Location'!$AR$6:$AR$33,'3-2. (Raw data) Scope2_Location'!$AD$6:$AD$33,'2-2. Quantitative data_Market'!B$64,'3-2. (Raw data) Scope2_Location'!$D$6:$D$33,'2-2. Quantitative data_Market'!$B70) -> 9336.8608
A71: 2024년 | B71: PT. HJL INDO NETWORKS | C71: =D71+K71 -> 128.43711 | D71: =SUM(E71:J71) -> 110.40541 | E71: =SUMIFS('3-1. (Raw data) Scope 1'!$AT$6:$AT$79,'3-1. (Raw data) Scope 1'!$Y$6:$Y$79,'2-2. Quantitative data_Market'!$B$64,'3-1. (Raw data) Scope 1'!$D$6:$D$79,'2-2. Quantitative data_Market'!$B71,'3-1. (Raw data) Scope 1'!$AB$6:$AB$79,'2-2. Quantitative data_Market'!E$65) -> 110.40541 | F71: =SUMIFS('3-1. (Raw data) Scope 1'!$AT$6:$AT$79,'3-1. (Raw data) Scope 1'!$Y$6:$Y$79,'2-2. Quantitative data_Market'!$B$64,'3-1. (Raw data) Scope 1'!$D$6:$D$79,'2-2. Quantitative data_Market'!$B71,'3-1. (Raw data) Scope 1'!$AB$6:$AB$79,'2-2. Quantitative data_Market'!F$65) -> 0 | G71: =SUMIFS('3-1. (Raw data) Scope 1'!$AT$6:$AT$79,'3-1. (Raw data) Scope 1'!$Y$6:$Y$79,'2-2. Quantitative data_Market'!$B$64,'3-1. (Raw data) Scope 1'!$D$6:$D$79,'2-2. Quantitative data_Market'!$B71,'3-1. (Raw data) Scope 1'!$AB$6:$AB$79,'2-2. Quantitative data_Market'!G$65) -> 0 | H71: =SUMIFS('3-1. (Raw data) Scope 1'!$AT$6:$AT$79,'3-1. (Raw data) Scope 1'!$Y$6:$Y$79,'2-2. Quantitative data_Market'!$B$64,'3-1. (Raw data) Scope 1'!$D$6:$D$79,'2-2. Quantitative data_Market'!$B71,'3-1. (Raw data) Scope 1'!$AB$6:$AB$79,'2-2. Quantitative data_Market'!H$65) -> 0 | I71: =SUMIFS('3-1. (Raw data) Scope 1'!$AT$6:$AT$79,'3-1. (Raw data) Scope 1'!$Y$6:$Y$79,'2-2. Quantitative data_Market'!$B$64,'3-1. (Raw data) Scope 1'!$D$6:$D$79,'2-2. Quantitative data_Market'!$B71,'3-1. (Raw data) Scope 1'!$AB$6:$AB$79,'2-2. Quantitative data_Market'!I$65) -> 0 | J71: =SUMIFS('3-1. (Raw data) Scope 1'!$AT$6:$AT$79,'3-1. (Raw data) Scope 1'!$Y$6:$Y$79,'2-2. Quantitative data_Market'!$B$64,'3-1. (Raw data) Scope 1'!$D$6:$D$79,'2-2. Quantitative data_Market'!$B71,'3-1. (Raw data) Scope 1'!$AB$6:$AB$79,'2-2. Quantitative data_Market'!J$65) -> 0 | K71: =SUMIFS('3-3. (Raw data) Scope 2_Market'!$AY$6:$AY$33,'3-3. (Raw data) Scope 2_Market'!$AD$6:$AD$33,'2-2. Quantitative data_Market'!$B$64,'3-3. (Raw data) Scope 2_Market'!$D$6:$D$33,'2-2. Quantitative data_Market'!$B71) -> 18.031707 | L71: =SUMIFS('3-3. (Raw data) Scope 2_Market'!$AY$6:$AY$33,'3-3. (Raw data) Scope 2_Market'!$AD$6:$AD$33,'2-2. Quantitative data_Market'!$B$64,'3-3. (Raw data) Scope 2_Market'!$D$6:$D$33,'2-2. Quantitative data_Market'!$B71) -> 18.031707 | M71: =SUMIFS('3-2. (Raw data) Scope2_Location'!$AR$6:$AR$33,'3-2. (Raw data) Scope2_Location'!$AD$6:$AD$33,'2-2. Quantitative data_Market'!B$64,'3-2. (Raw data) Scope2_Location'!$D$6:$D$33,'2-2. Quantitative data_Market'!$B71) -> 20.7261
A72: 2024년 | B72: PT.HOGA REKSA GARMENT | C72: =D72+K72 -> 3198.3873 | D72: =SUM(E72:J72) -> 116.35485 | E72: =SUMIFS('3-1. (Raw data) Scope 1'!$AT$6:$AT$79,'3-1. (Raw data) Scope 1'!$Y$6:$Y$79,'2-2. Quantitative data_Market'!$B$64,'3-1. (Raw data) Scope 1'!$D$6:$D$79,'2-2. Quantitative data_Market'!$B72,'3-1. (Raw data) Scope 1'!$AB$6:$AB$79,'2-2. Quantitative data_Market'!E$65) -> 45.653187 | F72: =SUMIFS('3-1. (Raw data) Scope 1'!$AT$6:$AT$79,'3-1. (Raw data) Scope 1'!$Y$6:$Y$79,'2-2. Quantitative data_Market'!$B$64,'3-1. (Raw data) Scope 1'!$D$6:$D$79,'2-2. Quantitative data_Market'!$B72,'3-1. (Raw data) Scope 1'!$AB$6:$AB$79,'2-2. Quantitative data_Market'!F$65) -> 0 | G72: =SUMIFS('3-1. (Raw data) Scope 1'!$AT$6:$AT$79,'3-1. (Raw data) Scope 1'!$Y$6:$Y$79,'2-2. Quantitative data_Market'!$B$64,'3-1. (Raw data) Scope 1'!$D$6:$D$79,'2-2. Quantitative data_Market'!$B72,'3-1. (Raw data) Scope 1'!$AB$6:$AB$79,'2-2. Quantitative data_Market'!G$65) -> 70.701666 | H72: =SUMIFS('3-1. (Raw data) Scope 1'!$AT$6:$AT$79,'3-1. (Raw data) Scope 1'!$Y$6:$Y$79,'2-2. Quantitative data_Market'!$B$64,'3-1. (Raw data) Scope 1'!$D$6:$D$79,'2-2. Quantitative data_Market'!$B72,'3-1. (Raw data) Scope 1'!$AB$6:$AB$79,'2-2. Quantitative data_Market'!H$65) -> 0 | I72: =SUMIFS('3-1. (Raw data) Scope 1'!$AT$6:$AT$79,'3-1. (Raw data) Scope 1'!$Y$6:$Y$79,'2-2. Quantitative data_Market'!$B$64,'3-1. (Raw data) Scope 1'!$D$6:$D$79,'2-2. Quantitative data_Market'!$B72,'3-1. (Raw data) Scope 1'!$AB$6:$AB$79,'2-2. Quantitative data_Market'!I$65) -> 0 | J72: =SUMIFS('3-1. (Raw data) Scope 1'!$AT$6:$AT$79,'3-1. (Raw data) Scope 1'!$Y$6:$Y$79,'2-2. Quantitative data_Market'!$B$64,'3-1. (Raw data) Scope 1'!$D$6:$D$79,'2-2. Quantitative data_Market'!$B72,'3-1. (Raw data) Scope 1'!$AB$6:$AB$79,'2-2. Quantitative data_Market'!J$65) -> 0 | K72: =SUMIFS('3-3. (Raw data) Scope 2_Market'!$AY$6:$AY$33,'3-3. (Raw data) Scope 2_Market'!$AD$6:$AD$33,'2-2. Quantitative data_Market'!$B$64,'3-3. (Raw data) Scope 2_Market'!$D$6:$D$33,'2-2. Quantitative data_Market'!$B72) -> 3082.0324 | L72: =SUMIFS('3-3. (Raw data) Scope 2_Market'!$AY$6:$AY$33,'3-3. (Raw data) Scope 2_Market'!$AD$6:$AD$33,'2-2. Quantitative data_Market'!$B$64,'3-3. (Raw data) Scope 2_Market'!$D$6:$D$33,'2-2. Quantitative data_Market'!$B72) -> 3082.0324 | M72: =SUMIFS('3-2. (Raw data) Scope2_Location'!$AR$6:$AR$33,'3-2. (Raw data) Scope2_Location'!$AD$6:$AD$33,'2-2. Quantitative data_Market'!B$64,'3-2. (Raw data) Scope2_Location'!$D$6:$D$33,'2-2. Quantitative data_Market'!$B72) -> 3542.566
A73: 2024년 | B73: MFAFA Co., Ltd | C73: =D73+K73 -> 2.6038034 | D73: =SUM(E73:J73) -> 0 | E73: =SUMIFS('3-1. (Raw data) Scope 1'!$AT$6:$AT$79,'3-1. (Raw data) Scope 1'!$Y$6:$Y$79,'2-2. Quantitative data_Market'!$B$64,'3-1. (Raw data) Scope 1'!$D$6:$D$79,'2-2. Quantitative data_Market'!$B73,'3-1. (Raw data) Scope 1'!$AB$6:$AB$79,'2-2. Quantitative data_Market'!E$65) -> 0 | F73: =SUMIFS('3-1. (Raw data) Scope 1'!$AT$6:$AT$79,'3-1. (Raw data) Scope 1'!$Y$6:$Y$79,'2-2. Quantitative data_Market'!$B$64,'3-1. (Raw data) Scope 1'!$D$6:$D$79,'2-2. Quantitative data_Market'!$B73,'3-1. (Raw data) Scope 1'!$AB$6:$AB$79,'2-2. Quantitative data_Market'!F$65) -> 0 | G73: =SUMIFS('3-1. (Raw data) Scope 1'!$AT$6:$AT$79,'3-1. (Raw data) Scope 1'!$Y$6:$Y$79,'2-2. Quantitative data_Market'!$B$64,'3-1. (Raw data) Scope 1'!$D$6:$D$79,'2-2. Quantitative data_Market'!$B73,'3-1. (Raw data) Scope 1'!$AB$6:$AB$79,'2-2. Quantitative data_Market'!G$65) -> 0 | H73: =SUMIFS('3-1. (Raw data) Scope 1'!$AT$6:$AT$79,'3-1. (Raw data) Scope 1'!$Y$6:$Y$79,'2-2. Quantitative data_Market'!$B$64,'3-1. (Raw data) Scope 1'!$D$6:$D$79,'2-2. Quantitative data_Market'!$B73,'3-1. (Raw data) Scope 1'!$AB$6:$AB$79,'2-2. Quantitative data_Market'!H$65) -> 0 | I73: =SUMIFS('3-1. (Raw data) Scope 1'!$AT$6:$AT$79,'3-1. (Raw data) Scope 1'!$Y$6:$Y$79,'2-2. Quantitative data_Market'!$B$64,'3-1. (Raw data) Scope 1'!$D$6:$D$79,'2-2. Quantitative data_Market'!$B73,'3-1. (Raw data) Scope 1'!$AB$6:$AB$79,'2-2. Quantitative data_Market'!I$65) -> 0 | J73: =SUMIFS('3-1. (Raw data) Scope 1'!$AT$6:$AT$79,'3-1. (Raw data) Scope 1'!$Y$6:$Y$79,'2-2. Quantitative data_Market'!$B$64,'3-1. (Raw data) Scope 1'!$D$6:$D$79,'2-2. Quantitative data_Market'!$B73,'3-1. (Raw data) Scope 1'!$AB$6:$AB$79,'2-2. Quantitative data_Market'!J$65) -> 0 | K73: =SUMIFS('3-3. (Raw data) Scope 2_Market'!$AY$6:$AY$33,'3-3. (Raw data) Scope 2_Market'!$AD$6:$AD$33,'2-2. Quantitative data_Market'!$B$64,'3-3. (Raw data) Scope 2_Market'!$D$6:$D$33,'2-2. Quantitative data_Market'!$B73) -> 2.6038034 | L73: =SUMIFS('3-3. (Raw data) Scope 2_Market'!$AY$6:$AY$33,'3-3. (Raw data) Scope 2_Market'!$AD$6:$AD$33,'2-2. Quantitative data_Market'!$B$64,'3-3. (Raw data) Scope 2_Market'!$D$6:$D$33,'2-2. Quantitative data_Market'!$B73) -> 2.6038034 | M73: =SUMIFS('3-2. (Raw data) Scope2_Location'!$AR$6:$AR$33,'3-2. (Raw data) Scope2_Location'!$AD$6:$AD$33,'2-2. Quantitative data_Market'!B$64,'3-2. (Raw data) Scope2_Location'!$D$6:$D$33,'2-2. Quantitative data_Market'!$B73) -> 5.576
B74: * No steam purchase has been recorded.

Sheet (참고} 시각데이터
B1: 2022~2024년 연료 사용량 및 온실가스 배출량 그래프
B4: 2022~2024년 Scope 1+2 온실가스 배출량(tCO2eq)
B6: 호전실업 사업장별 Scope 1+2 온실가스 배출량 | P6: 연료 종류별 Scope 1+2 온실가스 배출량
C8: 데이터 수집년도 | D8: 사업장명 | E8: 데이터 수집범위 | F8: Scope 1 연료 종류 | G8: Scope 2 연료 종류 | Q8: 데이터 수집년도 | S8: 2024년
C9: -선택- | D9: -선택- | E9: -선택- | F9: -선택- | G9: -선택- | Q9: 사업장명 | S9: PT. YONGJIN JAVASUKA GARMENT (2,3공장)
C10: 2022년 | D10: 호전실업 주식회사 | E10: Scope 1 + Scope 2 | F10: {=_xlfn.UNIQUE('3-1. (Raw data) Scope 1'!AB6:AB79)} -> Automotive gasoline (petrol) | G10: 전력
C11: 2023년 | D11: KAHOINDAH CITRAGARMENT | E11: Scope 1 | F11: Industrial Wastes | G11: 스팀 | Q11: Scope 1+2 | R11: Scope 1 | Z11: Scope 2
C12: 2024년 | D12: PT. YONGJIN JAVASUKA GARMENT (1공장) | E12: Scope 2 | F12: Biodiesel | Q12: 합계 | R12: {=_xlfn.TOROW(_xlfn.UNIQUE('3-1. (Raw data) Scope 1'!AB6:AB79))} -> Automotive gasoline (petrol) | S12: Industrial Wastes | T12: Biodiesel | U12: Liquefied Petroleum Gas (LPG) | V12: Gas / Diesel oil | W12: Hydrofluorocarbons(HFCs) | Z12: 전력
D13: PT. YONGJIN JAVASUKA GARMENT (2,3공장) | F13: Liquefied Petroleum Gas (LPG) | O13: ▶ | Q13: =SUM(R13:Z13) -> 0 | R13: =SUMIFS('3-1. (Raw data) Scope 1'!$AT$6:$AT$79,'3-1. (Raw data) Scope 1'!$Y$6:$Y$79,'(참고} 시각데이터'!$S$8,'3-1. (Raw data) Scope 1'!$D$6:$D$79,'(참고} 시각데이터'!$S$9,'3-1. (Raw data) Scope 1'!$AB$6:$AB$79,'(참고} 시각데이터'!R$12) -> 0 | S13: =SUMIFS('3-1. (Raw data) Scope 1'!$AT$6:$AT$79,'3-1. (Raw data) Scope 1'!$Y$6:$Y$79,'(참고} 시각데이터'!$S$8,'3-1. (Raw data) Scope 1'!$D$6:$D$79,'(참고} 시각데이터'!$S$9,'3-1. (Raw data) Scope 1'!$AB$6:$AB$79,'(참고} 시각데이터'!S$12) -> 0 | T13: =SUMIFS('3-1. (Raw data) Scope 1'!$AT$6:$AT$79,'3-1. (Raw data) Scope 1'!$Y$6:$Y$79,'(참고} 시각데이터'!$S$8,'3-1. (Raw data) Scope 1'!$D$6:$D$79,'(참고} 시각데이터'!$S$9,'3-1. (Raw data) Scope 1'!$AB$6:$AB$79,'(참고} 시각데이터'!T$12) -> 0 | U13: =SUMIFS('3-1. (Raw data) Scope 1'!$AT$6:$AT$79,'3-1. (Raw data) Scope 1'!$Y$6:$Y$79,'(참고} 시각데이터'!$S$8,'3-1. (Raw data) Scope 1'!$D$6:$D$79,'(참고} 시각데이터'!$S$9,'3-1. (Raw data) Scope 1'!$AB$6:$AB$79,'(참고} 시각데이터'!U$12) -> 0 | V13: =SUMIFS('3-1. (Raw data) Scope 1'!$AT$6:$AT$79,'3-1. (Raw data) Scope 1'!$Y$6:$Y$79,'(참고} 시각데이터'!$S$8,'3-1. (Raw data) Scope 1'!$D$6:$D$79,'(참고} 시각데이터'!$S$9,'3-1. (Raw data) Scope 1'!$AB$6:$AB$79,'(참고} 시각데이터'!V$12) -> 0 | W13: =SUMIFS('3-1. (Raw data) Scope 1'!$AT$6:$AT$79,'3-1. (Raw data) Scope 1'!$Y$6:$Y$79,'(참고} 시각데이터'!$S$8,'3-1. (Raw data) Scope 1'!$D$6:$D$79,'(참고} 시각데이터'!$S$9,'3-1. (Raw data) Scope 1'!$AB$6:$AB$79,'(참고} 시각데이터'!W$12) -> 0 | X13: =SUMIFS('3-1. (Raw data) Scope 1'!$AT$6:$AT$79,'3-1. (Raw data) Scope 1'!$Y$6:$Y$79,'(참고} 시각데이터'!$S$8,'3-1. (Raw data) Scope 1'!$D$6:$D$79,'(참고} 시각데이터'!$S$9,'3-1. (Raw data) Scope 1'!$AB$6:$AB$79,'(참고} 시각데이터'!X$12) -> 0 | Z13: =SUMIFS('3-2. (Raw data) Scope2_Location'!$AY$6:$AY$33,'3-2. (Raw data) Scope2_Location'!$AD$6:$AD$33,'(참고} 시각데이터'!$S$8,'3-2. (Raw data) Scope2_Location'!$D$6:$D$33,'(참고} 시각데이터'!$S$9,'3-2. (Raw data) Scope2_Location'!$AE$6:$AE$33,'(참고} 시각데이터'!$Z$12) -> 0
D14: PT. HJL INDO NETWORKS | F14: Gas / Diesel oil
D15: PT.HOGA REKSA GARMENT | F15: Hydrofluorocarbons(HFCs)
D16: 주식회사 엠파파
B20: 특이사항 및 확인 필요사항 | D20: - HOGA 사업장의 2024년 배출량 급증 사유 -> 데이터 소수점자리 오기입 수정 完
D21: - YONGJIN 2,3공장의 2024년 Scope 1 배출량 급감 사유 : 산업폐기물의 사용량 급감으로 보이며, 단위 오기입인지 사용량 증가인지 확인 필요
C23: Scope 1+2 | E23: Scope 1 | M23: Scope 2 | Q23: Scope 1+2 | S23: Scope 1 | AA23: Scope 2
C24: 데이터 수집년도 | D24: 합계 | E24: {=_xlfn.TOROW(_xlfn.UNIQUE('3-1. (Raw data) Scope 1'!AB6:AB79))} -> Automotive gasoline (petrol) | F24: Industrial Wastes | G24: Biodiesel | H24: Liquefied Petroleum Gas (LPG) | I24: Gas / Diesel oil | J24: Hydrofluorocarbons(HFCs) | M24: 전력 | Q24: 데이터 수집년도 | R24: 합계 | S24: {=_xlfn.TOROW(_xlfn.UNIQUE('3-1. (Raw data) Scope 1'!AB6:AB79))} -> Automotive gasoline (petrol) | T24: Industrial Wastes | U24: Biodiesel | V24: Liquefied Petroleum Gas (LPG) | W24: Gas / Diesel oil | X24: Hydrofluorocarbons(HFCs) | AA24: 전력
C25: 2022년 | D25: =SUM(E25:M25) -> 0 | E25: =SUMIFS('3-1. (Raw data) Scope 1'!$AT$6:$AT$79,'3-1. (Raw data) Scope 1'!$Y$6:$Y$79,'(참고} 시각데이터'!$C25,'3-1. (Raw data) Scope 1'!$AB$6:$AB$79,E$24) -> 0 | F25: =SUMIFS('3-1. (Raw data) Scope 1'!$AT$6:$AT$79,'3-1. (Raw data) Scope 1'!$Y$6:$Y$79,'(참고} 시각데이터'!$C25,'3-1. (Raw data) Scope 1'!$AB$6:$AB$79,F$24) -> 0 | G25: =SUMIFS('3-1. (Raw data) Scope 1'!$AT$6:$AT$79,'3-1. (Raw data) Scope 1'!$Y$6:$Y$79,'(참고} 시각데이터'!$C25,'3-1. (Raw data) Scope 1'!$AB$6:$AB$79,G$24) -> 0 | H25: =SUMIFS('3-1. (Raw data) Scope 1'!$AT$6:$AT$79,'3-1. (Raw data) Scope 1'!$Y$6:$Y$79,'(참고} 시각데이터'!$C25,'3-1. (Raw data) Scope 1'!$AB$6:$AB$79,H$24) -> 0 | I25: =SUMIFS('3-1. (Raw data) Scope 1'!$AT$6:$AT$79,'3-1. (Raw data) Scope 1'!$Y$6:$Y$79,'(참고} 시각데이터'!$C25,'3-1. (Raw data) Scope 1'!$AB$6:$AB$79,I$24) -> 0 | J25: =SUMIFS('3-1. (Raw data) Scope 1'!$AT$6:$AT$79,'3-1. (Raw data) Scope 1'!$Y$6:$Y$79,'(참고} 시각데이터'!$C25,'3-1. (Raw data) Scope 1'!$AB$6:$AB$79,J$24) -> 0 | K25: =SUMIFS('3-1. (Raw data) Scope 1'!$AT$6:$AT$79,'3-1. (Raw data) Scope 1'!$Y$6:$Y$79,'(참고} 시각데이터'!$C25,'3-1. (Raw data) Scope 1'!$AB$6:$AB$79,K$24) -> 0 | M25: =SUMIFS('3-2. (Raw data) Scope2_Location'!$AY$6:$AY$33,'3-2. (Raw data) Scope2_Location'!$AD$6:$AD$33,'(참고} 시각데이터'!$C25,'3-2. (Raw data) Scope2_Location'!$AE$6:$AE$33,'(참고} 시각데이터'!$M$24) -> 0 | Q25: 2022년 | R25: =SUM(S25:AA25) -> 0 | S25: =SUMIFS('3-1. (Raw data) Scope 1'!$AT$6:$AT$79,'3-1. (Raw data) Scope 1'!$Y$6:$Y$79,'(참고} 시각데이터'!$Q$25,'3-1. (Raw data) Scope 1'!$D$6:$D$79,'(참고} 시각데이터'!$S$9,'3-1. (Raw data) Scope 1'!$AB$6:$AB$79,S$24) -> 0 | T25: =SUMIFS('3-1. (Raw data) Scope 1'!$AT$6:$AT$79,'3-1. (Raw data) Scope 1'!$Y$6:$Y$79,'(참고} 시각데이터'!$Q$25,'3-1. (Raw data) Scope 1'!$D$6:$D$79,'(참고} 시각데이터'!$S$9,'3-1. (Raw data) Scope 1'!$AB$6:$AB$79,'(참고} 시각데이터'!T$24) -> 0 | U25: =SUMIFS('3-1. (Raw data) Scope 1'!$AT$6:$AT$79,'3-1. (Raw data) Scope 1'!$Y$6:$Y$79,'(참고} 시각데이터'!$Q$25,'3-1. (Raw data) Scope 1'!$D$6:$D$79,'(참고} 시각데이터'!$S$9,'3-1. (Raw data) Scope 1'!$AB$6:$AB$79,'(참고} 시각데이터'!U$24) -> 0 | V25: =SUMIFS('3-1. (Raw data) Scope 1'!$AT$6:$AT$79,'3-1. (Raw data) Scope 1'!$Y$6:$Y$79,'(참고} 시각데이터'!$Q$25,'3-1. (Raw data) Scope 1'!$D$6:$D$79,'(참고} 시각데이터'!$S$9,'3-1. (Raw data) Scope 1'!$AB$6:$AB$79,'(참고} 시각데이터'!V$24) -> 0 | W25: =SUMIFS('3-1. (Raw data) Scope 1'!$AT$6:$AT$79,'3-1. (Raw data) Scope 1'!$Y$6:$Y$79,'(참고} 시각데이터'!$Q$25,'3-1. (Raw data) Scope 1'!$D$6:$D$79,'(참고} 시각데이터'!$S$9,'3-1. (Raw data) Scope 1'!$AB$6:$AB$79,'(참고} 시각데이터'!W$24) -> 0 | X25: =SUMIFS('3-1. (Raw data) Scope 1'!$AT$6:$AT$79,'3-1. (Raw data) Scope 1'!$Y$6:$Y$79,'(참고} 시각데이터'!$Q$25,'3-1. (Raw data) Scope 1'!$D$6:$D$79,'(참고} 시각데이터'!$S$9,'3-1. (Raw data) Scope 1'!$AB$6:$AB$79,'(참고} 시각데이터'!X$24) -> 0 | Y25: =SUMIFS('3-1. (Raw data) Scope 1'!$AT$6:$AT$79,'3-1. (Raw data) Scope 1'!$Y$6:$Y$79,'(참고} 시각데이터'!$Q$25,'3-1. (Raw data) Scope 1'!$D$6:$D$79,'(참고} 시각데이터'!$S$9,'3-1. (Raw data) Scope 1'!$AB$6:$AB$79,'(참고} 시각데이터'!Y$24) -> 0 | Z25: =SUMIFS('3-1. (Raw data) Scope 1'!$AT$6:$AT$79,'3-1. (Raw data) Scope 1'!$Y$6:$Y$79,'(참고} 시각데이터'!$Q$25,'3-1. (Raw data) Scope 1'!$D$6:$D$79,'(참고} 시각데이터'!$S$9,'3-1. (Raw data) Scope 1'!$AB$6:$AB$79,'(참고} 시각데이터'!Z$24) -> 0 | AA25: =SUMIFS('3-2. (Raw data) Scope2_Location'!$AY$6:$AY$33,'3-2. (Raw data) Scope2_Location'!$AD$6:$AD$33,'(참고} 시각데이터'!$Q25,'3-2. (Raw data) Scope2_Location'!$D$6:$D$33,'(참고} 시각데이터'!$S$9,'3-2. (Raw data) Scope2_Location'!$AE$6:$AE$33,'(참고} 시각데이터'!$AA$24) -> 0
C26: 2023년 | D26: =SUM(E26:M26) -> 0 | E26: =SUMIFS('3-1. (Raw data) Scope 1'!$AT$6:$AT$79,'3-1. (Raw data) Scope 1'!$Y$6:$Y$79,'(참고} 시각데이터'!$C26,'3-1. (Raw data) Scope 1'!$AB$6:$AB$79,E$24) -> 0 | F26: =SUMIFS('3-1. (Raw data) Scope 1'!$AT$6:$AT$79,'3-1. (Raw data) Scope 1'!$Y$6:$Y$79,'(참고} 시각데이터'!$C26,'3-1. (Raw data) Scope 1'!$AB$6:$AB$79,F$24) -> 0 | G26: =SUMIFS('3-1. (Raw data) Scope 1'!$AT$6:$AT$79,'3-1. (Raw data) Scope 1'!$Y$6:$Y$79,'(참고} 시각데이터'!$C26,'3-1. (Raw data) Scope 1'!$AB$6:$AB$79,G$24) -> 0 | H26: =SUMIFS('3-1. (Raw data) Scope 1'!$AT$6:$AT$79,'3-1. (Raw data) Scope 1'!$Y$6:$Y$79,'(참고} 시각데이터'!$C26,'3-1. (Raw data) Scope 1'!$AB$6:$AB$79,H$24) -> 0 | I26: =SUMIFS('3-1. (Raw data) Scope 1'!$AT$6:$AT$79,'3-1. (Raw data) Scope 1'!$Y$6:$Y$79,'(참고} 시각데이터'!$C26,'3-1. (Raw data) Scope 1'!$AB$6:$AB$79,I$24) -> 0 | J26: =SUMIFS('3-1. (Raw data) Scope 1'!$AT$6:$AT$79,'3-1. (Raw data) Scope 1'!$Y$6:$Y$79,'(참고} 시각데이터'!$C26,'3-1. (Raw data) Scope 1'!$AB$6:$AB$79,J$24) -> 0 | K26: =SUMIFS('3-1. (Raw data) Scope 1'!$AT$6:$AT$79,'3-1. (Raw data) Scope 1'!$Y$6:$Y$79,'(참고} 시각데이터'!$C26,'3-1. (Raw data) Scope 1'!$AB$6:$AB$79,K$24) -> 0 | M26: =SUMIFS('3-2. (Raw data) Scope2_Location'!$AY$6:$AY$33,'3-2. (Raw data) Scope2_Location'!$AD$6:$AD$33,'(참고} 시각데이터'!$C26,'3-2. (Raw data) Scope2_Location'!$AE$6:$AE$33,'(참고} 시각데이터'!$M$24) -> 0 | Q26: 2023년 | R26: =SUM(S26:AA26) -> 0 | S26: =SUMIFS('3-1. (Raw data) Scope 1'!$AT$6:$AT$79,'3-1. (Raw data) Scope 1'!$Y$6:$Y$79,'(참고} 시각데이터'!$Q$25,'3-1. (Raw data) Scope 1'!$D$6:$D$79,'(참고} 시각데이터'!$S$9,'3-1. (Raw data) Scope 1'!$AB$6:$AB$79,S$24) -> 0 | T26: =SUMIFS('3-1. (Raw data) Scope 1'!$AT$6:$AT$79,'3-1. (Raw data) Scope 1'!$Y$6:$Y$79,'(참고} 시각데이터'!$Q$26,'3-1. (Raw data) Scope 1'!$D$6:$D$79,'(참고} 시각데이터'!$S$9,'3-1. (Raw data) Scope 1'!$AB$6:$AB$79,'(참고} 시각데이터'!T$24) -> 0 | U26: =SUMIFS('3-1. (Raw data) Scope 1'!$AT$6:$AT$79,'3-1. (Raw data) Scope 1'!$Y$6:$Y$79,'(참고} 시각데이터'!$Q$26,'3-1. (Raw data) Scope 1'!$D$6:$D$79,'(참고} 시각데이터'!$S$9,'3-1. (Raw data) Scope 1'!$AB$6:$AB$79,'(참고} 시각데이터'!U$24) -> 0 | V26: =SUMIFS('3-1. (Raw data) Scope 1'!$AT$6:$AT$79,'3-1. (Raw data) Scope 1'!$Y$6:$Y$79,'(참고} 시각데이터'!$Q$26,'3-1. (Raw data) Scope 1'!$D$6:$D$79,'(참고} 시각데이터'!$S$9,'3-1. (Raw data) Scope 1'!$AB$6:$AB$79,'(참고} 시각데이터'!V$24) -> 0 | W26: =SUMIFS('3-1. (Raw data) Scope 1'!$AT$6:$AT$79,'3-1. (Raw data) Scope 1'!$Y$6:$Y$79,'(참고} 시각데이터'!$Q$26,'3-1. (Raw data) Scope 1'!$D$6:$D$79,'(참고} 시각데이터'!$S$9,'3-1. (Raw data) Scope 1'!$AB$6:$AB$79,'(참고} 시각데이터'!W$24) -> 0 | X26: =SUMIFS('3-1. (Raw data) Scope 1'!$AT$6:$AT$79,'3-1. (Raw data) Scope 1'!$Y$6:$Y$79,'(참고} 시각데이터'!$Q$26,'3-1. (Raw data) Scope 1'!$D$6:$D$79,'(참고} 시각데이터'!$S$9,'3-1. (Raw data) Scope 1'!$AB$6:$AB$79,'(참고} 시각데이터'!X$24) -> 0 | Y26: =SUMIFS('3-1. (Raw data) Scope 1'!$AT$6:$AT$79,'3-1. (Raw data) Scope 1'!$Y$6:$Y$79,'(참고} 시각데이터'!$Q$25,'3-1. (Raw data) Scope 1'!$D$6:$D$79,'(참고} 시각데이터'!$S$9,'3-1. (Raw data) Scope 1'!$AB$6:$AB$79,'(참고} 시각데이터'!Y$24) -> 0 | Z26: =SUMIFS('3-1. (Raw data) Scope 1'!$AT$6:$AT$79,'3-1. (Raw data) Scope 1'!$Y$6:$Y$79,'(참고} 시각데이터'!$Q$25,'3-1. (Raw data) Scope 1'!$D$6:$D$79,'(참고} 시각데이터'!$S$9,'3-1. (Raw data) Scope 1'!$AB$6:$AB$79,'(참고} 시각데이터'!Z$24) -> 0 | AA26: =SUMIFS('3-2. (Raw data) Scope2_Location'!$AY$6:$AY$33,'3-2. (Raw data) Scope2_Location'!$AD$6:$AD$33,'(참고} 시각데이터'!$Q26,'3-2. (Raw data) Scope2_Location'!$D$6:$D$33,'(참고} 시각데이터'!$S$9,'3-2. (Raw data) Scope2_Location'!$AE$6:$AE$33,'(참고} 시각데이터'!$AA$24) -> 0
C27: 2024년 | D27: =SUM(E27:M27) -> 0 | E27: =SUMIFS('3-1. (Raw data) Scope 1'!$AT$6:$AT$79,'3-1. (Raw data) Scope 1'!$Y$6:$Y$79,'(참고} 시각데이터'!$C27,'3-1. (Raw data) Scope 1'!$AB$6:$AB$79,E$24) -> 0 | F27: =SUMIFS('3-1. (Raw data) Scope 1'!$AT$6:$AT$79,'3-1. (Raw data) Scope 1'!$Y$6:$Y$79,'(참고} 시각데이터'!$C27,'3-1. (Raw data) Scope 1'!$AB$6:$AB$79,F$24) -> 0 | G27: =SUMIFS('3-1. (Raw data) Scope 1'!$AT$6:$AT$79,'3-1. (Raw data) Scope 1'!$Y$6:$Y$79,'(참고} 시각데이터'!$C27,'3-1. (Raw data) Scope 1'!$AB$6:$AB$79,G$24) -> 0 | H27: =SUMIFS('3-1. (Raw data) Scope 1'!$AT$6:$AT$79,'3-1. (Raw data) Scope 1'!$Y$6:$Y$79,'(참고} 시각데이터'!$C27,'3-1. (Raw data) Scope 1'!$AB$6:$AB$79,H$24) -> 0 | I27: =SUMIFS('3-1. (Raw data) Scope 1'!$AT$6:$AT$79,'3-1. (Raw data) Scope 1'!$Y$6:$Y$79,'(참고} 시각데이터'!$C27,'3-1. (Raw data) Scope 1'!$AB$6:$AB$79,I$24) -> 0 | J27: =SUMIFS('3-1. (Raw data) Scope 1'!$AT$6:$AT$79,'3-1. (Raw data) Scope 1'!$Y$6:$Y$79,'(참고} 시각데이터'!$C27,'3-1. (Raw data) Scope 1'!$AB$6:$AB$79,J$24) -> 0 | K27: =SUMIFS('3-1. (Raw data) Scope 1'!$AT$6:$AT$79,'3-1. (Raw data) Scope 1'!$Y$6:$Y$79,'(참고} 시각데이터'!$C27,'3-1. (Raw data) Scope 1'!$AB$6:$AB$79,K$24) -> 0 | M27: =SUMIFS('3-2. (Raw data) Scope2_Location'!$AY$6:$AY$33,'3-2. (Raw data) Scope2_Location'!$AD$6:$AD$33,'(참고} 시각데이터'!$C27,'3-2. (Raw data) Scope2_Location'!$AE$6:$AE$33,'(참고} 시각데이터'!$M$24) -> 0 | Q27: 2024년 | R27: =SUM(S27:AA27) -> 0 | S27: =SUMIFS('3-1. (Raw data) Scope 1'!$AT$6:$AT$79,'3-1. (Raw data) Scope 1'!$Y$6:$Y$79,'(참고} 시각데이터'!$Q$25,'3-1. (Raw data) Scope 1'!$D$6:$D$79,'(참고} 시각데이터'!$S$9,'3-1. (Raw data) Scope 1'!$AB$6:$AB$79,S$24) -> 0 | T27: =SUMIFS('3-1. (Raw data) Scope 1'!$AT$6:$AT$79,'3-1. (Raw data) Scope 1'!$Y$6:$Y$79,'(참고} 시각데이터'!$Q$27,'3-1. (Raw data) Scope 1'!$D$6:$D$79,'(참고} 시각데이터'!$S$9,'3-1. (Raw data) Scope 1'!$AB$6:$AB$79,'(참고} 시각데이터'!T$24) -> 0 | U27: =SUMIFS('3-1. (Raw data) Scope 1'!$AT$6:$AT$79,'3-1. (Raw data) Scope 1'!$Y$6:$Y$79,'(참고} 시각데이터'!$Q$27,'3-1. (Raw data) Scope 1'!$D$6:$D$79,'(참고} 시각데이터'!$S$9,'3-1. (Raw data) Scope 1'!$AB$6:$AB$79,'(참고} 시각데이터'!U$24) -> 0 | V27: =SUMIFS('3-1. (Raw data) Scope 1'!$AT$6:$AT$79,'3-1. (Raw data) Scope 1'!$Y$6:$Y$79,'(참고} 시각데이터'!$Q$27,'3-1. (Raw data) Scope 1'!$D$6:$D$79,'(참고} 시각데이터'!$S$9,'3-1. (Raw data) Scope 1'!$AB$6:$AB$79,'(참고} 시각데이터'!V$24) -> 0 | W27: =SUMIFS('3-1. (Raw data) Scope 1'!$AT$6:$AT$79,'3-1. (Raw data) Scope 1'!$Y$6:$Y$79,'(참고} 시각데이터'!$Q$27,'3-1. (Raw data) Scope 1'!$D$6:$D$79,'(참고} 시각데이터'!$S$9,'3-1. (Raw data) Scope 1'!$AB$6:$AB$79,'(참고} 시각데이터'!W$24) -> 0 | X27: =SUMIFS('3-1. (Raw data) Scope 1'!$AT$6:$AT$79,'3-1. (Raw data) Scope 1'!$Y$6:$Y$79,'(참고} 시각데이터'!$Q$27,'3-1. (Raw data) Scope 1'!$D$6:$D$79,'(참고} 시각데이터'!$S$9,'3-1. (Raw data) Scope 1'!$AB$6:$AB$79,'(참고} 시각데이터'!X$24) -> 0 | Y27: =SUMIFS('3-1. (Raw data) Scope 1'!$AT$6:$AT$79,'3-1. (Raw data) Scope 1'!$Y$6:$Y$79,'(참고} 시각데이터'!$Q$25,'3-1. (Raw data) Scope 1'!$D$6:$D$79,'(참고} 시각데이터'!$S$9,'3-1. (Raw data) Scope 1'!$AB$6:$AB$79,'(참고} 시각데이터'!Y$24) -> 0 | Z27: =SUMIFS('3-1. (Raw data) Scope 1'!$AT$6:$AT$79,'3-1. (Raw data) Scope 1'!$Y$6:$Y$79,'(참고} 시각데이터'!$Q$25,'3-1. (Raw data) Scope 1'!$D$6:$D$79,'(참고} 시각데이터'!$S$9,'3-1. (Raw data) Scope 1'!$AB$6:$AB$79,'(참고} 시각데이터'!Z$24) -> 0 | AA27: =SUMIFS('3-2. (Raw data) Scope2_Location'!$AY$6:$AY$33,'3-2. (Raw data) Scope2_Location'!$AD$6:$AD$33,'(참고} 시각데이터'!$Q27,'3-2. (Raw data) Scope2_Location'!$D$6:$D$33,'(참고} 시각데이터'!$S$9,'3-2. (Raw data) Scope2_Location'!$AE$6:$AE$33,'(참고} 시각데이터'!$AA$24) -> 0
B46: 2022~2024년 Scope 1 온실가스 배출량(tCO2eq)
B48: 호전실업 사업장별 Scope 1 온실가스 배출량 | P48: Scope 1 연료 종류별 온실가스 배출량
Q50: 데이터 수집년도 | S50: 2024년
Q51: 연료 종류 | S51: 자동차용 가솔린(휘발유)
Q53: 합계 | R53: 호전실업 주식회사 | S53: KAHOINDAH CITRAGARMENT | T53: PT. YONGJIN JAVASUKA GARMENT (1공장) | U53: PT. YONGJIN JAVASUKA GARMENT (2,3공장) | V53: PT. HJL INDO NETWORKS | W53: PT.HOGA REKSA GARMENT | X53: 주식회사 엠파파
Q54: =SUM(R54:X54) -> 0 | R54: =SUMIFS('3-1. (Raw data) Scope 1'!$AT$6:$AT$79,'3-1. (Raw data) Scope 1'!$Y$6:$Y$79,'(참고} 시각데이터'!$S$50,'3-1. (Raw data) Scope 1'!$AB$6:$AB$79,'(참고} 시각데이터'!$S$51,'3-1. (Raw data) Scope 1'!$D$6:$D$79,'(참고} 시각데이터'!R$53) -> 0 | S54: =SUMIFS('3-1. (Raw data) Scope 1'!$AT$6:$AT$79,'3-1. (Raw data) Scope 1'!$Y$6:$Y$79,'(참고} 시각데이터'!$S$50,'3-1. (Raw data) Scope 1'!$AB$6:$AB$79,'(참고} 시각데이터'!$S$51,'3-1. (Raw data) Scope 1'!$D$6:$D$79,'(참고} 시각데이터'!S$53) -> 0 | T54: =SUMIFS('3-1. (Raw data) Scope 1'!$AT$6:$AT$79,'3-1. (Raw data) Scope 1'!$Y$6:$Y$79,'(참고} 시각데이터'!$S$50,'3-1. (Raw data) Scope 1'!$AB$6:$AB$79,'(참고} 시각데이터'!$S$51,'3-1. (Raw data) Scope 1'!$D$6:$D$79,'(참고} 시각데이터'!T$53) -> 0 | U54: =SUMIFS('3-1. (Raw data) Scope 1'!$AT$6:$AT$79,'3-1. (Raw data) Scope 1'!$Y$6:$Y$79,'(참고} 시각데이터'!$S$50,'3-1. (Raw data) Scope 1'!$AB$6:$AB$79,'(참고} 시각데이터'!$S$51,'3-1. (Raw data) Scope 1'!$D$6:$D$79,'(참고} 시각데이터'!U$53) -> 0 | V54: =SUMIFS('3-1. (Raw data) Scope 1'!$AT$6:$AT$79,'3-1. (Raw data) Scope 1'!$Y$6:$Y$79,'(참고} 시각데이터'!$S$50,'3-1. (Raw data) Scope 1'!$AB$6:$AB$79,'(참고} 시각데이터'!$S$51,'3-1. (Raw data) Scope 1'!$D$6:$D$79,'(참고} 시각데이터'!V$53) -> 0 | W54: =SUMIFS('3-1. (Raw data) Scope 1'!$AT$6:$AT$79,'3-1. (Raw data) Scope 1'!$Y$6:$Y$79,'(참고} 시각데이터'!$S$50,'3-1. (Raw data) Scope 1'!$AB$6:$AB$79,'(참고} 시각데이터'!$S$51,'3-1. (Raw data) Scope 1'!$D$6:$D$79,'(참고} 시각데이터'!W$53) -> 0 | X54: =SUMIFS('3-1. (Raw data) Scope 1'!$AT$6:$AT$79,'3-1. (Raw data) Scope 1'!$Y$6:$Y$79,'(참고} 시각데이터'!$S$50,'3-1. (Raw data) Scope 1'!$AB$6:$AB$79,'(참고} 시각데이터'!$S$51,'3-1. (Raw data) Scope 1'!$D$6:$D$79,'(참고} 시각데이터'!X$53) -> 0
O55: ▶
B63: 특이사항 | D63: - KAHO 사업장의 배출량이 지속적으로 감소하는 추세
D64: - 엠파파는 Scope 1 배출량 없는 것으로 확인됨
B65: 확인 필요사항 | D65: - YONGJIN 2,3공장의 2023년 Scope 1 배출량 급증 사유 : 수소불화탄소의 사용량 급증으로 보이며, 단위 오기입인지 사용량 증가인지 확인 필요
D66: - 엠파파의 Scope 1 연료 사용여부 확인 필요
B68: 호전실업 사업장별 "S50셀"에서 선택한 Scope 1 연료의 온실가스 배출량 | P68: 호전실업 사업장별 Scope 1 연료 사용량
C70: =Q51 -> 연료 종류 | E70: =S51 -> 자동차용 가솔린(휘발유) | Q70: 사업장명 | S70: PT.HOGA REKSA GARMENT | U70: =Q50 -> 데이터 수집년도 | W70: =S50 -> 2024년 | Y70: =Q51 -> 연료 종류 | AA70: =S51 -> 자동차용 가솔린(휘발유)
C72: =CONCATENATE($E$70," 온실가스 배출량(tCO2eq)") -> 자동차용 가솔린(휘발유) 온실가스 배출량(tCO2eq) | AB72: 단위 : | AC72: =VLOOKUP($S$51,'3-1. (Raw data) Scope 1'!$AB$6:$AQ$79,16,0) -> #N/A
C73: 데이터 수집년도 | D73: 합계 | E73: {=_xlfn.TOROW(_xlfn.UNIQUE(D10:D16))} -> 호전실업 주식회사 | F73: KAHOINDAH CITRAGARMENT | G73: PT. YONGJIN JAVASUKA GARMENT (1공장) | H73: PT. YONGJIN JAVASUKA GARMENT (2,3공장) | I73: PT. HJL INDO NETWORKS | J73: PT.HOGA REKSA GARMENT | K73: 주식회사 엠파파 | Q73: 합계 | R73: 1월 | S73: 2월 | T73: 3월 | U73: 4월 | V73: 5월 | W73: 6월 | X73: 7월 | Y73: 8월 | Z73: 9월 | AA73: 10월 | AB73: 11월 | AC73: 12월
C74: 2022년 | D74: =SUM(E74:K74) -> 0 | E74: =SUMIFS('3-1. (Raw data) Scope 1'!$AT$6:$AT$79,'3-1. (Raw data) Scope 1'!$Y$6:$Y$79,'(참고} 시각데이터'!$C74,'3-1. (Raw data) Scope 1'!$AB$6:$AB$79,$S$51,'3-1. (Raw data) Scope 1'!$D$6:$D$79,'(참고} 시각데이터'!E$73) -> 0 | F74: =SUMIFS('3-1. (Raw data) Scope 1'!$AT$6:$AT$79,'3-1. (Raw data) Scope 1'!$Y$6:$Y$79,'(참고} 시각데이터'!$C74,'3-1. (Raw data) Scope 1'!$AB$6:$AB$79,$S$51,'3-1. (Raw data) Scope 1'!$D$6:$D$79,'(참고} 시각데이터'!F$73) -> 0 | G74: =SUMIFS('3-1. (Raw data) Scope 1'!$AT$6:$AT$79,'3-1. (Raw data) Scope 1'!$Y$6:$Y$79,'(참고} 시각데이터'!$C74,'3-1. (Raw data) Scope 1'!$AB$6:$AB$79,$S$51,'3-1. (Raw data) Scope 1'!$D$6:$D$79,'(참고} 시각데이터'!G$73) -> 0 | H74: =SUMIFS('3-1. (Raw data) Scope 1'!$AT$6:$AT$79,'3-1. (Raw data) Scope 1'!$Y$6:$Y$79,'(참고} 시각데이터'!$C74,'3-1. (Raw data) Scope 1'!$AB$6:$AB$79,$S$51,'3-1. (Raw data) Scope 1'!$D$6:$D$79,'(참고} 시각데이터'!H$73) -> 0 | I74: =SUMIFS('3-1. (Raw data) Scope 1'!$AT$6:$AT$79,'3-1. (Raw data) Scope 1'!$Y$6:$Y$79,'(참고} 시각데이터'!$C74,'3-1. (Raw data) Scope 1'!$AB$6:$AB$79,$S$51,'3-1. (Raw data) Scope 1'!$D$6:$D$79,'(참고} 시각데이터'!I$73) -> 0 | J74: =SUMIFS('3-1. (Raw data) Scope 1'!$AT$6:$AT$79,'3-1. (Raw data) Scope 1'!$Y$6:$Y$79,'(참고} 시각데이터'!$C74,'3-1. (Raw data) Scope 1'!$AB$6:$AB$79,$S$51,'3-1. (Raw data) Scope 1'!$D$6:$D$79,'(참고} 시각데이터'!J$73) -> 0 | K74: =SUMIFS('3-1. (Raw data) Scope 1'!$AT$6:$AT$79,'3-1. (Raw data) Scope 1'!$Y$6:$Y$79,'(참고} 시각데이터'!$C74,'3-1. (Raw data) Scope 1'!$AB$6:$AB$79,$S$51,'3-1. (Raw data) Scope 1'!$D$6:$D$79,'(참고} 시각데이터'!K$73) -> 0 | Q74: =SUM(R74:AC74) -> 0 | R74: =SUMIFS('3-1. (Raw data) Scope 1'!AC$6:AC$79,'3-1. (Raw data) Scope 1'!$Y$6:$Y$79,'(참고} 시각데이터'!$S$50,'3-1. (Raw data) Scope 1'!$AB$6:$AB$79,'(참고} 시각데이터'!$S$51,'3-1. (Raw data) Scope 1'!$D$6:$D$79,$S$70) -> 0 | S74: =SUMIFS('3-1. (Raw data) Scope 1'!AD$6:AD$79,'3-1. (Raw data) Scope 1'!$Y$6:$Y$79,'(참고} 시각데이터'!$S$50,'3-1. (Raw data) Scope 1'!$AB$6:$AB$79,'(참고} 시각데이터'!$S$51,'3-1. (Raw data) Scope 1'!$D$6:$D$79,$S$70) -> 0 | T74: =SUMIFS('3-1. (Raw data) Scope 1'!AE$6:AE$79,'3-1. (Raw data) Scope 1'!$Y$6:$Y$79,'(참고} 시각데이터'!$S$50,'3-1. (Raw data) Scope 1'!$AB$6:$AB$79,'(참고} 시각데이터'!$S$51,'3-1. (Raw data) Scope 1'!$D$6:$D$79,$S$70) -> 0 | U74: =SUMIFS('3-1. (Raw data) Scope 1'!AF$6:AF$79,'3-1. (Raw data) Scope 1'!$Y$6:$Y$79,'(참고} 시각데이터'!$S$50,'3-1. (Raw data) Scope 1'!$AB$6:$AB$79,'(참고} 시각데이터'!$S$51,'3-1. (Raw data) Scope 1'!$D$6:$D$79,$S$70) -> 0 | V74: =SUMIFS('3-1. (Raw data) Scope 1'!AG$6:AG$79,'3-1. (Raw data) Scope 1'!$Y$6:$Y$79,'(참고} 시각데이터'!$S$50,'3-1. (Raw data) Scope 1'!$AB$6:$AB$79,'(참고} 시각데이터'!$S$51,'3-1. (Raw data) Scope 1'!$D$6:$D$79,$S$70) -> 0 | W74: =SUMIFS('3-1. (Raw data) Scope 1'!AH$6:AH$79,'3-1. (Raw data) Scope 1'!$Y$6:$Y$79,'(참고} 시각데이터'!$S$50,'3-1. (Raw data) Scope 1'!$AB$6:$AB$79,'(참고} 시각데이터'!$S$51,'3-1. (Raw data) Scope 1'!$D$6:$D$79,$S$70) -> 0 | X74: =SUMIFS('3-1. (Raw data) Scope 1'!AI$6:AI$79,'3-1. (Raw data) Scope 1'!$Y$6:$Y$79,'(참고} 시각데이터'!$S$50,'3-1. (Raw data) Scope 1'!$AB$6:$AB$79,'(참고} 시각데이터'!$S$51,'3-1. (Raw data) Scope 1'!$D$6:$D$79,$S$70) -> 0 | Y74: =SUMIFS('3-1. (Raw data) Scope 1'!AJ$6:AJ$79,'3-1. (Raw data) Scope 1'!$Y$6:$Y$79,'(참고} 시각데이터'!$S$50,'3-1. (Raw data) Scope 1'!$AB$6:$AB$79,'(참고} 시각데이터'!$S$51,'3-1. (Raw data) Scope 1'!$D$6:$D$79,$S$70) -> 0 | ... AC74: =SUMIFS('3-1. (Raw data) Scope 1'!AN$6:AN$79,'3-1. (Raw data) Scope 1'!$Y$6:$Y$79,'(참고} 시각데이터'!$S$50,'3-1. (Raw data) Scope 1'!$AB$6:$AB$79,'(참고} 시각데이터'!$S$51,'3-1. (Raw data) Scope 1'!$D$6:$D$79,$S$70) -> 0
C75: 2023년 | D75: =SUM(E75:K75) -> 0 | E75: =SUMIFS('3-1. (Raw data) Scope 1'!$AT$6:$AT$79,'3-1. (Raw data) Scope 1'!$Y$6:$Y$79,'(참고} 시각데이터'!$C75,'3-1. (Raw data) Scope 1'!$AB$6:$AB$79,$S$51,'3-1. (Raw data) Scope 1'!$D$6:$D$79,'(참고} 시각데이터'!E$73) -> 0 | F75: =SUMIFS('3-1. (Raw data) Scope 1'!$AT$6:$AT$79,'3-1. (Raw data) Scope 1'!$Y$6:$Y$79,'(참고} 시각데이터'!$C75,'3-1. (Raw data) Scope 1'!$AB$6:$AB$79,$S$51,'3-1. (Raw data) Scope 1'!$D$6:$D$79,'(참고} 시각데이터'!F$73) -> 0 | G75: =SUMIFS('3-1. (Raw data) Scope 1'!$AT$6:$AT$79,'3-1. (Raw data) Scope 1'!$Y$6:$Y$79,'(참고} 시각데이터'!$C75,'3-1. (Raw data) Scope 1'!$AB$6:$AB$79,$S$51,'3-1. (Raw data) Scope 1'!$D$6:$D$79,'(참고} 시각데이터'!G$73) -> 0 | H75: =SUMIFS('3-1. (Raw data) Scope 1'!$AT$6:$AT$79,'3-1. (Raw data) Scope 1'!$Y$6:$Y$79,'(참고} 시각데이터'!$C75,'3-1. (Raw data) Scope 1'!$AB$6:$AB$79,$S$51,'3-1. (Raw data) Scope 1'!$D$6:$D$79,'(참고} 시각데이터'!H$73) -> 0 | I75: =SUMIFS('3-1. (Raw data) Scope 1'!$AT$6:$AT$79,'3-1. (Raw data) Scope 1'!$Y$6:$Y$79,'(참고} 시각데이터'!$C75,'3-1. (Raw data) Scope 1'!$AB$6:$AB$79,$S$51,'3-1. (Raw data) Scope 1'!$D$6:$D$79,'(참고} 시각데이터'!I$73) -> 0 | J75: =SUMIFS('3-1. (Raw data) Scope 1'!$AT$6:$AT$79,'3-1. (Raw data) Scope 1'!$Y$6:$Y$79,'(참고} 시각데이터'!$C75,'3-1. (Raw data) Scope 1'!$AB$6:$AB$79,$S$51,'3-1. (Raw data) Scope 1'!$D$6:$D$79,'(참고} 시각데이터'!J$73) -> 0 | K75: =SUMIFS('3-1. (Raw data) Scope 1'!$AT$6:$AT$79,'3-1. (Raw data) Scope 1'!$Y$6:$Y$79,'(참고} 시각데이터'!$C75,'3-1. (Raw data) Scope 1'!$AB$6:$AB$79,$S$51,'3-1. (Raw data) Scope 1'!$D$6:$D$79,'(참고} 시각데이터'!K$73) -> 0
C76: 2024년 | D76: =SUM(E76:K76) -> 0 | E76: =SUMIFS('3-1. (Raw data) Scope 1'!$AT$6:$AT$79,'3-1. (Raw data) Scope 1'!$Y$6:$Y$79,'(참고} 시각데이터'!$C76,'3-1. (Raw data) Scope 1'!$AB$6:$AB$79,$S$51,'3-1. (Raw data) Scope 1'!$D$6:$D$79,'(참고} 시각데이터'!E$73) -> 0 | F76: =SUMIFS('3-1. (Raw data) Scope 1'!$AT$6:$AT$79,'3-1. (Raw data) Scope 1'!$Y$6:$Y$79,'(참고} 시각데이터'!$C76,'3-1. (Raw data) Scope 1'!$AB$6:$AB$79,$S$51,'3-1. (Raw data) Scope 1'!$D$6:$D$79,'(참고} 시각데이터'!F$73) -> 0 | G76: =SUMIFS('3-1. (Raw data) Scope 1'!$AT$6:$AT$79,'3-1. (Raw data) Scope 1'!$Y$6:$Y$79,'(참고} 시각데이터'!$C76,'3-1. (Raw data) Scope 1'!$AB$6:$AB$79,$S$51,'3-1. (Raw data) Scope 1'!$D$6:$D$79,'(참고} 시각데이터'!G$73) -> 0 | H76: =SUMIFS('3-1. (Raw data) Scope 1'!$AT$6:$AT$79,'3-1. (Raw data) Scope 1'!$Y$6:$Y$79,'(참고} 시각데이터'!$C76,'3-1. (Raw data) Scope 1'!$AB$6:$AB$79,$S$51,'3-1. (Raw data) Scope 1'!$D$6:$D$79,'(참고} 시각데이터'!H$73) -> 0 | I76: =SUMIFS('3-1. (Raw data) Scope 1'!$AT$6:$AT$79,'3-1. (Raw data) Scope 1'!$Y$6:$Y$79,'(참고} 시각데이터'!$C76,'3-1. (Raw data) Scope 1'!$AB$6:$AB$79,$S$51,'3-1. (Raw data) Scope 1'!$D$6:$D$79,'(참고} 시각데이터'!I$73) -> 0 | J76: =SUMIFS('3-1. (Raw data) Scope 1'!$AT$6:$AT$79,'3-1. (Raw data) Scope 1'!$Y$6:$Y$79,'(참고} 시각데이터'!$C76,'3-1. (Raw data) Scope 1'!$AB$6:$AB$79,$S$51,'3-1. (Raw data) Scope 1'!$D$6:$D$79,'(참고} 시각데이터'!J$73) -> 0 | K76: =SUMIFS('3-1. (Raw data) Scope 1'!$AT$6:$AT$79,'3-1. (Raw data) Scope 1'!$Y$6:$Y$79,'(참고} 시각데이터'!$C76,'3-1. (Raw data) Scope 1'!$AB$6:$AB$79,$S$51,'3-1. (Raw data) Scope 1'!$D$6:$D$79,'(참고} 시각데이터'!K$73) -> 0
AC91: 단위 : | AD91: =VLOOKUP($S$51,'3-1. (Raw data) Scope 1'!$AB$6:$AQ$79,16,0) -> #N/A
Q92: 데이터 수집년도 | R92: 합계 | S92: 1월 | T92: 2월 | U92: 3월 | V92: 4월 | W92: 5월 | X92: 6월 | Y92: 7월 | Z92: 8월 | AA92: 9월 | AB92: 10월 | AC92: 11월 | AD92: 12월
Q93: 2022년 | R93: =SUM(S93:AD93) -> 0 | S93: =SUMIFS('3-1. (Raw data) Scope 1'!AC$6:AC$79,'3-1. (Raw data) Scope 1'!$Y$6:$Y$79,'(참고} 시각데이터'!$Q$93,'3-1. (Raw data) Scope 1'!$AB$6:$AB$79,'(참고} 시각데이터'!$S$51,'3-1. (Raw data) Scope 1'!$D$6:$D$79,$S$70) -> 0 | T93: =SUMIFS('3-1. (Raw data) Scope 1'!AD$6:AD$79,'3-1. (Raw data) Scope 1'!$Y$6:$Y$79,'(참고} 시각데이터'!$Q$93,'3-1. (Raw data) Scope 1'!$AB$6:$AB$79,'(참고} 시각데이터'!$S$51,'3-1. (Raw data) Scope 1'!$D$6:$D$79,$S$70) -> 0 | U93: =SUMIFS('3-1. (Raw data) Scope 1'!AE$6:AE$79,'3-1. (Raw data) Scope 1'!$Y$6:$Y$79,'(참고} 시각데이터'!$Q$93,'3-1. (Raw data) Scope 1'!$AB$6:$AB$79,'(참고} 시각데이터'!$S$51,'3-1. (Raw data) Scope 1'!$D$6:$D$79,$S$70) -> 0 | V93: =SUMIFS('3-1. (Raw data) Scope 1'!AF$6:AF$79,'3-1. (Raw data) Scope 1'!$Y$6:$Y$79,'(참고} 시각데이터'!$Q$93,'3-1. (Raw data) Scope 1'!$AB$6:$AB$79,'(참고} 시각데이터'!$S$51,'3-1. (Raw data) Scope 1'!$D$6:$D$79,$S$70) -> 0 | W93: =SUMIFS('3-1. (Raw data) Scope 1'!AG$6:AG$79,'3-1. (Raw data) Scope 1'!$Y$6:$Y$79,'(참고} 시각데이터'!$Q$93,'3-1. (Raw data) Scope 1'!$AB$6:$AB$79,'(참고} 시각데이터'!$S$51,'3-1. (Raw data) Scope 1'!$D$6:$D$79,$S$70) -> 0 | X93: =SUMIFS('3-1. (Raw data) Scope 1'!AH$6:AH$79,'3-1. (Raw data) Scope 1'!$Y$6:$Y$79,'(참고} 시각데이터'!$Q$93,'3-1. (Raw data) Scope 1'!$AB$6:$AB$79,'(참고} 시각데이터'!$S$51,'3-1. (Raw data) Scope 1'!$D$6:$D$79,$S$70) -> 0 | Y93: =SUMIFS('3-1. (Raw data) Scope 1'!AI$6:AI$79,'3-1. (Raw data) Scope 1'!$Y$6:$Y$79,'(참고} 시각데이터'!$Q$93,'3-1. (Raw data) Scope 1'!$AB$6:$AB$79,'(참고} 시각데이터'!$S$51,'3-1. (Raw data) Scope 1'!$D$6:$D$79,$S$70) -> 0 | Z93: =SUMIFS('3-1. (Raw data) Scope 1'!AJ$6:AJ$79,'3-1. (Raw data) Scope 1'!$Y$6:$Y$79,'(참고} 시각데이터'!$Q$93,'3-1. (Raw data) Scope 1'!$AB$6:$AB$79,'(참고} 시각데이터'!$S$51,'3-1. (Raw data) Scope 1'!$D$6:$D$79,$S$70) -> 0 | ... AD93: =SUMIFS('3-1. (Raw data) Scope 1'!AN$6:AN$79,'3-1. (Raw data) Scope 1'!$Y$6:$Y$79,'(참고} 시각데이터'!$Q$93,'3-1. (Raw data) Scope 1'!$AB$6:$AB$79,'(참고} 시각데이터'!$S$51,'3-1. (Raw data) Scope 1'!$D$6:$D$79,$S$70) -> 0
Q94: 2023년 | R94: =SUM(S94:AD94) -> 0 | S94: =SUMIFS('3-1. (Raw data) Scope 1'!AC$6:AC$79,'3-1. (Raw data) Scope 1'!$Y$6:$Y$79,'(참고} 시각데이터'!$Q$94,'3-1. (Raw data) Scope 1'!$AB$6:$AB$79,'(참고} 시각데이터'!$S$51,'3-1. (Raw data) Scope 1'!$D$6:$D$79,$S$70) -> 0 | T94: =SUMIFS('3-1. (Raw data) Scope 1'!AD$6:AD$79,'3-1. (Raw data) Scope 1'!$Y$6:$Y$79,'(참고} 시각데이터'!$Q$94,'3-1. (Raw data) Scope 1'!$AB$6:$AB$79,'(참고} 시각데이터'!$S$51,'3-1. (Raw data) Scope 1'!$D$6:$D$79,$S$70) -> 0 | U94: =SUMIFS('3-1. (Raw data) Scope 1'!AE$6:AE$79,'3-1. (Raw data) Scope 1'!$Y$6:$Y$79,'(참고} 시각데이터'!$Q$94,'3-1. (Raw data) Scope 1'!$AB$6:$AB$79,'(참고} 시각데이터'!$S$51,'3-1. (Raw data) Scope 1'!$D$6:$D$79,$S$70) -> 0 | V94: =SUMIFS('3-1. (Raw data) Scope 1'!AF$6:AF$79,'3-1. (Raw data) Scope 1'!$Y$6:$Y$79,'(참고} 시각데이터'!$Q$94,'3-1. (Raw data) Scope 1'!$AB$6:$AB$79,'(참고} 시각데이터'!$S$51,'3-1. (Raw data) Scope 1'!$D$6:$D$79,$S$70) -> 0 | W94: =SUMIFS('3-1. (Raw data) Scope 1'!AG$6:AG$79,'3-1. (Raw data) Scope 1'!$Y$6:$Y$79,'(참고} 시각데이터'!$Q$94,'3-1. (Raw data) Scope 1'!$AB$6:$AB$79,'(참고} 시각데이터'!$S$51,'3-1. (Raw data) Scope 1'!$D$6:$D$79,$S$70) -> 0 | X94: =SUMIFS('3-1. (Raw data) Scope 1'!AH$6:AH$79,'3-1. (Raw data) Scope 1'!$Y$6:$Y$79,'(참고} 시각데이터'!$Q$94,'3-1. (Raw data) Scope 1'!$AB$6:$AB$79,'(참고} 시각데이터'!$S$51,'3-1. (Raw data) Scope 1'!$D$6:$D$79,$S$70) -> 0 | Y94: =SUMIFS('3-1. (Raw data) Scope 1'!AI$6:AI$79,'3-1. (Raw data) Scope 1'!$Y$6:$Y$79,'(참고} 시각데이터'!$Q$94,'3-1. (Raw data) Scope 1'!$AB$6:$AB$79,'(참고} 시각데이터'!$S$51,'3-1. (Raw data) Scope 1'!$D$6:$D$79,$S$70) -> 0 | Z94: =SUMIFS('3-1. (Raw data) Scope 1'!AJ$6:AJ$79,'3-1. (Raw data) Scope 1'!$Y$6:$Y$79,'(참고} 시각데이터'!$Q$94,'3-1. (Raw data) Scope 1'!$AB$6:$AB$79,'(참고} 시각데이터'!$S$51,'3-1. (Raw data) Scope 1'!$D$6:$D$79,$S$70) -> 0 | ... AD94: =SUMIFS('3-1. (Raw data) Scope 1'!AN$6:AN$79,'3-1. (Raw data) Scope 1'!$Y$6:$Y$79,'(참고} 시각데이터'!$Q$94,'3-1. (Raw data) Scope 1'!$AB$6:$AB$79,'(참고} 시각데이터'!$S$51,'3-1. (Raw data) Scope 1'!$D$6:$D$79,$S$70) -> 0
Q95: 2024년 | R95: =SUM(S95:AD95) -> 0 | S95: =SUMIFS('3-1. (Raw data) Scope 1'!AC$6:AC$79,'3-1. (Raw data) Scope 1'!$Y$6:$Y$79,'(참고} 시각데이터'!$Q$95,'3-1. (Raw data) Scope 1'!$AB$6:$AB$79,'(참고} 시각데이터'!$S$51,'3-1. (Raw data) Scope 1'!$D$6:$D$79,$S$70) -> 0 | T95: =SUMIFS('3-1. (Raw data) Scope 1'!AD$6:AD$79,'3-1. (Raw data) Scope 1'!$Y$6:$Y$79,'(참고} 시각데이터'!$Q$95,'3-1. (Raw data) Scope 1'!$AB$6:$AB$79,'(참고} 시각데이터'!$S$51,'3-1. (Raw data) Scope 1'!$D$6:$D$79,$S$70) -> 0 | U95: =SUMIFS('3-1. (Raw data) Scope 1'!AE$6:AE$79,'3-1. (Raw data) Scope 1'!$Y$6:$Y$79,'(참고} 시각데이터'!$Q$95,'3-1. (Raw data) Scope 1'!$AB$6:$AB$79,'(참고} 시각데이터'!$S$51,'3-1. (Raw data) Scope 1'!$D$6:$D$79,$S$70) -> 0 | V95: =SUMIFS('3-1. (Raw data) Scope 1'!AF$6:AF$79,'3-1. (Raw data) Scope 1'!$Y$6:$Y$79,'(참고} 시각데이터'!$Q$95,'3-1. (Raw data) Scope 1'!$AB$6:$AB$79,'(참고} 시각데이터'!$S$51,'3-1. (Raw data) Scope 1'!$D$6:$D$79,$S$70) -> 0 | W95: =SUMIFS('3-1. (Raw data) Scope 1'!AG$6:AG$79,'3-1. (Raw data) Scope 1'!$Y$6:$Y$79,'(참고} 시각데이터'!$Q$95,'3-1. (Raw data) Scope 1'!$AB$6:$AB$79,'(참고} 시각데이터'!$S$51,'3-1. (Raw data) Scope 1'!$D$6:$D$79,$S$70) -> 0 | X95: =SUMIFS('3-1. (Raw data) Scope 1'!AH$6:AH$79,'3-1. (Raw data) Scope 1'!$Y$6:$Y$79,'(참고} 시각데이터'!$Q$95,'3-1. (Raw data) Scope 1'!$AB$6:$AB$79,'(참고} 시각데이터'!$S$51,'3-1. (Raw data) Scope 1'!$D$6:$D$79,$S$70) -> 0 | Y95: =SUMIFS('3-1. (Raw data) Scope 1'!AI$6:AI$79,'3-1. (Raw data) Scope 1'!$Y$6:$Y$79,'(참고} 시각데이터'!$Q$95,'3-1. (Raw data) Scope 1'!$AB$6:$AB$79,'(참고} 시각데이터'!$S$51,'3-1. (Raw data) Scope 1'!$D$6:$D$79,$S$70) -> 0 | Z95: =SUMIFS('3-1. (Raw data) Scope 1'!AJ$6:AJ$79,'3-1. (Raw data) Scope 1'!$Y$6:$Y$79,'(참고} 시각데이터'!$Q$95,'3-1. (Raw data) Scope 1'!$AB$6:$AB$79,'(참고} 시각데이터'!$S$51,'3-1. (Raw data) Scope 1'!$D$6:$D$79,$S$70) -> 0 | ... AD95: =SUMIFS('3-1. (Raw data) Scope 1'!AN$6:AN$79,'3-1. (Raw data) Scope 1'!$Y$6:$Y$79,'(참고} 시각데이터'!$Q$95,'3-1. (Raw data) Scope 1'!$AB$6:$AB$79,'(참고} 시각데이터'!$S$51,'3-1. (Raw data) Scope 1'!$D$6:$D$79,$S$70) -> 0
B116: 2022~2024년 Scope 2 온실가스 배출량(tCO2eq)
B118: 호전실업 사업장별 Scope 2 온실가스 배출량 | P118: Scope 2 연료 종류별 온실가스 배출량
Q120: 데이터 수집년도 | S120: 2024년
Q121: 연료 종류 | S121: 전력
Q123: 합계 | R123: 호전실업 주식회사 | S123: KAHOINDAH CITRAGARMENT | T123: PT. YONGJIN JAVASUKA GARMENT (1공장) | U123: PT. YONGJIN JAVASUKA GARMENT (2,3공장) | V123: PT. HJL INDO NETWORKS | W123: PT.HOGA REKSA GARMENT | X123: 주식회사 엠파파
Q124: =SUM(R124:X124) -> 0 | R124: =SUMIFS('3-2. (Raw data) Scope2_Location'!$AY$6:$AY$33,'3-2. (Raw data) Scope2_Location'!$AD$6:$AD$33,'(참고} 시각데이터'!$S$120,'3-2. (Raw data) Scope2_Location'!$AE$6:$AE$33,'(참고} 시각데이터'!$S$121,'3-2. (Raw data) Scope2_Location'!$D$6:$D$33,'(참고} 시각데이터'!R$123) -> 0 | S124: =SUMIFS('3-2. (Raw data) Scope2_Location'!$AY$6:$AY$33,'3-2. (Raw data) Scope2_Location'!$AD$6:$AD$33,'(참고} 시각데이터'!$S$120,'3-2. (Raw data) Scope2_Location'!$AE$6:$AE$33,'(참고} 시각데이터'!$S$121,'3-2. (Raw data) Scope2_Location'!$D$6:$D$33,'(참고} 시각데이터'!S$123) -> 0 | T124: =SUMIFS('3-2. (Raw data) Scope2_Location'!$AY$6:$AY$33,'3-2. (Raw data) Scope2_Location'!$AD$6:$AD$33,'(참고} 시각데이터'!$S$120,'3-2. (Raw data) Scope2_Location'!$AE$6:$AE$33,'(참고} 시각데이터'!$S$121,'3-2. (Raw data) Scope2_Location'!$D$6:$D$33,'(참고} 시각데이터'!T$123) -> 0 | U124: =SUMIFS('3-2. (Raw data) Scope2_Location'!$AY$6:$AY$33,'3-2. (Raw data) Scope2_Location'!$AD$6:$AD$33,'(참고} 시각데이터'!$S$120,'3-2. (Raw data) Scope2_Location'!$AE$6:$AE$33,'(참고} 시각데이터'!$S$121,'3-2. (Raw data) Scope2_Location'!$D$6:$D$33,'(참고} 시각데이터'!U$123) -> 0 | V124: =SUMIFS('3-2. (Raw data) Scope2_Location'!$AY$6:$AY$33,'3-2. (Raw data) Scope2_Location'!$AD$6:$AD$33,'(참고} 시각데이터'!$S$120,'3-2. (Raw data) Scope2_Location'!$AE$6:$AE$33,'(참고} 시각데이터'!$S$121,'3-2. (Raw data) Scope2_Location'!$D$6:$D$33,'(참고} 시각데이터'!V$123) -> 0 | W124: =SUMIFS('3-2. (Raw data) Scope2_Location'!$AY$6:$AY$33,'3-2. (Raw data) Scope2_Location'!$AD$6:$AD$33,'(참고} 시각데이터'!$S$120,'3-2. (Raw data) Scope2_Location'!$AE$6:$AE$33,'(참고} 시각데이터'!$S$121,'3-2. (Raw data) Scope2_Location'!$D$6:$D$33,'(참고} 시각데이터'!W$123) -> 0 | X124: =SUMIFS('3-2. (Raw data) Scope2_Location'!$AY$6:$AY$33,'3-2. (Raw data) Scope2_Location'!$AD$6:$AD$33,'(참고} 시각데이터'!$S$120,'3-2. (Raw data) Scope2_Location'!$AE$6:$AE$33,'(참고} 시각데이터'!$S$121,'3-2. (Raw data) Scope2_Location'!$D$6:$D$33,'(참고} 시각데이터'!X$123) -> 0
O126: ▶
B133: 특이사항 및 확인 필요사항 | D133: - HOGA 사업장의 2024년 배출량 급증 사유
D134: - YONGJIN 2,3공장의 배출량이 지속적으로 증가하는 추세
P136: 호전실업 사업장별 Scope 2 전력 구매량
Q138: 사업장명 | S138: PT. YONGJIN JAVASUKA GARMENT (1공장) | U138: =Q120 -> 데이터 수집년도 | W138: =S120 -> 2024년 | Y138: =Q121 -> 연료 종류 | AA138: =S121 -> 전력
AB140: 단위 : | AC140: =VLOOKUP($S$121,'3-2. (Raw data) Scope2_Location'!$AE$6:$AS$33,15,0) -> #N/A
Q141: 합계 | R141: 1월 | S141: 2월 | T141: 3월 | U141: 4월 | V141: 5월 | W141: 6월 | X141: 7월 | Y141: 8월 | Z141: 9월 | AA141: 10월 | AB141: 11월 | AC141: 12월
Q142: =SUM(R142:AC142) -> 0 | R142: =SUMIFS('3-2. (Raw data) Scope2_Location'!AF$6:AF$33,'3-2. (Raw data) Scope2_Location'!$AD$6:$AD$33,'(참고} 시각데이터'!$S$120,'3-2. (Raw data) Scope2_Location'!$AE$6:$AE$33,'(참고} 시각데이터'!$S$121,'3-2. (Raw data) Scope2_Location'!$D$6:$D$33,$S$138) -> 0 | S142: =SUMIFS('3-2. (Raw data) Scope2_Location'!AG$6:AG$33,'3-2. (Raw data) Scope2_Location'!$AD$6:$AD$33,'(참고} 시각데이터'!$S$120,'3-2. (Raw data) Scope2_Location'!$AE$6:$AE$33,'(참고} 시각데이터'!$S$121,'3-2. (Raw data) Scope2_Location'!$D$6:$D$33,$S$138) -> 0 | T142: =SUMIFS('3-2. (Raw data) Scope2_Location'!AH$6:AH$33,'3-2. (Raw data) Scope2_Location'!$AD$6:$AD$33,'(참고} 시각데이터'!$S$120,'3-2. (Raw data) Scope2_Location'!$AE$6:$AE$33,'(참고} 시각데이터'!$S$121,'3-2. (Raw data) Scope2_Location'!$D$6:$D$33,$S$138) -> 0 | U142: =SUMIFS('3-2. (Raw data) Scope2_Location'!AI$6:AI$33,'3-2. (Raw data) Scope2_Location'!$AD$6:$AD$33,'(참고} 시각데이터'!$S$120,'3-2. (Raw data) Scope2_Location'!$AE$6:$AE$33,'(참고} 시각데이터'!$S$121,'3-2. (Raw data) Scope2_Location'!$D$6:$D$33,$S$138) -> 0 | V142: =SUMIFS('3-2. (Raw data) Scope2_Location'!AJ$6:AJ$33,'3-2. (Raw data) Scope2_Location'!$AD$6:$AD$33,'(참고} 시각데이터'!$S$120,'3-2. (Raw data) Scope2_Location'!$AE$6:$AE$33,'(참고} 시각데이터'!$S$121,'3-2. (Raw data) Scope2_Location'!$D$6:$D$33,$S$138) -> 0 | W142: =SUMIFS('3-2. (Raw data) Scope2_Location'!AK$6:AK$33,'3-2. (Raw data) Scope2_Location'!$AD$6:$AD$33,'(참고} 시각데이터'!$S$120,'3-2. (Raw data) Scope2_Location'!$AE$6:$AE$33,'(참고} 시각데이터'!$S$121,'3-2. (Raw data) Scope2_Location'!$D$6:$D$33,$S$138) -> 0 | X142: =SUMIFS('3-2. (Raw data) Scope2_Location'!AL$6:AL$33,'3-2. (Raw data) Scope2_Location'!$AD$6:$AD$33,'(참고} 시각데이터'!$S$120,'3-2. (Raw data) Scope2_Location'!$AE$6:$AE$33,'(참고} 시각데이터'!$S$121,'3-2. (Raw data) Scope2_Location'!$D$6:$D$33,$S$138) -> 0 | Y142: =SUMIFS('3-2. (Raw data) Scope2_Location'!AM$6:AM$33,'3-2. (Raw data) Scope2_Location'!$AD$6:$AD$33,'(참고} 시각데이터'!$S$120,'3-2. (Raw data) Scope2_Location'!$AE$6:$AE$33,'(참고} 시각데이터'!$S$121,'3-2. (Raw data) Scope2_Location'!$D$6:$D$33,$S$138) -> 0 | ... AC142: =SUMIFS('3-2. (Raw data) Scope2_Location'!AQ$6:AQ$33,'3-2. (Raw data) Scope2_Location'!$AD$6:$AD$33,'(참고} 시각데이터'!$S$120,'3-2. (Raw data) Scope2_Location'!$AE$6:$AE$33,'(참고} 시각데이터'!$S$121,'3-2. (Raw data) Scope2_Location'!$D$6:$D$33,$S$138) -> 0
AC160: 단위 : | AD160: =VLOOKUP($S$121,'3-2. (Raw data) Scope2_Location'!$AE$6:$AS$33,15,0) -> #N/A
Q161: 데이터 수집년도 | R161: 합계 | S161: 1월 | T161: 2월 | U161: 3월 | V161: 4월 | W161: 5월 | X161: 6월 | Y161: 7월 | Z161: 8월 | AA161: 9월 | AB161: 10월 | AC161: 11월 | AD161: 12월
Q162: 2022년 | R162: =SUM(S162:AD162) -> 0 | S162: =SUMIFS('3-2. (Raw data) Scope2_Location'!AF$6:AF$33,'3-2. (Raw data) Scope2_Location'!$AD$6:$AD$33,'(참고} 시각데이터'!$Q$162,'3-2. (Raw data) Scope2_Location'!$AE$6:$AE$33,'(참고} 시각데이터'!$S$121,'3-2. (Raw data) Scope2_Location'!$D$6:$D$33,$S$138) -> 0 | T162: =SUMIFS('3-2. (Raw data) Scope2_Location'!AG$6:AG$33,'3-2. (Raw data) Scope2_Location'!$AD$6:$AD$33,'(참고} 시각데이터'!$Q$162,'3-2. (Raw data) Scope2_Location'!$AE$6:$AE$33,'(참고} 시각데이터'!$S$121,'3-2. (Raw data) Scope2_Location'!$D$6:$D$33,$S$138) -> 0 | U162: =SUMIFS('3-2. (Raw data) Scope2_Location'!AH$6:AH$33,'3-2. (Raw data) Scope2_Location'!$AD$6:$AD$33,'(참고} 시각데이터'!$Q$162,'3-2. (Raw data) Scope2_Location'!$AE$6:$AE$33,'(참고} 시각데이터'!$S$121,'3-2. (Raw data) Scope2_Location'!$D$6:$D$33,$S$138) -> 0 | V162: =SUMIFS('3-2. (Raw data) Scope2_Location'!AI$6:AI$33,'3-2. (Raw data) Scope2_Location'!$AD$6:$AD$33,'(참고} 시각데이터'!$Q$162,'3-2. (Raw data) Scope2_Location'!$AE$6:$AE$33,'(참고} 시각데이터'!$S$121,'3-2. (Raw data) Scope2_Location'!$D$6:$D$33,$S$138) -> 0 | W162: =SUMIFS('3-2. (Raw data) Scope2_Location'!AJ$6:AJ$33,'3-2. (Raw data) Scope2_Location'!$AD$6:$AD$33,'(참고} 시각데이터'!$Q$162,'3-2. (Raw data) Scope2_Location'!$AE$6:$AE$33,'(참고} 시각데이터'!$S$121,'3-2. (Raw data) Scope2_Location'!$D$6:$D$33,$S$138) -> 0 | X162: =SUMIFS('3-2. (Raw data) Scope2_Location'!AK$6:AK$33,'3-2. (Raw data) Scope2_Location'!$AD$6:$AD$33,'(참고} 시각데이터'!$Q$162,'3-2. (Raw data) Scope2_Location'!$AE$6:$AE$33,'(참고} 시각데이터'!$S$121,'3-2. (Raw data) Scope2_Location'!$D$6:$D$33,$S$138) -> 0 | Y162: =SUMIFS('3-2. (Raw data) Scope2_Location'!AL$6:AL$33,'3-2. (Raw data) Scope2_Location'!$AD$6:$AD$33,'(참고} 시각데이터'!$Q$162,'3-2. (Raw data) Scope2_Location'!$AE$6:$AE$33,'(참고} 시각데이터'!$S$121,'3-2. (Raw data) Scope2_Location'!$D$6:$D$33,$S$138) -> 0 | Z162: =SUMIFS('3-2. (Raw data) Scope2_Location'!AM$6:AM$33,'3-2. (Raw data) Scope2_Location'!$AD$6:$AD$33,'(참고} 시각데이터'!$Q$162,'3-2. (Raw data) Scope2_Location'!$AE$6:$AE$33,'(참고} 시각데이터'!$S$121,'3-2. (Raw data) Scope2_Location'!$D$6:$D$33,$S$138) -> 0 | ... AD162: =SUMIFS('3-2. (Raw data) Scope2_Location'!AQ$6:AQ$33,'3-2. (Raw data) Scope2_Location'!$AD$6:$AD$33,'(참고} 시각데이터'!$Q$162,'3-2. (Raw data) Scope2_Location'!$AE$6:$AE$33,'(참고} 시각데이터'!$S$121,'3-2. (Raw data) Scope2_Location'!$D$6:$D$33,$S$138) -> 0
Q163: 2023년 | R163: =SUM(S163:AD163) -> 0 | S163: =SUMIFS('3-2. (Raw data) Scope2_Location'!AF$6:AF$33,'3-2. (Raw data) Scope2_Location'!$AD$6:$AD$33,'(참고} 시각데이터'!$Q$163,'3-2. (Raw data) Scope2_Location'!$AE$6:$AE$33,'(참고} 시각데이터'!$S$121,'3-2. (Raw data) Scope2_Location'!$D$6:$D$33,$S$138) -> 0 | T163: =SUMIFS('3-2. (Raw data) Scope2_Location'!AG$6:AG$33,'3-2. (Raw data) Scope2_Location'!$AD$6:$AD$33,'(참고} 시각데이터'!$Q$163,'3-2. (Raw data) Scope2_Location'!$AE$6:$AE$33,'(참고} 시각데이터'!$S$121,'3-2. (Raw data) Scope2_Location'!$D$6:$D$33,$S$138) -> 0 | U163: =SUMIFS('3-2. (Raw data) Scope2_Location'!AH$6:AH$33,'3-2. (Raw data) Scope2_Location'!$AD$6:$AD$33,'(참고} 시각데이터'!$Q$163,'3-2. (Raw data) Scope2_Location'!$AE$6:$AE$33,'(참고} 시각데이터'!$S$121,'3-2. (Raw data) Scope2_Location'!$D$6:$D$33,$S$138) -> 0 | V163: =SUMIFS('3-2. (Raw data) Scope2_Location'!AI$6:AI$33,'3-2. (Raw data) Scope2_Location'!$AD$6:$AD$33,'(참고} 시각데이터'!$Q$163,'3-2. (Raw data) Scope2_Location'!$AE$6:$AE$33,'(참고} 시각데이터'!$S$121,'3-2. (Raw data) Scope2_Location'!$D$6:$D$33,$S$138) -> 0 | W163: =SUMIFS('3-2. (Raw data) Scope2_Location'!AJ$6:AJ$33,'3-2. (Raw data) Scope2_Location'!$AD$6:$AD$33,'(참고} 시각데이터'!$Q$163,'3-2. (Raw data) Scope2_Location'!$AE$6:$AE$33,'(참고} 시각데이터'!$S$121,'3-2. (Raw data) Scope2_Location'!$D$6:$D$33,$S$138) -> 0 | X163: =SUMIFS('3-2. (Raw data) Scope2_Location'!AK$6:AK$33,'3-2. (Raw data) Scope2_Location'!$AD$6:$AD$33,'(참고} 시각데이터'!$Q$163,'3-2. (Raw data) Scope2_Location'!$AE$6:$AE$33,'(참고} 시각데이터'!$S$121,'3-2. (Raw data) Scope2_Location'!$D$6:$D$33,$S$138) -> 0 | Y163: =SUMIFS('3-2. (Raw data) Scope2_Location'!AL$6:AL$33,'3-2. (Raw data) Scope2_Location'!$AD$6:$AD$33,'(참고} 시각데이터'!$Q$163,'3-2. (Raw data) Scope2_Location'!$AE$6:$AE$33,'(참고} 시각데이터'!$S$121,'3-2. (Raw data) Scope2_Location'!$D$6:$D$33,$S$138) -> 0 | Z163: =SUMIFS('3-2. (Raw data) Scope2_Location'!AM$6:AM$33,'3-2. (Raw data) Scope2_Location'!$AD$6:$AD$33,'(참고} 시각데이터'!$Q$163,'3-2. (Raw data) Scope2_Location'!$AE$6:$AE$33,'(참고} 시각데이터'!$S$121,'3-2. (Raw data) Scope2_Location'!$D$6:$D$33,$S$138) -> 0 | ... AD163: =SUMIFS('3-2. (Raw data) Scope2_Location'!AQ$6:AQ$33,'3-2. (Raw data) Scope2_Location'!$AD$6:$AD$33,'(참고} 시각데이터'!$Q$163,'3-2. (Raw data) Scope2_Location'!$AE$6:$AE$33,'(참고} 시각데이터'!$S$121,'3-2. (Raw data) Scope2_Location'!$D$6:$D$33,$S$138) -> 0
Q164: 2024년 | R164: =SUM(S164:AD164) -> 0 | S164: =SUMIFS('3-2. (Raw data) Scope2_Location'!AF$6:AF$33,'3-2. (Raw data) Scope2_Location'!$AD$6:$AD$33,'(참고} 시각데이터'!$Q$164,'3-2. (Raw data) Scope2_Location'!$AE$6:$AE$33,'(참고} 시각데이터'!$S$121,'3-2. (Raw data) Scope2_Location'!$D$6:$D$33,$S$138) -> 0 | T164: =SUMIFS('3-2. (Raw data) Scope2_Location'!AG$6:AG$33,'3-2. (Raw data) Scope2_Location'!$AD$6:$AD$33,'(참고} 시각데이터'!$Q$164,'3-2. (Raw data) Scope2_Location'!$AE$6:$AE$33,'(참고} 시각데이터'!$S$121,'3-2. (Raw data) Scope2_Location'!$D$6:$D$33,$S$138) -> 0 | U164: =SUMIFS('3-2. (Raw data) Scope2_Location'!AH$6:AH$33,'3-2. (Raw data) Scope2_Location'!$AD$6:$AD$33,'(참고} 시각데이터'!$Q$164,'3-2. (Raw data) Scope2_Location'!$AE$6:$AE$33,'(참고} 시각데이터'!$S$121,'3-2. (Raw data) Scope2_Location'!$D$6:$D$33,$S$138) -> 0 | V164: =SUMIFS('3-2. (Raw data) Scope2_Location'!AI$6:AI$33,'3-2. (Raw data) Scope2_Location'!$AD$6:$AD$33,'(참고} 시각데이터'!$Q$164,'3-2. (Raw data) Scope2_Location'!$AE$6:$AE$33,'(참고} 시각데이터'!$S$121,'3-2. (Raw data) Scope2_Location'!$D$6:$D$33,$S$138) -> 0 | W164: =SUMIFS('3-2. (Raw data) Scope2_Location'!AJ$6:AJ$33,'3-2. (Raw data) Scope2_Location'!$AD$6:$AD$33,'(참고} 시각데이터'!$Q$164,'3-2. (Raw data) Scope2_Location'!$AE$6:$AE$33,'(참고} 시각데이터'!$S$121,'3-2. (Raw data) Scope2_Location'!$D$6:$D$33,$S$138) -> 0 | X164: =SUMIFS('3-2. (Raw data) Scope2_Location'!AK$6:AK$33,'3-2. (Raw data) Scope2_Location'!$AD$6:$AD$33,'(참고} 시각데이터'!$Q$164,'3-2. (Raw data) Scope2_Location'!$AE$6:$AE$33,'(참고} 시각데이터'!$S$121,'3-2. (Raw data) Scope2_Location'!$D$6:$D$33,$S$138) -> 0 | Y164: =SUMIFS('3-2. (Raw data) Scope2_Location'!AL$6:AL$33,'3-2. (Raw data) Scope2_Location'!$AD$6:$AD$33,'(참고} 시각데이터'!$Q$164,'3-2. (Raw data) Scope2_Location'!$AE$6:$AE$33,'(참고} 시각데이터'!$S$121,'3-2. (Raw data) Scope2_Location'!$D$6:$D$33,$S$138) -> 0 | Z164: =SUMIFS('3-2. (Raw data) Scope2_Location'!AM$6:AM$33,'3-2. (Raw data) Scope2_Location'!$AD$6:$AD$33,'(참고} 시각데이터'!$Q$164,'3-2. (Raw data) Scope2_Location'!$AE$6:$AE$33,'(참고} 시각데이터'!$S$121,'3-2. (Raw data) Scope2_Location'!$D$6:$D$33,$S$138) -> 0 | ... AD164: =SUMIFS('3-2. (Raw data) Scope2_Location'!AQ$6:AQ$33,'3-2. (Raw data) Scope2_Location'!$AD$6:$AD$33,'(참고} 시각데이터'!$Q$164,'3-2. (Raw data) Scope2_Location'!$AE$6:$AE$33,'(참고} 시각데이터'!$S$121,'3-2. (Raw data) Scope2_Location'!$D$6:$D$33,$S$138) -> 0

Sheet 3-1. (Raw data) Scope 1
AU1: 2022 | AV1: 2023 | AW1: 2024
B2: Fuel/Raw Material Usage and Waste Incineration Activity Data | AS2: =SUM(AU2:AW2) -> 16695.558 | AT2: Total Scope 1 Emissions | AU2: =SUMIF($Y$6:$Y$79,"2022",$AT$6:$AT$79) -> 5807.3723 | AV2: =SUMIF($Y$6:$Y$79,"2023",$AT$6:$AT$79) -> 5472.6179 | AW2: =SUMIF($Y$6:$Y$79,"2024",$AT$6:$AT$79) -> 5415.5677
B4: No | D4: Information of Entity/Facility Site | E4: Fuel Usage Information | Y4: Deloitte_raw data 보완 | AS4: Emissions calculation
B5: No | C5: Name of Entity | D5: Name of Facility | E5: Name of Own facility | F5: Classification of Fuel/Raw Material | G5: Emissions Activities | H5: Detailed Description | I5: Types of fuel | J5: Detailed Description of Fuel/Raw Material | K5: Fuel usage | L5: Jan | M5: Feb | N5: Mar | O5: Apr | P5: May | Q5: Jun | R5: Jul | S5: Aug | T5: Sep | U5: Oct | V5: Nov | W5: Dec | X5: Unit | Y5: Data Collection Year | Z5: Name of Own facility | AA5: Combustion Type | AB5: Types of fuel | AC5: Jan | AD5: Feb | AE5: Mar | AF5: Apr | AG5: May | AH5: Jun | AI5: Jul | AJ5: Aug | AK5: Sep | AL5: Oct | AM5: Nov | AN5: Dec | AO5: For Review | AP5: Fuel usage | AQ5: Unit | AR5: Fuel Consumption (kg) | AS5: Energy Consumption (MJ) | AT5: GHG Emissions (tCO2eq) | AU5: kgCO2 | AV5: kgCH4 | AW5: kgN2O
B6: 1 | C6: HOJEON LIMITED | D6: HOJEON LIMITED Co., Ltd | E6: Vehicle | F6: Fuel | G6: Mobile combustion | H6: 차량 운행 | I6: Automotive gasoline (petrol) | K6: 21.896259 | L6: 1.7928166 | M6: 1.6324213 | N6: 1.6471847 | O6: 2.0347238 | P6: 1.9814761 | Q6: 1.5390641 | R6: 2.0951131 | S6: 2.0864833 | T6: 2.0737647 | U6: 1.5738172 | V6: 1.347481 | W6: 2.0919136 | X6: ㎥ | Y6: 2022 | Z6: =VLOOKUP($E6,'5-2. Emission Facility'!$B$7:$D$16,2,0) -> Vehicle | AA6: =VLOOKUP($Z6,'5-2. Emission Facility'!$C$7:$D$16,2,0) -> Mobile combustion | AB6: =IF($C6="","",IF(VLOOKUP($C6,'1. General Facility Information'!$C$7:$E$13,3,0)="Korea",'3-1. (Raw data) Scope 1'!$I6,INDEX('5-1. Fuel Density'!$B$6:$B$18,MATCH('3-1. (Raw data) Scope 1'!$I6,'5-1. Fuel Density'!$C$6:$C$18,0)))) -> Automotive gasoline (petrol) | AC6: =IF(OR($X6="㎥",$X6="kg"),$L6,"") -> 1.7928166 | AD6: =IF(OR($X6="㎥",$X6="kg"),M6,"") -> 1.6324213 | AE6: =IF(OR($X6="㎥",$X6="kg"),N6,"") -> 1.6471847 | AF6: =IF(OR($X6="㎥",$X6="kg"),O6,"") -> 2.0347238 | AG6: =IF(OR($X6="㎥",$X6="kg"),P6,"") -> 1.9814761 | AH6: =IF(OR($X6="㎥",$X6="kg"),Q6,"") -> 1.5390641 | AI6: =IF(OR($X6="㎥",$X6="kg"),R6,"") -> 2.0951131 | AJ6: =IF(OR($X6="㎥",$X6="kg"),S6,"") -> 2.0864833 | AK6: =IF(OR($X6="㎥",$X6="kg"),T6,"") -> 2.0737647 | ... AN6: =IF(OR($X6="㎥",$X6="kg"),W6,"") -> 2.0919136 | AO6: =IF(SUM(AC6:AN6)-AP6=0,"","X") | AP6: =IF(OR($X6="㎥",$X6="kg"),$K6,"") -> 21.896259 | AQ6: =IF(OR($X6="㎥",$X6="kg"),$X6,"") -> ㎥ | AR6: =IF($C6="","",$AP6*IF($AQ6="㎥",VLOOKUP('3-1. (Raw data) Scope 1'!AQ6,'5-3. Unit Conversion'!$B$5:$J$13,3,FALSE)*VLOOKUP('3-1. (Raw data) Scope 1'!AB6,'5-1. Fuel Density'!$B$6:$D$18,3,FALSE)*1000,IF($AQ6="kg",VLOOKUP('3-1. (Raw data) Scope 1'!AQ6,'5-3. Unit Conversion'!$B$16:$G$21,3,FALSE),0))) -> 16225.128 | AS6: =IFERROR(IF($AB6="","",IF(VLOOKUP($AB6,'5-1. Fuel Density'!$B$6:$G$19,6,0)="Use of other GHGs",0,IF($AB6="Industrial Wastes",$AR6*'5-4. Calorific&Emission factor'!$R$75,$AR6*VLOOKUP($AB6,'5-4. Calorific&Emission factor'!$P$9:$R$74,3,FALSE)))),0) -> 718773.18 | AT6: =IF($AB6="","",IF(OR($AB6="Hydrofluorocarbons(HFCs)",$AB6="ETC"),$AR6*VLOOKUP($J6,'5-4. Calorific&Emission factor'!$B$10:$D$14,3,0)/1000,IF(VLOOKUP($AB6,'5-1. Fuel Density'!$B$6:$G$19,6,0)="Use of other GHGs",$AU6/1000,(($AU6*'5-4. Calorific&Emission factor'!$D$7)+($AV6*'5-4. Calorific&Emission factor'!$D$8)+($AW6*'5-4. Calorific&Emission factor'!$D$9))/1000))) -> 49.986937 | AU6: =IF($AB6="","",IF(VLOOKUP($AB6,'5-1. Fuel Density'!$B$6:$G$19,6,0)="Use of other GHGs",$AR6*VLOOKUP($AB6,'5-4. Calorific&Emission factor'!$O$9:$Y$74,5,FALSE)/1000000,$AS6*VLOOKUP($AB6,'5-4. Calorific&Emission factor'!$P$9:$Y$74,4,FALSE)/1000000)) -> 49810.981 | AV6: =IF($AB6="","",IF(VLOOKUP($AB6,'5-1. Fuel Density'!$B$6:$G$19,6,0)="Use of other GHGs",0,$AS6*VLOOKUP($AB6,'5-4. Calorific&Emission factor'!$P$9:$Y$74,6,FALSE)/1000000)) -> 2.1563195 | AW6: =IF($AB6="","",IF(VLOOKUP($AB6,'5-1. Fuel Density'!$B$6:$G$19,6,0)="Use of other GHGs",0,$AS6*VLOOKUP($AB6,'5-4. Calorific&Emission factor'!$P$9:$Y$74,9,FALSE)/1000000)) -> 0.43126391
B7: 2 | C7: PT. KAHOINDAH CITRAGARMENT | D7: KAHOINDAH CITRAGARMENT | E7: Vehicle | F7: Fuel | G7: Mobile combustion fuels and vehicle | H7: manager-level operational vehicles | I7: Automotive gasoline (petrol) | J7: RON 90 (called Pertalite) | K7: 30.25447 | L7: 2.6508 | M7: 1.94136 | N7: 2.56895 | O7: 2.61433 | P7: 1.80482 | Q7: 2.89079 | R7: 2.89508 | S7: 2.83213 | T7: 2.59511 | U7: 2.39294 | V7: 2.50454 | W7: 2.56362 | X7: ㎥ | Y7: 2022 | Z7: =VLOOKUP($E7,'5-2. Emission Facility'!$B$7:$D$16,2,0) -> Vehicle | AA7: =VLOOKUP($Z7,'5-2. Emission Facility'!$C$7:$D$16,2,0) -> Mobile combustion | AB7: =IF($C7="","",IF(VLOOKUP($C7,'1. General Facility Information'!$C$7:$E$13,3,0)="Korea",'3-1. (Raw data) Scope 1'!$I7,INDEX('5-1. Fuel Density'!$B$6:$B$18,MATCH('3-1. (Raw data) Scope 1'!$I7,'5-1. Fuel Density'!$C$6:$C$18,0)))) -> Automotive gasoline (petrol) | AC7: =IF(OR($X7="㎥",$X7="kg"),$L7,"") -> 2.6508 | AD7: =IF(OR($X7="㎥",$X7="kg"),M7,"") -> 1.94136 | AE7: =IF(OR($X7="㎥",$X7="kg"),N7,"") -> 2.56895 | AF7: =IF(OR($X7="㎥",$X7="kg"),O7,"") -> 2.61433 | AG7: =IF(OR($X7="㎥",$X7="kg"),P7,"") -> 1.80482 | AH7: =IF(OR($X7="㎥",$X7="kg"),Q7,"") -> 2.89079 | AI7: =IF(OR($X7="㎥",$X7="kg"),R7,"") -> 2.89508 | AJ7: =IF(OR($X7="㎥",$X7="kg"),S7,"") -> 2.83213 | AK7: =IF(OR($X7="㎥",$X7="kg"),T7,"") -> 2.59511 | ... AN7: =IF(OR($X7="㎥",$X7="kg"),W7,"") -> 2.56362 | AO7: =IF(SUM(AC7:AN7)-AP7=0,"","X") | AP7: =IF(OR($X7="㎥",$X7="kg"),$K7,"") -> 30.25447 | AQ7: =IF(OR($X7="㎥",$X7="kg"),$X7,"") -> ㎥ | AR7: =IF($C7="","",$AP7*IF($AQ7="㎥",VLOOKUP('3-1. (Raw data) Scope 1'!AQ7,'5-3. Unit Conversion'!$B$5:$J$13,3,FALSE)*VLOOKUP('3-1. (Raw data) Scope 1'!AB7,'5-1. Fuel Density'!$B$6:$D$18,3,FALSE)*1000,IF($AQ7="kg",VLOOKUP('3-1. (Raw data) Scope 1'!AQ7,'5-3. Unit Conversion'!$B$16:$G$21,3,FALSE),0))) -> 22418.562 | AS7: =IFERROR(IF($AB7="","",IF(VLOOKUP($AB7,'5-1. Fuel Density'!$B$6:$G$19,6,0)="Use of other GHGs",0,IF($AB7="Industrial Wastes",$AR7*'5-4. Calorific&Emission factor'!$R$75,$AR7*VLOOKUP($AB7,'5-4. Calorific&Emission factor'!$P$9:$R$74,3,FALSE)))),0) -> 993142.31 | AT7: =IF($AB7="","",IF(OR($AB7="Hydrofluorocarbons(HFCs)",$AB7="ETC"),$AR7*VLOOKUP($J7,'5-4. Calorific&Emission factor'!$B$10:$D$14,3,0)/1000,IF(VLOOKUP($AB7,'5-1. Fuel Density'!$B$6:$G$19,6,0)="Use of other GHGs",$AU7/1000,(($AU7*'5-4. Calorific&Emission factor'!$D$7)+($AV7*'5-4. Calorific&Emission factor'!$D$8)+($AW7*'5-4. Calorific&Emission factor'!$D$9))/1000))) -> 69.067883 | AU7: =IF($AB7="","",IF(VLOOKUP($AB7,'5-1. Fuel Density'!$B$6:$G$19,6,0)="Use of other GHGs",$AR7*VLOOKUP($AB7,'5-4. Calorific&Emission factor'!$O$9:$Y$74,5,FALSE)/1000000,$AS7*VLOOKUP($AB7,'5-4. Calorific&Emission factor'!$P$9:$Y$74,4,FALSE)/1000000)) -> 68824.762 | AV7: =IF($AB7="","",IF(VLOOKUP($AB7,'5-1. Fuel Density'!$B$6:$G$19,6,0)="Use of other GHGs",0,$AS7*VLOOKUP($AB7,'5-4. Calorific&Emission factor'!$P$9:$Y$74,6,FALSE)/1000000)) -> 2.9794269 | AW7: =IF($AB7="","",IF(VLOOKUP($AB7,'5-1. Fuel Density'!$B$6:$G$19,6,0)="Use of other GHGs",0,$AS7*VLOOKUP($AB7,'5-4. Calorific&Emission factor'!$P$9:$Y$74,9,FALSE)/1000000)) -> 0.59588539
B8: 3 | C8: PT. KAHOINDAH CITRAGARMENT | D8: KAHOINDAH CITRAGARMENT | E8: Boiler | F8: Fuel | G8: Stationary combustion fuels and equipment - Solid Fuel | H8: converts boiler combustion to produce heat that is used for steam ironing and fabric relaxation. | I8: Industrial Wastes | J8: Fabric Waste from Production | K8: 323390 | L8: 24973 | M8: 22164 | N8: 29643 | O8: 26953 | P8: 19481 | Q8: 26867 | R8: 24545 | S8: 27071 | T8: 31734 | U8: 29833 | V8: 30496 | W8: 29630 | X8: kg | Y8: 2022 | Z8: =VLOOKUP($E8,'5-2. Emission Facility'!$B$7:$D$16,2,0) -> Boiler | AA8: =VLOOKUP($Z8,'5-2. Emission Facility'!$C$7:$D$16,2,0) -> Stationary Combustion | AB8: =IF($C8="","",IF(VLOOKUP($C8,'1. General Facility Information'!$C$7:$E$13,3,0)="Korea",'3-1. (Raw data) Scope 1'!$I8,INDEX('5-1. Fuel Density'!$B$6:$B$18,MATCH('3-1. (Raw data) Scope 1'!$I8,'5-1. Fuel Density'!$C$6:$C$18,0)))) -> Industrial Wastes | AC8: =IF(OR($X8="㎥",$X8="kg"),$L8,"") -> 24973 | AD8: =IF(OR($X8="㎥",$X8="kg"),M8,"") -> 22164 | AE8: =IF(OR($X8="㎥",$X8="kg"),N8,"") -> 29643 | AF8: =IF(OR($X8="㎥",$X8="kg"),O8,"") -> 26953 | AG8: =IF(OR($X8="㎥",$X8="kg"),P8,"") -> 19481 | AH8: =IF(OR($X8="㎥",$X8="kg"),Q8,"") -> 26867 | AI8: =IF(OR($X8="㎥",$X8="kg"),R8,"") -> 24545 | AJ8: =IF(OR($X8="㎥",$X8="kg"),S8,"") -> 27071 | AK8: =IF(OR($X8="㎥",$X8="kg"),T8,"") -> 31734 | ... AN8: =IF(OR($X8="㎥",$X8="kg"),W8,"") -> 29630 | AO8: =IF(SUM(AC8:AN8)-AP8=0,"","X") | AP8: =IF(OR($X8="㎥",$X8="kg"),$K8,"") -> 323390 | AQ8: =IF(OR($X8="㎥",$X8="kg"),$X8,"") -> kg | AR8: =IF($C8="","",$AP8*IF($AQ8="㎥",VLOOKUP('3-1. (Raw data) Scope 1'!AQ8,'5-3. Unit Conversion'!$B$5:$J$13,3,FALSE)*VLOOKUP('3-1. (Raw data) Scope 1'!AB8,'5-1. Fuel Density'!$B$6:$D$18,3,FALSE)*1000,IF($AQ8="kg",VLOOKUP('3-1. (Raw data) Scope 1'!AQ8,'5-3. Unit Conversion'!$B$16:$G$21,3,FALSE),0))) -> 323390 | AS8: =IFERROR(IF($AB8="","",IF(VLOOKUP($AB8,'5-1. Fuel Density'!$B$6:$G$19,6,0)="Use of other GHGs",0,IF($AB8="Industrial Wastes",$AR8*'5-4. Calorific&Emission factor'!$R$75,$AR8*VLOOKUP($AB8,'5-4. Calorific&Emission factor'!$P$9:$R$74,3,FALSE)))),0) -> 7035936.5 | AT8: =IF($AB8="","",IF(OR($AB8="Hydrofluorocarbons(HFCs)",$AB8="ETC"),$AR8*VLOOKUP($J8,'5-4. Calorific&Emission factor'!$B$10:$D$14,3,0)/1000,IF(VLOOKUP($AB8,'5-1. Fuel Density'!$B$6:$G$19,6,0)="Use of other GHGs",$AU8/1000,(($AU8*'5-4. Calorific&Emission factor'!$D$7)+($AV8*'5-4. Calorific&Emission factor'!$D$8)+($AW8*'5-4. Calorific&Emission factor'!$D$9))/1000))) -> 1019.5213 | AU8: =IF($AB8="","",IF(VLOOKUP($AB8,'5-1. Fuel Density'!$B$6:$G$19,6,0)="Use of other GHGs",$AR8*VLOOKUP($AB8,'5-4. Calorific&Emission factor'!$O$9:$Y$74,5,FALSE)/1000000,$AS8*VLOOKUP($AB8,'5-4. Calorific&Emission factor'!$P$9:$Y$74,4,FALSE)/1000000)) -> 1006138.9 | AV8: =IF($AB8="","",IF(VLOOKUP($AB8,'5-1. Fuel Density'!$B$6:$G$19,6,0)="Use of other GHGs",0,$AS8*VLOOKUP($AB8,'5-4. Calorific&Emission factor'!$P$9:$Y$74,6,FALSE)/1000000)) -> 211.0781 | AW8: =IF($AB8="","",IF(VLOOKUP($AB8,'5-1. Fuel Density'!$B$6:$G$19,6,0)="Use of other GHGs",0,$AS8*VLOOKUP($AB8,'5-4. Calorific&Emission factor'!$P$9:$Y$74,9,FALSE)/1000000)) -> 28.143746
B9: 4 | C9: PT. KAHOINDAH CITRAGARMENT | D9: KAHOINDAH CITRAGARMENT | E9: Forklift | F9: Fuel | G9: Mobile combustion fuels and vehicle | H9: to transport heavy weight item from one location to another location using forklift | I9: Biodiesel | J9: Biosolar (B30) | K9: 1.55 | L9: 0.13 | M9: 0.13 | N9: 0.14 | O9: 0.14 | P9: 0.12 | Q9: 0.12 | R9: 0.13 | S9: 0.14 | T9: 0.14 | U9: 0.12 | V9: 0.12 | W9: 0.12 | X9: ㎥ | Y9: 2022 | Z9: =VLOOKUP($E9,'5-2. Emission Facility'!$B$7:$D$16,2,0) -> Forklift | AA9: =VLOOKUP($Z9,'5-2. Emission Facility'!$C$7:$D$16,2,0) -> Mobile combustion | AB9: =IF($C9="","",IF(VLOOKUP($C9,'1. General Facility Information'!$C$7:$E$13,3,0)="Korea",'3-1. (Raw data) Scope 1'!$I9,INDEX('5-1. Fuel Density'!$B$6:$B$18,MATCH('3-1. (Raw data) Scope 1'!$I9,'5-1. Fuel Density'!$C$6:$C$18,0)))) -> Biodiesel | AC9: =IF(OR($X9="㎥",$X9="kg"),$L9,"") -> 0.13 | AD9: =IF(OR($X9="㎥",$X9="kg"),M9,"") -> 0.13 | AE9: =IF(OR($X9="㎥",$X9="kg"),N9,"") -> 0.14 | AF9: =IF(OR($X9="㎥",$X9="kg"),O9,"") -> 0.14 | AG9: =IF(OR($X9="㎥",$X9="kg"),P9,"") -> 0.12 | AH9: =IF(OR($X9="㎥",$X9="kg"),Q9,"") -> 0.12 | AI9: =IF(OR($X9="㎥",$X9="kg"),R9,"") -> 0.13 | AJ9: =IF(OR($X9="㎥",$X9="kg"),S9,"") -> 0.14 | AK9: =IF(OR($X9="㎥",$X9="kg"),T9,"") -> 0.14 | ... AN9: =IF(OR($X9="㎥",$X9="kg"),W9,"") -> 0.12 | AO9: =IF(SUM(AC9:AN9)-AP9=0,"","X") | AP9: =IF(OR($X9="㎥",$X9="kg"),$K9,"") -> 1.55 | AQ9: =IF(OR($X9="㎥",$X9="kg"),$X9,"") -> ㎥ | AR9: =IF($C9="","",$AP9*IF($AQ9="㎥",VLOOKUP('3-1. (Raw data) Scope 1'!AQ9,'5-3. Unit Conversion'!$B$5:$J$13,3,FALSE)*VLOOKUP('3-1. (Raw data) Scope 1'!AB9,'5-1. Fuel Density'!$B$6:$D$18,3,FALSE)*1000,IF($AQ9="kg",VLOOKUP('3-1. (Raw data) Scope 1'!AQ9,'5-3. Unit Conversion'!$B$16:$G$21,3,FALSE),0))) -> 1309.75 | AS9: =IFERROR(IF($AB9="","",IF(VLOOKUP($AB9,'5-1. Fuel Density'!$B$6:$G$19,6,0)="Use of other GHGs",0,IF($AB9="Industrial Wastes",$AR9*'5-4. Calorific&Emission factor'!$R$75,$AR9*VLOOKUP($AB9,'5-4. Calorific&Emission factor'!$P$9:$R$74,3,FALSE)))),0) -> 35363.25 | AT9: =IF($AB9="","",IF(OR($AB9="Hydrofluorocarbons(HFCs)",$AB9="ETC"),$AR9*VLOOKUP($J9,'5-4. Calorific&Emission factor'!$B$10:$D$14,3,0)/1000,IF(VLOOKUP($AB9,'5-1. Fuel Density'!$B$6:$G$19,6,0)="Use of other GHGs",$AU9/1000,(($AU9*'5-4. Calorific&Emission factor'!$D$7)+($AV9*'5-4. Calorific&Emission factor'!$D$8)+($AW9*'5-4. Calorific&Emission factor'!$D$9))/1000))) -> 2.512375 | AU9: =IF($AB9="","",IF(VLOOKUP($AB9,'5-1. Fuel Density'!$B$6:$G$19,6,0)="Use of other GHGs",$AR9*VLOOKUP($AB9,'5-4. Calorific&Emission factor'!$O$9:$Y$74,5,FALSE)/1000000,$AS9*VLOOKUP($AB9,'5-4. Calorific&Emission factor'!$P$9:$Y$74,4,FALSE)/1000000)) -> 2503.7181 | AV9: =IF($AB9="","",IF(VLOOKUP($AB9,'5-1. Fuel Density'!$B$6:$G$19,6,0)="Use of other GHGs",0,$AS9*VLOOKUP($AB9,'5-4. Calorific&Emission factor'!$P$9:$Y$74,6,FALSE)/1000000)) -> 0.10608975 | AW9: =IF($AB9="","",IF(VLOOKUP($AB9,'5-1. Fuel Density'!$B$6:$G$19,6,0)="Use of other GHGs",0,$AS9*VLOOKUP($AB9,'5-4. Calorific&Emission factor'!$P$9:$Y$74,9,FALSE)/1000000)) -> 0.02121795
